Workbook

Sheet CONTROLE FINANCEIRO - 2025 
A1: CONTROLE FINANCEIRO 2025
A3: DESPESAS FIXAS | B3: JANEIRO | C3: FEVEREIRO | D3: MARÇO | E3: ABRIL | F3: MAIO | G3: JUNHO | H3: JULHO | I3: AGOSTO | J3: SETEMBRO | K3: OUTUBRO | L3: NOVEMBRO | M3: DEZEMBRO
A4: Aluguel | B4: 4450.38 | C4: 4450.38 | D4: 4450.38 | E4: 4450.38 | F4: 4450.38 | G4: 4450.38 | H4: 4450.38 | I4: 4450.38
A5: Condomínio
A6: IPTU
A7: Luz | B7: 140.28 | C7: 140.28 | D7: 140.28 | E7: 140.28 | F7: 140.28 | G7: 140.28 | H7: 140.28 | I7: 140.28
A8: Telefone | B8: 379.98 | C8: 379.98 | D8: 379.98 | E8: 379.98 | F8: 379.98 | G8: 379.98 | H8: 379.98 | I8: 379.98
A9: Celular
A10: Internet | B10: 197.53 | C10: 197.53 | D10: 197.53 | E10: 197.53 | F10: 197.53 | G10: 197.53 | H10: 197.53 | I10: 197.53
A11: T.I.
A12: Contador | B12: 1412 | C12: 1518 | D12: 1518 | E12: 1518 | F12: 1518 | G12: 1518 | H12: 1518 | I12: 1518
A13: Faxineira | B13: =90*8 -> 720 | C13: =90*8 -> 720 | D13: =90*8 -> 720 | E13: =90*8 -> 720 | F13: =90*8 -> 720 | G13: =90*8 -> 720 | H13: =90*8 -> 720 | I13: =90*8 -> 720
A14: Sistema | B14: 285.97 | C14: 285.97 | D14: 285.97 | E14: 285.97 | F14: 285.97 | G14: 285.97 | H14: 285.97 | I14: 285.97
A15: Alarme
A16: CRM | B16: 856.9
A17: Seguro de Equipamentos
A18: Mensalidade Conta Corrente
A19: Mensalidade Cartão de Crédito
A20: Mensalidade Maquineta de Cartão
A21: Anuidade Certificado Digital
A22: Outros
A23: TOTAL | B23: =SUM(B4:B22) -> 8443.04 | C23: =SUM(C4:C22) -> 7692.14 | D23: =SUM(D4:D22) -> 7692.14 | E23: =SUM(E4:E22) -> 7692.14 | F23: =SUM(F4:F22) -> 7692.14 | G23: =SUM(G4:G22) -> 7692.14 | H23: =SUM(H4:H22) -> 7692.14 | I23: =SUM(I4:I22) -> 7692.14 | ... M23: =SUM(M4:M22) -> 0
A25: DESPESAS VARIÁVEIS | B25: JANEIRO | C25: FEVEREIRO | D25: MARÇO | E25: ABRIL | F25: MAIO | G25: JUNHO | H25: JULHO | I25: AGOSTO | J25: SETEMBRO | K25: OUTUBRO | L25: NOVEMBRO | M25: DEZEMBRO
A26: Correios
A27: Consultoria
A28: Lanche para o paciente (Coffee Break)
A29: Higienização de Estofaos
A30: Cursos e treinamentos
A31: Manutenção Ar-condicionado
A32: Manutenção Geral
A33: Locação de Equipamentos (MPT Transporte) | B33: 200 | C33: 200 | D33: 200 | E33: 200 | F33: 200 | G33: 200 | H33: 200 | I33: 200 | J33: 200
A34: Serviço de bordado (Rouparia)
A35: Material de Expediente (Itens para escritório)
A36: Material de Limpeza
A37: Insumos para Copa/ Descartáveis
A38: Insumos Clínica
A39: Equipamentos e informatica
A40: Outros
A41: TOTAL | B41: 10000 | C41: 10000 | D41: 10000 | E41: 10000 | F41: 10000 | G41: 10000 | H41: 10000 | I41: 10000 | J41: 10000 | K41: 10000 | L41: 10000 | M41: 10000
A43: DESPESAS COM PESSOAL | B43: JANEIRO | C43: FEVEREIRO | D43: MARÇO | E43: ABRIL | F43: MAIO | G43: JUNHO | H43: JULHO | I43: AGOSTO | J43: SETEMBRO | K43: OUTUBRO | L43: NOVEMBRO | M43: DEZEMBRO
A44: Uniformes
A45: Serviço de bordado (Uniformes)
A46: Comissão Fixa
A47: Ponto eletrônico
A48: Salários | B48: 300 | C48: 300 | D48: 300 | E48: 300 | F48: 300 | G48: 300 | H48: 400
A49: Prestadores de Serviços
A50: Vale Alimentação | Refeição
A51: Vale Transporte
A52: Plano de Saúde | Odontológico
A53: FGTS | INSS | IRRF/ CONFINS/ PIS / ISS
A54: Verbas de Rescisões
A55: Exames Admissional | Demissional
A56: Retirada Pessoal - Médico
A57: Outros
A58: TOTAL | B58: =SUM(B44:B57) -> 300 | C58: =SUM(C44:C57) -> 300 | D58: =SUM(D44:D57) -> 300 | E58: =SUM(E44:E57) -> 300 | F58: =SUM(F44:F57) -> 300 | G58: =SUM(G44:G57) -> 300 | H58: =SUM(H44:H57) -> 400 | I58: =SUM(I44:I57) -> 0 | ... M58: =SUM(M44:M57) -> 0
A60: DESPESAS COM MARKETING | B60: JANEIRO | C60: FEVEREIRO | D60: MARÇO | E60: ABRIL | F60: MAIO | G60: JUNHO | H60: JULHO | I60: AGOSTO | J60: SETEMBRO | K60: OUTUBRO | L60: NOVEMBRO | M60: DEZEMBRO
A61: Mentoria
A62: Relações Públicas
A63: Agência de Marketing
A64: Gestão de Redes Sociais
A65: Lembranças para o paciente
A66: Mídia
A67: Salario Marketing
A68: Impulsionamento (Google Adwords, Instagram)
A69: Decoração (flores, arranjos, datas comemorativas)
A70: Material Personalizado (sacolas, envelopes, pastas, cartões)
A71: Outros
A72: TOTAL | B72: =SUM(B61:B71) -> 0 | C72: 0 | G72: =SUM(G61:G71) -> 0 | H72: =SUM(H61:H71) -> 0 | I72: =SUM(I61:I71) -> 0 | J72: =SUM(J61:J71) -> 0 | K72: =SUM(K61:K71) -> 0 | L72: =SUM(L61:L71) -> 0 | M72: =SUM(M61:M71) -> 0
A74: RESUMO | B74: JANEIRO | C74: FEVEREIRO | D74: MARÇO | E74: ABRIL | F74: MAIO | G74: JUNHO | H74: JULHO | I74: AGOSTO | J74: SETEMBRO | K74: OUTUBRO | L74: NOVEMBRO | M74: DEZEMBRO | N74: MÉDIA | O74: % DESPESAS | P74: % FATURAMENTO
A75: Despesas Fixas | B75: =B23 -> 8443.04 | C75: =C23 -> 7692.14 | D75: =D23 -> 7692.14 | E75: =E23 -> 7692.14 | F75: =F23 -> 7692.14 | G75: =G23 -> 7692.14 | H75: =H23 -> 7692.14 | I75: =I23 -> 7692.14 | ... M75: =M23 -> 0 | N75: =AVERAGE(B75:D75) -> 7942.44 | O75: =N75/$N$80 -> 0.43538255 | P75: =N75/$P$73 -> #DIV/0!
A76: Despesas Variáveis | B76: =B41 -> 10000 | C76: =C41 -> 10000 | D76: =D41 -> 10000 | E76: =E41 -> 10000 | F76: =F41 -> 10000 | G76: =G41 -> 10000 | H76: =H41 -> 10000 | I76: =I41 -> 10000 | ... M76: =M41 -> 10000 | N76: =AVERAGE(B76:D76) -> 10000 | O76: =N76/$N$80 -> 0.54817228 | P76: =N76/$P$73 -> #DIV/0!
A77: Despesas com Pessoal | B77: =B58 -> 300 | C77: =C58 -> 300 | D77: =D58 -> 300 | E77: =E58 -> 300 | F77: =F58 -> 300 | G77: =G58 -> 300 | H77: =H58 -> 400 | I77: =I58 -> 0 | ... M77: =M58 -> 0 | N77: =AVERAGE(B77:D77) -> 300 | O77: =N77/$N$80 -> 0.016445169 | P77: =N77/$P$73 -> #DIV/0!
A78: Despesas com Marketing | B78: =B72 -> 0 | C78: =C72 -> 0 | D78: =D72 | E78: =E72 | F78: =F72 | G78: =G72 -> 0 | H78: =H72 -> 0 | I78: =I72 -> 0 | ... M78: =M72 -> 0 | N78: =AVERAGE(B78:D78) -> 0 | O78: =N78/$N$80 -> 0 | P78: =N78/$P$73 -> #DIV/0!
A79: Reforma (Xmi/0.5%a.m./5a) | O79: =N79/$N$80 -> 0 | P79: =N79/$P$73 -> #DIV/0!
A80: Custo Total | B80: 0 | C80: =SUM(C75:C79) -> 17992.14 | D80: =SUM(D75:D79) -> 17992.14 | E80: =SUM(E75:E79) -> 17992.14 | F80: =SUM(F75:F79) -> 17992.14 | G80: =SUM(G75:G79) -> 17992.14 | H80: =SUM(H75:H79) -> 18092.14 | I80: =SUM(I75:I79) -> 17692.14 | J80: =SUM(J75:J79) -> 10000 | ... O80: =SUM(O75:O79) -> 1 | P80: =N80/$P$73 -> #DIV/0!
A81: Horas trabalhadas no mês | B81: 100 | C81: 100 | D81: 100 | E81: 100 | F81: 100 | G81: 100 | H81: 100 | I81: 100 | J81: 100 | K81: 100 | L81: 100 | M81: 100 | N81: 200
A82: Taxa de Sala - hora | B82: =B80/B81 -> 0 | C82: =C80/C81 -> 179.9214 | D82: =D80/D81 -> 179.9214 | E82: =E80/E81 -> 179.9214 | F82: =F80/F81 -> 179.9214 | G82: =G80/G81 -> 179.9214 | H82: =H80/H81 -> 180.9214 | I82: =I80/I81 -> 176.9214 | ... N82: =N80/N81 -> 91.2122
A83: Taxa de Sala - minuto | B83: =B82/60 -> 0 | C83: =C82/60 -> 2.99869 | D83: =D82/60 -> 2.99869 | E83: =E82/60 -> 2.99869 | F83: =F82/60 -> 2.99869 | G83: =G82/60 -> 2.99869 | H83: =H82/60 -> 3.0153567 | I83: =I82/60 -> 2.94869 | ... N83: =N82/60 -> 1.5202033
A84: Custo Clínica - dia | B84: =B80/20 -> 0 | C84: =C80/20 -> 899.607 | D84: =D80/20 -> 899.607 | E84: =E80/20 -> 899.607 | F84: =F80/20 -> 899.607 | G84: =G80/20 -> 899.607 | H84: =H80/20 -> 904.607 | I84: =I80/20 -> 884.607 | ... N84: =N80/20 -> 912.122
A85: Custo Clínica - semana | B85: =B80/4 -> 0 | C85: =C80/4 -> 4498.035 | D85: =D80/4 -> 4498.035 | E85: =E80/4 -> 4498.035 | F85: =F80/4 -> 4498.035 | G85: =G80/4 -> 4498.035 | H85: =H80/4 -> 4523.035 | I85: =I80/4 -> 4423.035 | ... N85: =N80/4 -> 4560.61

Sheet PRECIFICAÇÃO - SUGESTÃO
A1: CATEGORIA | B1: PROCEDIMENTOS | C1: OBS E SUGESTAO | D1: DURAÇÃO | E1: UNIDADES | F1: PRODUTOS | G1: TAXA DE SALA | H1: TOTAL - CUSTO OPERACIONAL | I1: PREÇO- TABELA | J1: CARTÃO DE CRÉDITO | K1: IMPOSTOS | L1: COMISSÃO | M1: LUCRO | O1: Quantidade | P1: Tempo | Q1: Faturamento | R1: Produto/ Material | S1: Taxa de Sala | T1: Imposto + Cartão | U1: Bonificação | V1: Lucro
A2: 30101077 | B2: BIÓPSIA DE PELE(TBM CARE PLUS) | D2: 30 | E2: 1 | G2: =D2*12.5 -> 375 | H2: =F2+G2 -> 375 | I2: 0 | J2: =I2*5% -> 0 | K2: =I2*16.5% -> 0 | L2: =H2*3% -> 11.25 | M2: =I2-H2-J2-K2-L2 -> -386.25 | N2: =M2/I2 -> #DIV/0! | P2: =O2*(D2/60) -> 0 | Q2: =O2*I2 -> 0 | R2: =O2*F2 -> 0 | S2: =O2*G2 -> 0 | T2: =O2*(J2+K2) -> 0 | U2: =O2*L2 -> 0 | V2: =Q2-R2-S2-T2-U2 -> 0
A3: 30101018 | B3: ABRASÃO CIRURGICA(TBM CARE PLUS) | D3: 30 | E3: 1 | G3: =D3*12.5 -> 375 | H3: =F3+G3 -> 375 | I3: 0 | J3: =I3*5% -> 0 | K3: =I3*16.5% -> 0 | L3: =H3*3% -> 11.25 | M3: =I3-H3-J3-K3-L3 -> -386.25 | N3: =M3/I3 -> #DIV/0! | P3: =O3*(D3/60) -> 0 | Q3: =O3*I3 -> 0 | R3: =O3*(F3+G3) -> 0 | S3: =O3*H3 -> 0 | T3: =O3*(J3+K3) -> 0 | U3: =O3*L3 -> 0 | V3: =Q3-R3-S3-T3-U3 -> 0
B4: AVALIAÇÃO | D4: 30 | E4: 1 | G4: =D4*12.5 -> 375 | H4: =F4+G4 -> 375 | I4: 360 | J4: =I4*5% -> 18 | K4: =I4*16.5% -> 59.4 | L4: =H4*3% -> 11.25 | M4: =I4-H4-J4-K4-L4 -> -103.65 | N4: =M4/I4 -> -0.28791667 | P4: =O4*(D4/60) -> 0 | Q4: =O4*I4 -> 0 | R4: =O4*(F4+G4) -> 0 | S4: =O4*H4 -> 0 | T4: =O4*(J4+K4) -> 0 | U4: =O4*L4 -> 0 | V4: =Q4-R4-S4-T4-U4 -> 0
B5: AVALIAÇÃO ONLINE | D5: 15 | E5: 1 | G5: =D5*12.5 -> 187.5 | H5: =F5+G5 -> 187.5 | I5: 0 | J5: =I5*5% -> 0 | K5: =I5*16.5% -> 0 | L5: =H5*3% -> 5.625 | M5: =I5-H5-J5-K5-L5 -> -193.125 | N5: =M5/I5 -> #DIV/0! | P5: =O5*(D5/60) -> 0 | Q5: =O5*I5 -> 0 | R5: =O5*(F5+G5) -> 0 | S5: =O5*H5 -> 0 | T5: =O5*(J5+K5) -> 0 | U5: =O5*L5 -> 0 | V5: =Q5-R5-S5-T5-U5 -> 0
B6: BIOESTIMULADOR DIAMOND - 1 AMPOLA | D6: 30 | E6: 1 | F6: 509.9 | G6: =D6*12.5 -> 375 | H6: =F6+G6 -> 884.9 | I6: 2300 | J6: =I6*5% -> 115 | K6: =I6*16.5% -> 379.5 | L6: =H6*3% -> 26.547 | M6: =I6-H6-J6-K6-L6 -> 894.053 | N6: =M6/I6 -> 0.3887187 | P6: =O6*(D6/60) -> 0 | Q6: =O6*I6 -> 0 | R6: =O6*(F6+G6) -> 0 | S6: =O6*H6 -> 0 | T6: =O6*(J6+K6) -> 0 | U6: =O6*L6 -> 0 | V6: =Q6-R6-S6-T6-U6 -> 0
B7: BIOESTIMULADOR RADIESSE - 1 AMPOLA | D7: 30 | E7: 1 | F7: 848 | G7: =D7*12.5 -> 375 | H7: =F7+G7 -> 1223 | I7: 2700 | J7: =I7*5% -> 135 | K7: =I7*16.5% -> 445.5 | L7: =H7*3% -> 36.69 | M7: =I7-H7-J7-K7-L7 -> 859.81 | N7: =M7/I7 -> 0.31844815 | P7: =O7*(D7/60) -> 0 | Q7: =O7*I7 -> 0 | R7: =O7*(F7+G7) -> 0 | S7: =O7*H7 -> 0 | T7: =O7*(J7+K7) -> 0 | U7: =O7*L7 -> 0 | V7: =Q7-R7-S7-T7-U7 -> 0
B8: BIOESTIMULADOR SCULPTRA - 1 AMPOLA | D8: 30 | E8: 1 | F8: 1106.7 | G8: =D8*12.5 -> 375 | H8: =F8+G8 -> 1481.7 | I8: 3300 | J8: =I8*5% -> 165 | K8: =I8*16.5% -> 544.5 | L8: =H8*3% -> 44.451 | M8: =I8-H8-J8-K8-L8 -> 1064.349 | N8: =M8/I8 -> 0.32253 | P8: =O8*(D8/60) -> 0 | Q8: =O8*I8 -> 0 | R8: =O8*(F8+G8) -> 0 | S8: =O8*H8 -> 0 | T8: =O8*(J8+K8) -> 0 | U8: =O8*L8 -> 0 | V8: =Q8-R8-S8-T8-U8 -> 0
B9: BIOESTIMULADOR ELLEVA - 1 AMPOLA | D9: 30 | E9: 1 | F9: 964.9 | G9: =D9*12.5 -> 375 | H9: =F9+G9 -> 1339.9 | I9: 3300 | J9: =I9*5% -> 165 | K9: =I9*16.5% -> 544.5 | L9: =H9*3% -> 40.197 | M9: =I9-H9-J9-K9-L9 -> 1210.403 | N9: =M9/I9 -> 0.36678879 | P9: =O9*(D9/60) -> 0 | Q9: =O9*I9 -> 0 | R9: =O9*(F9+G9) -> 0 | S9: =O9*H9 -> 0 | T9: =O9*(J9+K9) -> 0 | U9: =O9*L9 -> 0 | V9: =Q9-R9-S9-T9-U9 -> 0
B10: BIOIMPEDANCIA | D10: 15 | E10: 1 | G10: =D10*12.5 -> 187.5 | H10: =F10+G10 -> 187.5 | I10: 55 | J10: =I10*5% -> 2.75 | K10: =I10*16.5% -> 9.075 | L10: =H10*3% -> 5.625 | M10: =I10-H10-J10-K10-L10 -> -149.95 | N10: =M10/I10 -> -2.7263636 | P10: =O10*(D10/60) -> 0 | Q10: =O10*I10 -> 0 | R10: =O10*(F10+G10) -> 0 | S10: =O10*H10 -> 0 | T10: =O10*(J10+K10) -> 0 | U10: =O10*L10 -> 0 | V10: =Q10-R10-S10-T10-U10 -> 0
B11: BLEFAROPLASTIA - SUPERIOR OU INFERIOR | D11: 120 | E11: 1 | G11: =D11*12.5 -> 1500 | H11: =F11+G11 -> 1500 | I11: 7000 | J11: =I11*5% -> 350 | K11: =I11*16.5% -> 1155 | L11: =H11*3% -> 45 | M11: =I11-H11-J11-K11-L11 -> 3950 | N11: =M11/I11 -> 0.56428571 | P11: =O11*(D11/60) -> 0 | Q11: =O11*I11 -> 0 | R11: =O11*(F11+G11) -> 0 | S11: =O11*H11 -> 0 | T11: =O11*(J11+K11) -> 0 | U11: =O11*L11 -> 0 | V11: =Q11-R11-S11-T11-U11 -> 0
B12: BLEFAROPLASTIA - TOTAL | D12: 60 | E12: 1 | G12: =D12*12.5 -> 750 | H12: =F12+G12 -> 750 | I12: 7000 | J12: =I12*5% -> 350 | K12: =I12*16.5% -> 1155 | L12: =H12*3% -> 22.5 | M12: =I12-H12-J12-K12-L12 -> 4722.5 | N12: =M12/I12 -> 0.67464286 | P12: =O12*(D12/60) -> 0 | Q12: =O12*I12 -> 0 | R12: =O12*(F12+G12) -> 0 | S12: =O12*H12 -> 0 | T12: =O12*(J12+K12) -> 0 | U12: =O12*L12 -> 0 | V12: =Q12-R12-S12-T12-U12 -> 0
A13: 30101107 | B13: CAUTERIZAÇÃO QUÍMICA - ATÉ 5 LESÕES(TBM CARE PLUS) | D13: 30 | E13: 1 | G13: =D13*12.5 -> 375 | H13: =F13+G13 -> 375 | I13: 850 | J13: =I13*5% -> 42.5 | K13: =I13*16.5% -> 140.25 | L13: =H13*3% -> 11.25 | M13: =I13-H13-J13-K13-L13 -> 281 | N13: =M13/I13 -> 0.33058824 | P13: =O13*(D13/60) -> 0 | Q13: =O13*I13 -> 0 | R13: =O13*(F13+G13) -> 0 | S13: =O13*H13 -> 0 | T13: =O13*(J13+K13) -> 0 | U13: =O13*L13 -> 0 | V13: =Q13-R13-S13-T13-U13 -> 0
B14: CONSULTA DERMATOLOGICA - RJ | D14: 60 | E14: 1 | G14: =D14*12.5 -> 750 | H14: =F14+G14 -> 750 | I14: 680 | J14: =I14*5% -> 34 | K14: =I14*16.5% -> 112.2 | L14: =H14*3% -> 22.5 | M14: =I14-H14-J14-K14-L14 -> -238.7 | N14: =M14/I14 -> -0.35102941 | P14: =O14*(D14/60) -> 0 | Q14: =O14*I14 -> 0 | R14: =O14*(F14+G14) -> 0 | S14: =O14*H14 -> 0 | T14: =O14*(J14+K14) -> 0 | U14: =O14*L14 -> 0 | V14: =Q14-R14-S14-T14-U14 -> 0
B15: CONSULTA DERMATOLÓGICA - SP | D15: 60 | E15: 1 | G15: =D15*12.5 -> 750 | H15: =F15+G15 -> 750 | I15: 720 | J15: =I15*5% -> 36 | K15: =I15*16.5% -> 118.8 | L15: =H15*3% -> 22.5 | M15: =I15-H15-J15-K15-L15 -> -207.3 | N15: =M15/I15 -> -0.28791667 | P15: =O15*(D15/60) -> 0 | Q15: =O15*I15 -> 0 | R15: =O15*(F15+G15) -> 0 | S15: =O15*H15 -> 0 | T15: =O15*(J15+K15) -> 0 | U15: =O15*L15 -> 0 | V15: =Q15-R15-S15-T15-U15 -> 0
B16: CONSULTA DR. VICTOR ROMERO - TRICOLOGISTA | D16: 60 | E16: 1 | G16: =D16*12.5 -> 750 | H16: =F16+G16 -> 750 | I16: 720 | J16: =I16*5% -> 36 | K16: =I16*16.5% -> 118.8 | L16: =H16*3% -> 22.5 | M16: =I16-H16-J16-K16-L16 -> -207.3 | N16: =M16/I16 -> -0.28791667 | P16: =O16*(D16/60) -> 0 | Q16: =O16*I16 -> 0 | R16: =O16*(F16+G16) -> 0 | S16: =O16*H16 -> 0 | T16: =O16*(J16+K16) -> 0 | U16: =O16*L16 -> 0 | V16: =Q16-R16-S16-T16-U16 -> 0
B17: CONSULTA ENDOCRINOLOGIA | D17: 30 | E17: 1 | G17: =D17*12.5 -> 375 | H17: =F17+G17 -> 375 | I17: 650 | J17: =I17*5% -> 32.5 | K17: =I17*16.5% -> 107.25 | L17: =H17*3% -> 11.25 | M17: =I17-H17-J17-K17-L17 -> 124 | N17: =M17/I17 -> 0.19076923 | P17: =O17*(D17/60) -> 0 | Q17: =O17*I17 -> 0 | R17: =O17*(F17+G17) -> 0 | S17: =O17*H17 -> 0 | T17: =O17*(J17+K17) -> 0 | U17: =O17*L17 -> 0 | V17: =Q17-R17-S17-T17-U17 -> 0
B18: CONSULTA NUTRIÇÃO | D18: 60 | E18: 1 | G18: =D18*12.5 -> 750 | H18: =F18+G18 -> 750 | I18: 450 | J18: =I18*5% -> 22.5 | K18: =I18*16.5% -> 74.25 | L18: =H18*3% -> 22.5 | M18: =I18-H18-J18-K18-L18 -> -419.25 | N18: =M18/I18 -> -0.93166667 | P18: =O18*(D18/60) -> 0 | Q18: =O18*I18 -> 0 | R18: =O18*(F18+G18) -> 0 | S18: =O18*H18 -> 0 | T18: =O18*(J18+K18) -> 0 | U18: =O18*L18 -> 0 | V18: =Q18-R18-S18-T18-U18 -> 0
B19: COOLSCULPTING CORPORAL ADVANTAGE - 1 CICLO | D19: 35 | E19: 1 | F19: 506.29 | G19: =D19*12.5 -> 437.5 | H19: =F19+G19 -> 943.79 | I19: 2500 | J19: =I19*5% -> 125 | K19: =I19*16.5% -> 412.5 | L19: =H19*3% -> 28.3137 | M19: =I19-H19-J19-K19-L19 -> 990.3963 | N19: =M19/I19 -> 0.39615852 | P19: =O19*(D19/60) -> 0 | Q19: =O19*I19 -> 0 | R19: =O19*(F19+G19) -> 0 | S19: =O19*H19 -> 0 | T19: =O19*(J19+K19) -> 0 | U19: =O19*L19 -> 0 | V19: =Q19-R19-S19-T19-U19 -> 0
B20: COOLSCULPTING FACIAL MINI - 1 CICLO | D20: 45 | E20: 1 | F20: 1222.29 | G20: =D20*12.5 -> 562.5 | H20: =F20+G20 -> 1784.79 | I20: 2700 | J20: =I20*5% -> 135 | K20: =I20*16.5% -> 445.5 | L20: =H20*3% -> 53.5437 | M20: =I20-H20-J20-K20-L20 -> 281.1663 | N20: =M20/I20 -> 0.10413567 | P20: =O20*(D20/60) -> 0 | Q20: =O20*I20 -> 0 | R20: =O20*(F20+G20) -> 0 | S20: =O20*H20 -> 0 | T20: =O20*(J20+K20) -> 0 | U20: =O20*L20 -> 0 | V20: =Q20-R20-S20-T20-U20 -> 0
B21: COOLSCUPTING CORPORAL PLUS - 1 CICLO | D21: 45 | E21: 1 | F21: 559.79 | G21: =D21*12.5 -> 562.5 | H21: =F21+G21 -> 1122.29 | I21: 2500 | J21: =I21*5% -> 125 | K21: =I21*16.5% -> 412.5 | L21: =H21*3% -> 33.6687 | M21: =I21-H21-J21-K21-L21 -> 806.5413 | N21: =M21/I21 -> 0.32261652 | P21: =O21*(D21/60) -> 0 | Q21: =O21*I21 -> 0 | R21: =O21*(F21+G21) -> 0 | S21: =O21*H21 -> 0 | T21: =O21*(J21+K21) -> 0 | U21: =O21*L21 -> 0 | V21: =Q21-R21-S21-T21-U21 -> 0
B22: COOLSCUPTING CORPORAL SMOOTH - 1 CICLO | D22: 75 | E22: 1 | F22: 284.77 | G22: =D22*12.5 -> 937.5 | H22: =F22+G22 -> 1222.27 | I22: 2500 | J22: =I22*5% -> 125 | K22: =I22*16.5% -> 412.5 | L22: =H22*3% -> 36.6681 | M22: =I22-H22-J22-K22-L22 -> 703.5619 | N22: =M22/I22 -> 0.28142476 | P22: =O22*(D22/60) -> 0 | Q22: =O22*I22 -> 0 | R22: =O22*(F22+G22) -> 0 | S22: =O22*H22 -> 0 | T22: =O22*(J22+K22) -> 0 | U22: =O22*L22 -> 0 | V22: =Q22-R22-S22-T22-U22 -> 0
B23: CORREÇÃO CIRURGICA CICATRIZ ACNE | D23: 40 | E23: 1 | G23: =D23*12.5 -> 500 | H23: =F23+G23 -> 500 | I23: 1200 | J23: =I23*5% -> 60 | K23: =I23*16.5% -> 198 | L23: =H23*3% -> 15 | M23: =I23-H23-J23-K23-L23 -> 427 | N23: =M23/I23 -> 0.35583333 | P23: =O23*(D23/60) -> 0 | Q23: =O23*I23 -> 0 | R23: =O23*(F23+G23) -> 0 | S23: =O23*H23 -> 0 | T23: =O23*(J23+K23) -> 0 | U23: =O23*L23 -> 0 | V23: =Q23-R23-S23-T23-U23 -> 0
B24: CORREÇÃO DE RINOFIMA | D24: 90 | E24: 1 | G24: =D24*12.5 -> 1125 | H24: =F24+G24 -> 1125 | I24: 3500 | J24: =I24*5% -> 175 | K24: =I24*16.5% -> 577.5 | L24: =H24*3% -> 33.75 | M24: =I24-H24-J24-K24-L24 -> 1588.75 | N24: =M24/I24 -> 0.45392857 | P24: =O24*(D24/60) -> 0 | Q24: =O24*I24 -> 0 | R24: =O24*(F24+G24) -> 0 | S24: =O24*H24 -> 0 | T24: =O24*(J24+K24) -> 0 | U24: =O24*L24 -> 0 | V24: =Q24-R24-S24-T24-U24 -> 0
B25: CRIOCIRURGIA DE NEOPLASIAS CUTANEAS - NITROGENIO LIQUIDO(TBM CARE PLUS) | D25: 20 | E25: 1 | G25: =D25*12.5 -> 250 | H25: =F25+G25 -> 250 | I25: 750 | J25: =I25*5% -> 37.5 | K25: =I25*16.5% -> 123.75 | L25: =H25*3% -> 7.5 | M25: =I25-H25-J25-K25-L25 -> 331.25 | N25: =M25/I25 -> 0.44166667 | P25: =O25*(D25/60) -> 0 | Q25: =O25*I25 -> 0 | R25: =O25*(F25+G25) -> 0 | S25: =O25*H25 -> 0 | T25: =O25*(J25+K25) -> 0 | U25: =O25*L25 -> 0 | V25: =Q25-R25-S25-T25-U25 -> 0
B26: CRIOPEELING | D26: 30 | E26: 1 | G26: =D26*12.5 -> 375 | H26: =F26+G26 -> 375 | I26: 850 | J26: =I26*5% -> 42.5 | K26: =I26*16.5% -> 140.25 | L26: =H26*3% -> 11.25 | M26: =I26-H26-J26-K26-L26 -> 281 | N26: =M26/I26 -> 0.33058824 | P26: =O26*(D26/60) -> 0 | Q26: =O26*I26 -> 0 | R26: =O26*(F26+G26) -> 0 | S26: =O26*H26 -> 0 | T26: =O26*(J26+K26) -> 0 | U26: =O26*L26 -> 0 | V26: =Q26-R26-S26-T26-U26 -> 0
B27: CRIOTERAPIA DE NEOPLASIA CUTÂNEA | D27: 30 | E27: 1 | G27: =D27*12.5 -> 375 | H27: =F27+G27 -> 375 | I27: 800 | J27: =I27*5% -> 40 | K27: =I27*16.5% -> 132 | L27: =H27*3% -> 11.25 | M27: =I27-H27-J27-K27-L27 -> 241.75 | N27: =M27/I27 -> 0.3021875 | P27: =O27*(D27/60) -> 0 | Q27: =O27*I27 -> 0 | R27: =O27*(F27+G27) -> 0 | S27: =O27*H27 -> 0 | T27: =O27*(J27+K27) -> 0 | U27: =O27*L27 -> 0 | V27: =Q27-R27-S27-T27-U27 -> 0
A28: 20104103 | B28: CURATIVOS EM GERAL SEM ANESTESIA, EXCETO QUEIMADOS | D28: 30 | E28: 1 | G28: =D28*12.5 -> 375 | H28: =F28+G28 -> 375 | I28: 19 | J28: =I28*5% -> 0.95 | K28: =I28*16.5% -> 3.135 | L28: =H28*3% -> 11.25 | M28: =I28-H28-J28-K28-L28 -> -371.335 | N28: =M28/I28 -> -19.543947 | P28: =O28*(D28/60) -> 0 | Q28: =O28*I28 -> 0 | R28: =O28*(F28+G28) -> 0 | S28: =O28*H28 -> 0 | T28: =O28*(J28+K28) -> 0 | U28: =O28*L28 -> 0 | V28: =Q28-R28-S28-T28-U28 -> 0
B29: CURETAGEM DE MOLUSCO | D29: 30 | E29: 1 | G29: =D29*12.5 -> 375 | H29: =F29+G29 -> 375 | I29: 1150 | J29: =I29*5% -> 57.5 | K29: =I29*16.5% -> 189.75 | L29: =H29*3% -> 11.25 | M29: =I29-H29-J29-K29-L29 -> 516.5 | N29: =M29/I29 -> 0.44913043 | P29: =O29*(D29/60) -> 0 | Q29: =O29*I29 -> 0 | R29: =O29*(F29+G29) -> 0 | S29: =O29*H29 -> 0 | T29: =O29*(J29+K29) -> 0 | U29: =O29*L29 -> 0 | V29: =Q29-R29-S29-T29-U29 -> 0
B30: CURETAGEM SIMPLES - ATÉ 15 LESÕES | D30: 30 | E30: 1 | G30: =D30*12.5 -> 375 | H30: =F30+G30 -> 375 | I30: 850 | J30: =I30*5% -> 42.5 | K30: =I30*16.5% -> 140.25 | L30: =H30*3% -> 11.25 | M30: =I30-H30-J30-K30-L30 -> 281 | N30: =M30/I30 -> 0.33058824 | P30: =O30*(D30/60) -> 0 | Q30: =O30*I30 -> 0 | R30: =O30*(F30+G30) -> 0 | S30: =O30*H30 -> 0 | T30: =O30*(J30+K30) -> 0 | U30: =O30*L30 -> 0 | V30: =Q30-R30-S30-T30-U30 -> 0
B31: CURSO CIRURGIA DERMATOLÓGICA | D31: 360 | E31: 1 | G31: =D31*12.5 -> 4500 | H31: =F31+G31 -> 4500 | I31: 2300 | J31: =I31*5% -> 115 | K31: =I31*16.5% -> 379.5 | L31: =H31*3% -> 135 | M31: =I31-H31-J31-K31-L31 -> -2829.5 | N31: =M31/I31 -> -1.2302174 | P31: =O31*(D31/60) -> 0 | Q31: =O31*I31 -> 0 | R31: =O31*(F31+G31) -> 0 | S31: =O31*H31 -> 0 | T31: =O31*(J31+K31) -> 0 | U31: =O31*L31 -> 0 | V31: =Q31-R31-S31-T31-U31 -> 0
B32: DEPILAÇÃO A LASER ANTEBRAÇO - 1 SESSÃO | D32: 20 | E32: 1 | G32: =D32*12.5 -> 250 | H32: =F32+G32 -> 250 | I32: 350 | J32: =I32*5% -> 17.5 | K32: =I32*16.5% -> 57.75 | L32: =H32*3% -> 7.5 | M32: =I32-H32-J32-K32-L32 -> 17.25 | N32: =M32/I32 -> 0.049285714 | P32: =O32*(D32/60) -> 0 | Q32: =O32*I32 -> 0 | R32: =O32*(F32+G32) -> 0 | S32: =O32*H32 -> 0 | T32: =O32*(J32+K32) -> 0 | U32: =O32*L32 -> 0 | V32: =Q32-R32-S32-T32-U32 -> 0
B33: DEPILAÇÃO A LASER AXILAS - 1 SESSÃO | D33: 20 | E33: 1 | G33: =D33*12.5 -> 250 | H33: =F33+G33 -> 250 | I33: 250 | J33: =I33*5% -> 12.5 | K33: =I33*16.5% -> 41.25 | L33: =H33*3% -> 7.5 | M33: =I33-H33-J33-K33-L33 -> -61.25 | N33: =M33/I33 -> -0.245 | P33: =O33*(D33/60) -> 0 | Q33: =O33*I33 -> 0 | R33: =O33*(F33+G33) -> 0 | S33: =O33*H33 -> 0 | T33: =O33*(J33+K33) -> 0 | U33: =O33*L33 -> 0 | V33: =Q33-R33-S33-T33-U33 -> 0
B34: DEPILAÇÃO A LASER BARBA - 1 SESSÃO | D34: 20 | G34: =D34*12.5 -> 250 | I34: 350 | J34: =I34*5% -> 17.5 | K34: =I34*16.5% -> 57.75 | L34: =H34*3% -> 0 | M34: =I34-H34-J34-K34-L34 -> 274.75 | N34: =M34/I34 -> 0.785 | P34: =O34*(D34/60) -> 0 | Q34: =O34*I34 -> 0 | R34: =O34*(F34+G34) -> 0 | S34: =O34*H34 -> 0 | T34: =O34*(J34+K34) -> 0 | U34: =O34*L34 -> 0 | V34: =Q34-R34-S34-T34-U34 -> 0
B35: DEPILAÇÃO A LASER BARBA INFERIOR - 1 SESSÃO | D35: 20 | G35: =D35*12.5 -> 250 | I35: 250 | J35: =I35*5% -> 12.5 | K35: =I35*16.5% -> 41.25 | L35: =H35*3% -> 0 | M35: =I35-H35-J35-K35-L35 -> 196.25 | N35: =M35/I35 -> 0.785 | P35: =O35*(D35/60) -> 0 | Q35: =O35*I35 -> 0 | R35: =O35*(F35+G35) -> 0 | S35: =O35*H35 -> 0 | T35: =O35*(J35+K35) -> 0 | U35: =O35*L35 -> 0 | V35: =Q35-R35-S35-T35-U35 -> 0
B36: DEPILAÇÃO A LASER BARRIGA (LINHA) - 1 SESSÃO | D36: 30 | G36: =D36*12.5 -> 375 | I36: 250 | J36: =I36*5% -> 12.5 | K36: =I36*16.5% -> 41.25 | L36: =H36*3% -> 0 | M36: =I36-H36-J36-K36-L36 -> 196.25 | N36: =M36/I36 -> 0.785 | P36: =O36*(D36/60) -> 0 | Q36: =O36*I36 -> 0 | R36: =O36*(F36+G36) -> 0 | S36: =O36*H36 -> 0 | T36: =O36*(J36+K36) -> 0 | U36: =O36*L36 -> 0 | V36: =Q36-R36-S36-T36-U36 -> 0
B37: DEPILAÇÃO A LASER BARRIGA COMPLETA - 1 SESSÃO | D37: 30 | G37: =D37*12.5 -> 375 | I37: 400 | J37: =I37*5% -> 20 | K37: =I37*16.5% -> 66 | L37: =H37*3% -> 0 | M37: =I37-H37-J37-K37-L37 -> 314 | N37: =M37/I37 -> 0.785 | P37: =O37*(D37/60) -> 0 | Q37: =O37*I37 -> 0 | R37: =O37*(F37+G37) -> 0 | S37: =O37*H37 -> 0 | T37: =O37*(J37+K37) -> 0 | U37: =O37*L37 -> 0 | V37: =Q37-R37-S37-T37-U37 -> 0
B38: DEPILAÇÃO A LASER BOCHECHAS - 1 SESSÃO | D38: 20 | G38: =D38*12.5 -> 250 | I38: 250 | J38: =I38*5% -> 12.5 | K38: =I38*16.5% -> 41.25 | L38: =H38*3% -> 0 | M38: =I38-H38-J38-K38-L38 -> 196.25 | N38: =M38/I38 -> 0.785 | P38: =O38*(D38/60) -> 0 | Q38: =O38*I38 -> 0 | R38: =O38*(F38+G38) -> 0 | S38: =O38*H38 -> 0 | T38: =O38*(J38+K38) -> 0 | U38: =O38*L38 -> 0 | V38: =Q38-R38-S38-T38-U38 -> 0
B39: DEPILAÇÃO A LASER BRAÇOS - 1 SESSÃO | D39: 30 | G39: =D39*12.5 -> 375 | I39: 400 | J39: =I39*5% -> 20 | K39: =I39*16.5% -> 66 | L39: =H39*3% -> 0 | M39: =I39-H39-J39-K39-L39 -> 314 | N39: =M39/I39 -> 0.785 | P39: =O39*(D39/60) -> 0 | Q39: =O39*I39 -> 0 | R39: =O39*(F39+G39) -> 0 | S39: =O39*H39 -> 0 | T39: =O39*(J39+K39) -> 0 | U39: =O39*L39 -> 0 | V39: =Q39-R39-S39-T39-U39 -> 0
B40: DEPILAÇÃO A LASER BUÇO - 1 SESSÃO | D40: 20 | G40: =D40*12.5 -> 250 | I40: 250 | J40: =I40*5% -> 12.5 | K40: =I40*16.5% -> 41.25 | L40: =H40*3% -> 0 | M40: =I40-H40-J40-K40-L40 -> 196.25 | N40: =M40/I40 -> 0.785 | P40: =O40*(D40/60) -> 0 | Q40: =O40*I40 -> 0 | R40: =O40*(F40+G40) -> 0 | S40: =O40*H40 -> 0 | T40: =O40*(J40+K40) -> 0 | U40: =O40*L40 -> 0 | V40: =Q40-R40-S40-T40-U40 -> 0
B41: DEPILAÇÃO A LASER COCCIX - 1 SESSÃO | D41: 20 | G41: =D41*12.5 -> 250 | I41: 300 | J41: =I41*5% -> 15 | K41: =I41*16.5% -> 49.5 | L41: =H41*3% -> 0 | M41: =I41-H41-J41-K41-L41 -> 235.5 | N41: =M41/I41 -> 0.785 | P41: =O41*(D41/60) -> 0 | Q41: =O41*I41 -> 0 | R41: =O41*(F41+G41) -> 0 | S41: =O41*H41 -> 0 | T41: =O41*(J41+K41) -> 0 | U41: =O41*L41 -> 0 | V41: =Q41-R41-S41-T41-U41 -> 0
B42: DEPILAÇÃO A LASER COSTAS - 1 SESSÃO | D42: 60 | G42: =D42*12.5 -> 750 | I42: 600 | J42: =I42*5% -> 30 | K42: =I42*16.5% -> 99 | L42: =H42*3% -> 0 | M42: =I42-H42-J42-K42-L42 -> 471 | N42: =M42/I42 -> 0.785 | P42: =O42*(D42/60) -> 0 | Q42: =O42*I42 -> 0 | R42: =O42*(F42+G42) -> 0 | S42: =O42*H42 -> 0 | T42: =O42*(J42+K42) -> 0 | U42: =O42*L42 -> 0 | V42: =Q42-R42-S42-T42-U42 -> 0
B43: DEPILAÇÃO A LASER COSTELETAS - 1 SESSÃO | D43: 20 | G43: =D43*12.5 -> 250 | I43: 250 | J43: =I43*5% -> 12.5 | K43: =I43*16.5% -> 41.25 | L43: =H43*3% -> 0 | M43: =I43-H43-J43-K43-L43 -> 196.25 | N43: =M43/I43 -> 0.785 | P43: =O43*(D43/60) -> 0 | Q43: =O43*I43 -> 0 | R43: =O43*(F43+G43) -> 0 | S43: =O43*H43 -> 0 | T43: =O43*(J43+K43) -> 0 | U43: =O43*L43 -> 0 | V43: =Q43-R43-S43-T43-U43 -> 0
B44: DEPILAÇÃO A LASER COXAS - 1 SESSÃO | D44: 50 | G44: =D44*12.5 -> 625 | I44: 600 | J44: =I44*5% -> 30 | K44: =I44*16.5% -> 99 | L44: =H44*3% -> 0 | M44: =I44-H44-J44-K44-L44 -> 471 | N44: =M44/I44 -> 0.785 | P44: =O44*(D44/60) -> 0 | Q44: =O44*I44 -> 0 | R44: =O44*(F44+G44) -> 0 | S44: =O44*H44 -> 0 | T44: =O44*(J44+K44) -> 0 | U44: =O44*L44 -> 0 | V44: =Q44-R44-S44-T44-U44 -> 0
B45: DEPILAÇÃO A LASER COXAS (ANTERIOR OU POSTERIOR) - 1 SESSÃO | D45: 30 | G45: =D45*12.5 -> 375 | I45: 350 | J45: =I45*5% -> 17.5 | K45: =I45*16.5% -> 57.75 | L45: =H45*3% -> 0 | M45: =I45-H45-J45-K45-L45 -> 274.75 | N45: =M45/I45 -> 0.785 | P45: =O45*(D45/60) -> 0 | Q45: =O45*I45 -> 0 | R45: =O45*(F45+G45) -> 0 | S45: =O45*H45 -> 0 | T45: =O45*(J45+K45) -> 0 | U45: =O45*L45 -> 0 | V45: =Q45-R45-S45-T45-U45 -> 0
... B88: ELETROCOAGULAÇÃO DE LESÕES CUTÂNEAS(TBM CARE PLUS) | D88: 40 | G88: =D88*12.5 -> 500 | I88: 1100 | J88: =I88*5% -> 55 | K88: =I88*16.5% -> 181.5 | L88: =H88*3% -> 0 | M88: =I88-H88-J88-K88-L88 -> 863.5 | N88: =M88/I88 -> 0.785 | P88: =O88*(D88/60) -> 0 | Q88: =O88*I88 -> 0 | R88: =O88*(F88+G88) -> 0 | S88: =O88*H88 -> 0 | T88: =O88*(J88+K88) -> 0 | U88: =O88*L88 -> 0 | V88: =Q88-R88-S88-T88-U88 -> 0
A89: 30101298 | B89: ELETROCOAGULAÇÃO DE LESÕES DE PELE E MUCOSAS- COM OU SEM CURETAGEM - ATÉ 5 LESÕES(TBM CARE PLUS) | D89: 30 | G89: =D89*12.5 -> 375 | I89: 0 | J89: =I89*5% -> 0 | K89: =I89*16.5% -> 0 | L89: =H89*3% -> 0 | M89: =I89-H89-J89-K89-L89 -> 0 | N89: =M89/I89 -> #DIV/0! | P89: =O89*(D89/60) -> 0 | Q89: =O89*I89 -> 0 | R89: =O89*(F89+G89) -> 0 | S89: =O89*H89 -> 0 | T89: =O89*(J89+K89) -> 0 | U89: =O89*L89 -> 0 | V89: =Q89-R89-S89-T89-U89 -> 0
A90: 30101352 | B90: EPILAÇÃO POR ELETROLISE - SESSÃO AVULSA(TBM CARE PLUS) | D90: 60 | G90: =D90*12.5 -> 750 | I90: 0 | J90: =I90*5% -> 0 | K90: =I90*16.5% -> 0 | L90: =H90*3% -> 0 | M90: =I90-H90-J90-K90-L90 -> 0 | N90: =M90/I90 -> #DIV/0! | P90: =O90*(D90/60) -> 0 | Q90: =O90*I90 -> 0 | R90: =O90*(F90+G90) -> 0 | S90: =O90*H90 -> 0 | T90: =O90*(J90+K90) -> 0 | U90: =O90*L90 -> 0 | V90: =Q90-R90-S90-T90-U90 -> 0
B91: EXCISÃO E SUTURA SIMPLES DE PEQUENAS LESÕES - LESÕES DE PELE E TECIDO CELULAR SUBCUTÂNEO - ATÉ 5 LESÕES (TBM CARE PLUS) | D91: 60 | G91: =D91*12.5 -> 750 | I91: 0 | J91: =I91*5% -> 0 | K91: =I91*16.5% -> 0 | L91: =H91*3% -> 0 | M91: =I91-H91-J91-K91-L91 -> 0 | N91: =M91/I91 -> #DIV/0! | P91: =O91*(D91/60) -> 0 | Q91: =O91*I91 -> 0 | R91: =O91*(F91+G91) -> 0 | S91: =O91*H91 -> 0 | T91: =O91*(J91+K91) -> 0 | U91: =O91*L91 -> 0 | V91: =Q91-R91-S91-T91-U91 -> 0
A92: 30201055 | B92: EXCISÃO EM CUNHA - EM LÁBIO(TBM CARE PLUS) | D92: 60 | G92: =D92*12.5 -> 750 | I92: 0 | J92: =I92*5% -> 0 | K92: =I92*16.5% -> 0 | L92: =H92*3% -> 0 | M92: =I92-H92-J92-K92-L92 -> 0 | N92: =M92/I92 -> #DIV/0! | P92: =O92*(D92/60) -> 0 | Q92: =O92*I92 -> 0 | R92: =O92*(F92+G92) -> 0 | S92: =O92*H92 -> 0 | T92: =O92*(J92+K92) -> 0 | U92: =O92*L92 -> 0 | V92: =Q92-R92-S92-T92-U92 -> 0
A93: 30101441 | B93: EXERESE DE LESÃO COM AUTO- ENXERTIA -LESÕES DE PELE E TECIDO CELULAR SUBCUTANEO | D93: 0 | G93: =D93*12.5 -> 0 | I93: 0 | J93: =I93*5% -> 0 | K93: =I93*16.5% -> 0 | L93: =H93*3% -> 0 | M93: =I93-H93-J93-K93-L93 -> 0 | N93: =M93/I93 -> #DIV/0! | P93: =O93*(D93/60) -> 0 | Q93: =O93*I93 -> 0 | R93: =O93*(F93+G93) -> 0 | S93: =O93*H93 -> 0 | T93: =O93*(J93+K93) -> 0 | U93: =O93*L93 -> 0 | V93: =Q93-R93-S93-T93-U93 -> 0
A94: 30101468 | B94: EXERESE DE LESÃO/TUMOR DE PELE E MUCOSA(TBM CARE PLUS) | D94: 0 | G94: =D94*12.5 -> 0 | I94: 0 | J94: =I94*5% -> 0 | K94: =I94*16.5% -> 0 | L94: =H94*3% -> 0 | M94: =I94-H94-J94-K94-L94 -> 0 | N94: =M94/I94 -> #DIV/0! | P94: =O94*(D94/60) -> 0 | Q94: =O94*I94 -> 0 | R94: =O94*(F94+G94) -> 0 | S94: =O94*H94 -> 0 | T94: =O94*(J94+K94) -> 0 | U94: =O94*L94 -> 0 | V94: =Q94-R94-S94-T94-U94 -> 0
A95: 30101921 | B95: EXERESE E SUTURA DE HEMANGIOMA, LINFANGIOMA OU NEVUS (POR GRUPO DE ATÉ 5 LESÕES)(TBM CARE PLUS) | D95: 30 | G95: =D95*12.5 -> 375 | I95: 0 | J95: =I95*5% -> 0 | K95: =I95*16.5% -> 0 | L95: =H95*3% -> 0 | M95: =I95-H95-J95-K95-L95 -> 0 | N95: =M95/I95 -> #DIV/0! | P95: =O95*(D95/60) -> 0 | Q95: =O95*I95 -> 0 | R95: =O95*(F95+G95) -> 0 | S95: =O95*H95 -> 0 | T95: =O95*(J95+K95) -> 0 | U95: =O95*L95 -> 0 | V95: =Q95-R95-S95-T95-U95 -> 0
A96: 30101450 | B96: EXERESE E SUTURA DE LESÕES (CIRCULARES OU NÃO) COM ROTAÇÃO DE RETALHOS CUTÂNEOS(TBM CARE PLUS) | D96: 0 | G96: =D96*12.5 -> 0 | I96: 0 | J96: =I96*5% -> 0 | K96: =I96*16.5% -> 0 | L96: =H96*3% -> 0 | M96: =I96-H96-J96-K96-L96 -> 0 | N96: =M96/I96 -> #DIV/0! | P96: =O96*(D96/60) -> 0 | Q96: =O96*I96 -> 0 | R96: =O96*(F96+G96) -> 0 | S96: =O96*H96 -> 0 | T96: =O96*(J96+K96) -> 0 | U96: =O96*L96 -> 0 | V96: =Q96-R96-S96-T96-U96 -> 0
A97: 30101492 | B97: EXERESE E SUTURA DE PEQUENAS LESÕES - GRUPO DE ATÉ 5 LESÕES - LESÕES DE PELE E TECIDO CELULAR SUBCUTÂNEO | C97: (TBM CARE PLUS) | D97: 30 | G97: =D97*12.5 -> 375 | I97: 0 | J97: =I97*5% -> 0 | K97: =I97*16.5% -> 0 | L97: =H97*3% -> 0 | M97: =I97-H97-J97-K97-L97 -> 0 | N97: =M97/I97 -> #DIV/0! | P97: =O97*(D97/60) -> 0 | Q97: =O97*I97 -> 0 | R97: =O97*(F97+G97) -> 0 | S97: =O97*H97 -> 0 | T97: =O97*(J97+K97) -> 0 | U97: =O97*L97 -> 0 | V97: =Q97-R97-S97-T97-U97 -> 0
B98: EXERESE GRAU I | D98: 40 | G98: =D98*12.5 -> 500 | I98: 1500 | J98: =I98*5% -> 75 | K98: =I98*16.5% -> 247.5 | L98: =H98*3% -> 0 | M98: =I98-H98-J98-K98-L98 -> 1177.5 | N98: =M98/I98 -> 0.785 | P98: =O98*(D98/60) -> 0 | Q98: =O98*I98 -> 0 | R98: =O98*(F98+G98) -> 0 | S98: =O98*H98 -> 0 | T98: =O98*(J98+K98) -> 0 | U98: =O98*L98 -> 0 | V98: =Q98-R98-S98-T98-U98 -> 0
B99: EXERESE GRAU II | D99: 60 | G99: =D99*12.5 -> 750 | I99: 1900 | J99: =I99*5% -> 95 | K99: =I99*16.5% -> 313.5 | L99: =H99*3% -> 0 | M99: =I99-H99-J99-K99-L99 -> 1491.5 | N99: =M99/I99 -> 0.785 | P99: =O99*(D99/60) -> 0 | Q99: =O99*I99 -> 0 | R99: =O99*(F99+G99) -> 0 | S99: =O99*H99 -> 0 | T99: =O99*(J99+K99) -> 0 | U99: =O99*L99 -> 0 | V99: =Q99-R99-S99-T99-U99 -> 0
B100: EXERESE GRAU III | D100: 90 | G100: =D100*12.5 -> 1125 | I100: 2500 | J100: =I100*5% -> 125 | K100: =I100*16.5% -> 412.5 | L100: =H100*3% -> 0 | M100: =I100-H100-J100-K100-L100 -> 1962.5 | N100: =M100/I100 -> 0.785 | P100: =O100*(D100/60) -> 0 | Q100: =O100*I100 -> 0 | R100: =O100*(F100+G100) -> 0 | S100: =O100*H100 -> 0 | T100: =O100*(J100+K100) -> 0 | U100: =O100*L100 -> 0 | V100: =Q100-R100-S100-T100-U100 -> 0
B101: EXERESE GRAU IV | D101: 90 | G101: =D101*12.5 -> 1125 | I101: 3000 | J101: =I101*5% -> 150 | K101: =I101*16.5% -> 495 | L101: =H101*3% -> 0 | M101: =I101-H101-J101-K101-L101 -> 2355 | N101: =M101/I101 -> 0.785 | P101: =O101*(D101/60) -> 0 | Q101: =O101*I101 -> 0 | R101: =O101*(F101+G101) -> 0 | S101: =O101*H101 -> 0 | T101: =O101*(J101+K101) -> 0 | U101: =O101*L101 -> 0 | V101: =Q101-R101-S101-T101-U101 -> 0
B102: EXILIS CORPORAL - 1 SESSÃO POR ÁREA | D102: 60 | F102: 25 | G102: =D102*12.5 -> 750 | I102: 600 | J102: =I102*5% -> 30 | K102: =I102*16.5% -> 99 | L102: =H102*3% -> 0 | M102: =I102-H102-J102-K102-L102 -> 471 | N102: =M102/I102 -> 0.785 | P102: =O102*(D102/60) -> 0 | Q102: =O102*I102 -> 0 | R102: =O102*(F102+G102) -> 0 | S102: =O102*H102 -> 0 | T102: =O102*(J102+K102) -> 0 | U102: =O102*L102 -> 0 | V102: =Q102-R102-S102-T102-U102 -> 0
B103: EXILIS CORPORAL - 3 SESSÃO POR ÁREA | D103: 60 | F103: 75 | G103: =D103*12.5 -> 750 | I103: 1200 | J103: =I103*5% -> 60 | K103: =I103*16.5% -> 198 | L103: =H103*3% -> 0 | M103: =I103-H103-J103-K103-L103 -> 942 | N103: =M103/I103 -> 0.785 | P103: =O103*(D103/60) -> 0 | Q103: =O103*I103 -> 0 | R103: =O103*(F103+G103) -> 0 | S103: =O103*H103 -> 0 | T103: =O103*(J103+K103) -> 0 | U103: =O103*L103 -> 0 | V103: =Q103-R103-S103-T103-U103 -> 0
B104: EXILIS FACE + PAPADA - 1 SESSÃO | D104: 60 | F104: 50 | G104: =D104*12.5 -> 750 | I104: 500 | J104: =I104*5% -> 25 | K104: =I104*16.5% -> 82.5 | L104: =H104*3% -> 0 | M104: =I104-H104-J104-K104-L104 -> 392.5 | N104: =M104/I104 -> 0.785 | P104: =O104*(D104/60) -> 0 | Q104: =O104*I104 -> 0 | R104: =O104*(F104+G104) -> 0 | S104: =O104*H104 -> 0 | T104: =O104*(J104+K104) -> 0 | U104: =O104*L104 -> 0 | V104: =Q104-R104-S104-T104-U104 -> 0
B105: EXILIS PAPADA - 1 SESSÃO | D105: 30 | F105: 25 | G105: =D105*12.5 -> 375 | I105: 500 | J105: =I105*5% -> 25 | K105: =I105*16.5% -> 82.5 | L105: =H105*3% -> 0 | M105: =I105-H105-J105-K105-L105 -> 392.5 | N105: =M105/I105 -> 0.785 | P105: =O105*(D105/60) -> 0 | Q105: =O105*I105 -> 0 | R105: =O105*(F105+G105) -> 0 | S105: =O105*H105 -> 0 | T105: =O105*(J105+K105) -> 0 | U105: =O105*L105 -> 0 | V105: =Q105-R105-S105-T105-U105 -> 0
B106: CM SLIM - CORTESIA | D106: 30 | G106: =D106*12.5 -> 375 | I106: 0 | J106: =I106*5% -> 0 | K106: =I106*16.5% -> 0 | L106: =H106*3% -> 0 | M106: =I106-H106-J106-K106-L106 -> 0 | N106: =M106/I106 -> #DIV/0! | P106: =O106*(D106/60) -> 0 | Q106: =O106*I106 -> 0 | R106: =O106*(F106+G106) -> 0 | S106: =O106*H106 -> 0 | T106: =O106*(J106+K106) -> 0 | U106: =O106*L106 -> 0 | V106: =Q106-R106-S106-T106-U106 -> 0
B107: CM SLIM - CORTESIA HIPEX | D107: 30 | G107: =D107*12.5 -> 375 | I107: 0 | J107: =I107*5% -> 0 | K107: =I107*16.5% -> 0 | L107: =H107*3% -> 0 | M107: =I107-H107-J107-K107-L107 -> 0 | N107: =M107/I107 -> #DIV/0! | P107: =O107*(D107/60) -> 0 | Q107: =O107*I107 -> 0 | R107: =O107*(F107+G107) -> 0 | S107: =O107*H107 -> 0 | T107: =O107*(J107+K107) -> 0 | U107: =O107*L107 -> 0 | V107: =Q107-R107-S107-T107-U107 -> 0
B108: FIO DE PDO BIOESTIMULO CROQUI - 10 FIOS | C108: FIO PDO - MARCA - ESPECIFICAÇÃO DO FIO | D108: 30 | F108: 362 | G108: =D108*12.5 -> 375 | I108: 3000 | J108: =I108*5% -> 150 | K108: =I108*16.5% -> 495 | L108: =H108*3% -> 0 | M108: =I108-H108-J108-K108-L108 -> 2355 | N108: =M108/I108 -> 0.785 | P108: =O108*(D108/60) -> 0 | Q108: =O108*I108 -> 0 | R108: =O108*(F108+G108) -> 0 | S108: =O108*H108 -> 0 | T108: =O108*(J108+K108) -> 0 | U108: =O108*L108 -> 0 | V108: =Q108-R108-S108-T108-U108 -> 0
B109: FIO DE PDO ESPECULADO CROQUI 6 FIOS | C109: FIO PDO - MARCA - ESPECIFICAÇÃO DO FIO | D109: 60 | E109: 6 | F109: 240 | G109: =D109*12.5 -> 750 | I109: 3300 | J109: =I109*5% -> 165 | K109: =I109*16.5% -> 544.5 | L109: =H109*3% -> 0 | M109: =I109-H109-J109-K109-L109 -> 2590.5 | N109: =M109/I109 -> 0.785 | P109: =O109*(D109/60) -> 0 | Q109: =O109*I109 -> 0 | R109: =O109*(F109+G109) -> 0 | S109: =O109*H109 -> 0 | T109: =O109*(J109+K109) -> 0 | U109: =O109*L109 -> 0 | V109: =Q109-R109-S109-T109-U109 -> 0
B110: FIO DE PDO TRAÇÃO CROQUI - 4 FIOS | C110: FIO PDO - MARCA - ESPECIFICAÇÃO DO FIO | D110: 60 | E110: 4 | F110: 1100 | G110: =D110*12.5 -> 750 | I110: 5223 | J110: =I110*5% -> 261.15 | K110: =I110*16.5% -> 861.795 | L110: =H110*3% -> 0 | M110: =I110-H110-J110-K110-L110 -> 4100.055 | N110: =M110/I110 -> 0.785 | P110: =O110*(D110/60) -> 0 | Q110: =O110*I110 -> 0 | R110: =O110*(F110+G110) -> 0 | S110: =O110*H110 -> 0 | T110: =O110*(J110+K110) -> 0 | U110: =O110*L110 -> 0 | V110: =Q110-R110-S110-T110-U110 -> 0
B111: FIO DE PDO TRAÇÃO CROQUI - 8 FIOS | C111: FIO PDO - MARCA - ESPECIFICAÇÃO DO FIO | D111: 120 | E111: 8 | F111: 2200 | G111: =D111*12.5 -> 1500 | I111: 10000 | J111: =I111*5% -> 500 | K111: =I111*16.5% -> 1650 | L111: =H111*3% -> 0 | M111: =I111-H111-J111-K111-L111 -> 7850 | N111: =M111/I111 -> 0.785 | P111: =O111*(D111/60) -> 0 | Q111: =O111*I111 -> 0 | R111: =O111*(F111+G111) -> 0 | S111: =O111*H111 -> 0 | T111: =O111*(J111+K111) -> 0 | U111: =O111*L111 -> 0 | V111: =Q111-R111-S111-T111-U111 -> 0
A112: 41301234 | B112: FOTODERMATOSCOPIA | D112: 30 | G112: =D112*12.5 -> 375 | I112: 0 | J112: =I112*5% -> 0 | K112: =I112*16.5% -> 0 | L112: =H112*3% -> 0 | M112: =I112-H112-J112-K112-L112 -> 0 | N112: =M112/I112 -> #DIV/0! | P112: =O112*(D112/60) -> 0 | Q112: =O112*I112 -> 0 | R112: =O112*(F112+G112) -> 0 | S112: =O112*H112 -> 0 | T112: =O112*(J112+K112) -> 0 | U112: =O112*L112 -> 0 | V112: =Q112-R112-S112-T112-U112 -> 0
A113: 30907071 | B113: FULGURAÇÃO DE TELANGECTASIAS ( POR GRUPO) - CIRUGIA VENOSA | D113: 60 | G113: =D113*12.5 -> 750 | I113: 0 | J113: =I113*5% -> 0 | K113: =I113*16.5% -> 0 | L113: =H113*3% -> 0 | M113: =I113-H113-J113-K113-L113 -> 0 | N113: =M113/I113 -> #DIV/0! | P113: =O113*(D113/60) -> 0 | Q113: =O113*I113 -> 0 | R113: =O113*(F113+G113) -> 0 | S113: =O113*H113 -> 0 | T113: =O113*(J113+K113) -> 0 | U113: =O113*L113 -> 0 | V113: =Q113-R113-S113-T113-U113 -> 0
B114: HARMONYCA - 1 AMPOLA | D114: 40 | E114: 1 | F114: 1291.13 | G114: =D114*12.5 -> 500 | I114: 2800 | J114: =I114*5% -> 140 | K114: =I114*16.5% -> 462 | L114: =H114*3% -> 0 | M114: =I114-H114-J114-K114-L114 -> 2198 | N114: =M114/I114 -> 0.785 | P114: =O114*(D114/60) -> 0 | Q114: =O114*I114 -> 0 | R114: =O114*(F114+G114) -> 0 | S114: =O114*H114 -> 0 | T114: =O114*(J114+K114) -> 0 | U114: =O114*L114 -> 0 | V114: =Q114-R114-S114-T114-U114 -> 0
B115: HIDRATAÇÃO PROFUNDA (SKINBOOSTERS) | D115: 40 | G115: =D115*12.5 -> 500 | I115: 1350 | J115: =I115*5% -> 67.5 | K115: =I115*16.5% -> 222.75 | L115: =H115*3% -> 0 | M115: =I115-H115-J115-K115-L115 -> 1059.75 | N115: =M115/I115 -> 0.785 | P115: =O115*(D115/60) -> 0 | Q115: =O115*I115 -> 0 | R115: =O115*(F115+G115) -> 0 | S115: =O115*H115 -> 0 | T115: =O115*(J115+K115) -> 0 | U115: =O115*L115 -> 0 | V115: =Q115-R115-S115-T115-U115 -> 0
A116: 30101620 | B116: INCISÃO E DRENAGEM DE ABCESSO | D116: 30 | G116: =D116*12.5 -> 375 | I116: 850 | J116: =I116*5% -> 42.5 | K116: =I116*16.5% -> 140.25 | L116: =H116*3% -> 0 | M116: =I116-H116-J116-K116-L116 -> 667.25 | N116: =M116/I116 -> 0.785 | P116: =O116*(D116/60) -> 0 | Q116: =O116*I116 -> 0 | R116: =O116*(F116+G116) -> 0 | S116: =O116*H116 -> 0 | T116: =O116*(J116+K116) -> 0 | U116: =O116*L116 -> 0 | V116: =Q116-R116-S116-T116-U116 -> 0
A117: 30101646 | B117: INFILTRAÇÃO DE CORTICÓIDE | D117: 30 | G117: =D117*12.5 -> 375 | I117: 800 | J117: =I117*5% -> 40 | K117: =I117*16.5% -> 132 | L117: =H117*3% -> 0 | M117: =I117-H117-J117-K117-L117 -> 628 | N117: =M117/I117 -> 0.785 | P117: =O117*(D117/60) -> 0 | Q117: =O117*I117 -> 0 | R117: =O117*(F117+G117) -> 0 | S117: =O117*H117 -> 0 | T117: =O117*(J117+K117) -> 0 | U117: =O117*L117 -> 0 | V117: =Q117-R117-S117-T117-U117 -> 0
B118: ETHEREA - 1 SESSÃO | C118: SUBSTITUIR LASER PELO NOME DO APARELHO | D118: 60 | G118: =D118*12.5 -> 750 | I118: 1200 | J118: =I118*5% -> 60 | K118: =I118*16.5% -> 198 | L118: =H118*3% -> 0 | M118: =I118-H118-J118-K118-L118 -> 942 | N118: =M118/I118 -> 0.785 | P118: =O118*(D118/60) -> 0 | Q118: =O118*I118 -> 0 | R118: =O118*(F118+G118) -> 0 | S118: =O118*H118 -> 0 | T118: =O118*(J118+K118) -> 0 | U118: =O118*L118 -> 0 | V118: =Q118-R118-S118-T118-U118 -> 0
B119: ETHEREA- CICATRIZ 1 A 2 AREAS - 1 SESSÃO | D119: 30 | G119: =D119*12.5 -> 375 | I119: 900 | J119: =I119*5% -> 45 | K119: =I119*16.5% -> 148.5 | L119: =H119*3% -> 0 | M119: =I119-H119-J119-K119-L119 -> 706.5 | N119: =M119/I119 -> 0.785 | P119: =O119*(D119/60) -> 0 | Q119: =O119*I119 -> 0 | R119: =O119*(F119+G119) -> 0 | S119: =O119*H119 -> 0 | T119: =O119*(J119+K119) -> 0 | U119: =O119*L119 -> 0 | V119: =Q119-R119-S119-T119-U119 -> 0
B120: ETHEREA - CICATRIZ 3 A 5 AREAS - 1 SESSÃO | D120: 45 | G120: =D120*12.5 -> 562.5 | I120: 1300 | J120: =I120*5% -> 65 | K120: =I120*16.5% -> 214.5 | L120: =H120*3% -> 0 | M120: =I120-H120-J120-K120-L120 -> 1020.5 | N120: =M120/I120 -> 0.785 | P120: =O120*(D120/60) -> 0 | Q120: =O120*I120 -> 0 | R120: =O120*(F120+G120) -> 0 | S120: =O120*H120 -> 0 | T120: =O120*(J120+K120) -> 0 | U120: =O120*L120 -> 0 | V120: =Q120-R120-S120-T120-U120 -> 0
B121: ETHEREA - CORPORAL 1 AREA - 1 SESSÃO | D121: 30 | G121: =D121*12.5 -> 375 | I121: 1200 | J121: =I121*5% -> 60 | K121: =I121*16.5% -> 198 | L121: =H121*3% -> 0 | M121: =I121-H121-J121-K121-L121 -> 942 | N121: =M121/I121 -> 0.785 | P121: =O121*(D121/60) -> 0 | Q121: =O121*I121 -> 0 | R121: =O121*(F121+G121) -> 0 | S121: =O121*H121 -> 0 | T121: =O121*(J121+K121) -> 0 | U121: =O121*L121 -> 0 | V121: =Q121-R121-S121-T121-U121 -> 0
B122: ETHEREA - CORPORAL 1/2 AREA - 1 SESSÃO | D122: 30 | G122: =D122*12.5 -> 375 | I122: 1200 | J122: =I122*5% -> 60 | K122: =I122*16.5% -> 198 | L122: =H122*3% -> 0 | M122: =I122-H122-J122-K122-L122 -> 942 | N122: =M122/I122 -> 0.785 | P122: =O122*(D122/60) -> 0 | Q122: =O122*I122 -> 0 | R122: =O122*(F122+G122) -> 0 | S122: =O122*H122 -> 0 | T122: =O122*(J122+K122) -> 0 | U122: =O122*L122 -> 0 | V122: =Q122-R122-S122-T122-U122 -> 0
B123: ETHEREA- CORPORAL 1/2 AREA - 1 SESSÃO | D123: 0 | G123: =D123*12.5 -> 0 | I123: 0 | J123: =I123*5% -> 0 | K123: =I123*16.5% -> 0 | L123: =H123*3% -> 0 | M123: =I123-H123-J123-K123-L123 -> 0 | N123: =M123/I123 -> #DIV/0! | P123: =O123*(D123/60) -> 0 | Q123: =O123*I123 -> 0 | R123: =O123*(F123+G123) -> 0 | S123: =O123*H123 -> 0 | T123: =O123*(J123+K123) -> 0 | U123: =O123*L123 -> 0 | V123: =Q123-R123-S123-T123-U123 -> 0
B124: ETHEREA - CORPORAL 2 AREAS - 1 SESSÃO | D124: 45 | G124: =D124*12.5 -> 562.5 | I124: 1600 | J124: =I124*5% -> 80 | K124: =I124*16.5% -> 264 | L124: =H124*3% -> 0 | M124: =I124-H124-J124-K124-L124 -> 1256 | N124: =M124/I124 -> 0.785 | P124: =O124*(D124/60) -> 0 | Q124: =O124*I124 -> 0 | R124: =O124*(F124+G124) -> 0 | S124: =O124*H124 -> 0 | T124: =O124*(J124+K124) -> 0 | U124: =O124*L124 -> 0 | V124: =Q124-R124-S124-T124-U124 -> 0
B125: ETHEREA - CORPORAL 3 AREAS - 1 SESSÃO | D125: 60 | G125: =D125*12.5 -> 750 | I125: 1900 | J125: =I125*5% -> 95 | K125: =I125*16.5% -> 313.5 | L125: =H125*3% -> 0 | M125: =I125-H125-J125-K125-L125 -> 1491.5 | N125: =M125/I125 -> 0.785 | P125: =O125*(D125/60) -> 0 | Q125: =O125*I125 -> 0 | R125: =O125*(F125+G125) -> 0 | S125: =O125*H125 -> 0 | T125: =O125*(J125+K125) -> 0 | U125: =O125*L125 -> 0 | V125: =Q125-R125-S125-T125-U125 -> 0
B126: ETHEREA - FACE 1 AREA - 1 SESSÃO | D126: 30 | G126: =D126*12.5 -> 375 | I126: 1984 | J126: =I126*5% -> 99.2 | K126: =I126*16.5% -> 327.36 | L126: =H126*3% -> 0 | M126: =I126-H126-J126-K126-L126 -> 1557.44 | N126: =M126/I126 -> 0.785 | P126: =O126*(D126/60) -> 0 | Q126: =O126*I126 -> 0 | R126: =O126*(F126+G126) -> 0 | S126: =O126*H126 -> 0 | T126: =O126*(J126+K126) -> 0 | U126: =O126*L126 -> 0 | V126: =Q126-R126-S126-T126-U126 -> 0
B127: ETHEREA - FACE 1/2 AREA - 1 SESSÃO | D127: 30 | G127: =D127*12.5 -> 375 | I127: 1200 | J127: =I127*5% -> 60 | K127: =I127*16.5% -> 198 | L127: =H127*3% -> 0 | M127: =I127-H127-J127-K127-L127 -> 942 | N127: =M127/I127 -> 0.785 | P127: =O127*(D127/60) -> 0 | Q127: =O127*I127 -> 0 | R127: =O127*(F127+G127) -> 0 | S127: =O127*H127 -> 0 | T127: =O127*(J127+K127) -> 0 | U127: =O127*L127 -> 0 | V127: =Q127-R127-S127-T127-U127 -> 0
B128: ETHEREA - FACE 2 AREAS - 1 SESSÃO | D128: 30 | G128: =D128*12.5 -> 375 | I128: 3073 | J128: =I128*5% -> 153.65 | K128: =I128*16.5% -> 507.045 | L128: =H128*3% -> 0 | M128: =I128-H128-J128-K128-L128 -> 2412.305 | N128: =M128/I128 -> 0.785 | P128: =O128*(D128/60) -> 0 | Q128: =O128*I128 -> 0 | R128: =O128*(F128+G128) -> 0 | S128: =O128*H128 -> 0 | T128: =O128*(J128+K128) -> 0 | U128: =O128*L128 -> 0 | V128: =Q128-R128-S128-T128-U128 -> 0
B129: ETHEREA - INTIMO - 1 SESSÃO | D129: 30 | G129: =D129*12.5 -> 375 | I129: 1445 | J129: =I129*5% -> 72.25 | K129: =I129*16.5% -> 238.425 | L129: =H129*3% -> 0 | M129: =I129-H129-J129-K129-L129 -> 1134.325 | N129: =M129/I129 -> 0.785 | P129: =O129*(D129/60) -> 0 | Q129: =O129*I129 -> 0 | R129: =O129*(F129+G129) -> 0 | S129: =O129*H129 -> 0 | T129: =O129*(J129+K129) -> 0 | U129: =O129*L129 -> 0 | V129: =Q129-R129-S129-T129-U129 -> 0
B130: ETHEREA - 1 SESSÃO | D130: 30 | G130: =D130*12.5 -> 375 | I130: 500 | J130: =I130*5% -> 25 | K130: =I130*16.5% -> 82.5 | L130: =H130*3% -> 0 | M130: =I130-H130-J130-K130-L130 -> 392.5 | N130: =M130/I130 -> 0.785 | P130: =O130*(D130/60) -> 0 | Q130: =O130*I130 -> 0 | R130: =O130*(F130+G130) -> 0 | S130: =O130*H130 -> 0 | T130: =O130*(J130+K130) -> 0 | U130: =O130*L130 -> 0 | V130: =Q130-R130-S130-T130-U130 -> 0
... B185: OTOPLASTIA (ORELHA) | D185: 60 | G185: =D185*12.5 -> 750 | I185: 6667 | J185: =I185*5% -> 333.35 | K185: =I185*16.5% -> 1100.055 | L185: =H185*3% -> 0 | M185: =I185-H185-J185-K185-L185 -> 5233.595 | N185: =M185/I185 -> 0.785 | P185: =O185*(D185/60) -> 0 | Q185: =O185*I185 -> 0 | R185: =O185*(F185+G185) -> 0 | S185: =O185*H185 -> 0 | T185: =O185*(J185+K185) -> 0 | U185: =O185*L185 -> 0 | V185: =Q185-R185-S185-T185-U185 -> 0
B186: PEELING CORPORAL - 1 SESSÃO | C186: PEELING - PRODUTO - CORPORAL | D186: 30 | G186: =D186*12.5 -> 375 | I186: 750 | J186: =I186*5% -> 37.5 | K186: =I186*16.5% -> 123.75 | L186: =H186*3% -> 0 | M186: =I186-H186-J186-K186-L186 -> 588.75 | N186: =M186/I186 -> 0.785 | P186: =O186*(D186/60) -> 0 | Q186: =O186*I186 -> 0 | R186: =O186*(F186+G186) -> 0 | S186: =O186*H186 -> 0 | T186: =O186*(J186+K186) -> 0 | U186: =O186*L186 -> 0 | V186: =Q186-R186-S186-T186-U186 -> 0
B187: PEELING MÉDIO - 1 SESSÃO | C187: PEELING - PRODUTO - MÉDIO | D187: 45 | G187: =D187*12.5 -> 562.5 | I187: 2000 | J187: =I187*5% -> 100 | K187: =I187*16.5% -> 330 | L187: =H187*3% -> 0 | M187: =I187-H187-J187-K187-L187 -> 1570 | N187: =M187/I187 -> 0.785 | P187: =O187*(D187/60) -> 0 | Q187: =O187*I187 -> 0 | R187: =O187*(F187+G187) -> 0 | S187: =O187*H187 -> 0 | T187: =O187*(J187+K187) -> 0 | U187: =O187*L187 -> 0 | V187: =Q187-R187-S187-T187-U187 -> 0
B188: PEELING MÉDIO DE CAMPO DE CLAREAMENTO | C188: INCLUIR O PRODUTO | D188: 30 | G188: =D188*12.5 -> 375 | I188: 850 | J188: =I188*5% -> 42.5 | K188: =I188*16.5% -> 140.25 | L188: =H188*3% -> 0 | M188: =I188-H188-J188-K188-L188 -> 667.25 | N188: =M188/I188 -> 0.785 | P188: =O188*(D188/60) -> 0 | Q188: =O188*I188 -> 0 | R188: =O188*(F188+G188) -> 0 | S188: =O188*H188 -> 0 | T188: =O188*(J188+K188) -> 0 | U188: =O188*L188 -> 0 | V188: =Q188-R188-S188-T188-U188 -> 0
B189: PEELING MÉDIO PALPEBRAL - 1 SESSÃO | C189: INCLUIR O PRODUTO -PEELING NÃO DA PRA SER PR NOME , PQ OS MEDICOS MISTURAM O PRODUTO | D189: 30 | G189: =D189*12.5 -> 375 | I189: 900 | J189: =I189*5% -> 45 | K189: =I189*16.5% -> 148.5 | L189: =H189*3% -> 0 | M189: =I189-H189-J189-K189-L189 -> 706.5 | N189: =M189/I189 -> 0.785 | P189: =O189*(D189/60) -> 0 | Q189: =O189*I189 -> 0 | R189: =O189*(F189+G189) -> 0 | S189: =O189*H189 -> 0 | T189: =O189*(J189+K189) -> 0 | U189: =O189*L189 -> 0 | V189: =Q189-R189-S189-T189-U189 -> 0
B190: PEELING SUPERFICIAL - 1 SESSÃO | C190: INCLUIR O PRODUTO | D190: 30 | G190: =D190*12.5 -> 375 | I190: 650 | J190: =I190*5% -> 32.5 | K190: =I190*16.5% -> 107.25 | L190: =H190*3% -> 0 | M190: =I190-H190-J190-K190-L190 -> 510.25 | N190: =M190/I190 -> 0.785 | P190: =O190*(D190/60) -> 0 | Q190: =O190*I190 -> 0 | R190: =O190*(F190+G190) -> 0 | S190: =O190*H190 -> 0 | T190: =O190*(J190+K190) -> 0 | U190: =O190*L190 -> 0 | V190: =Q190-R190-S190-T190-U190 -> 0
B191: PERFURAÇÃO HUMANIZADA - ADULTO (COM JÓIA OU SEM) | D191: 0 | G191: =D191*12.5 -> 0 | I191: 300 | J191: =I191*5% -> 15 | K191: =I191*16.5% -> 49.5 | L191: =H191*3% -> 0 | M191: =I191-H191-J191-K191-L191 -> 235.5 | N191: =M191/I191 -> 0.785 | P191: =O191*(D191/60) -> 0 | Q191: =O191*I191 -> 0 | R191: =O191*(F191+G191) -> 0 | S191: =O191*H191 -> 0 | T191: =O191*(J191+K191) -> 0 | U191: =O191*L191 -> 0 | V191: =Q191-R191-S191-T191-U191 -> 0
B192: PERFURAÇÃO HUMANIZADA - BEBÊ (COM JÓIA OU SEM) | D192: 30 | G192: =D192*12.5 -> 375 | I192: 380 | J192: =I192*5% -> 19 | K192: =I192*16.5% -> 62.7 | L192: =H192*3% -> 0 | M192: =I192-H192-J192-K192-L192 -> 298.3 | N192: =M192/I192 -> 0.785 | P192: =O192*(D192/60) -> 0 | Q192: =O192*I192 -> 0 | R192: =O192*(F192+G192) -> 0 | S192: =O192*H192 -> 0 | T192: =O192*(J192+K192) -> 0 | U192: =O192*L192 -> 0 | V192: =Q192-R192-S192-T192-U192 -> 0
A193: 30101670 | B193: PLÁSTICA EM Z OU W - LESÕES DE PELE E TECIDO CELULAR SUBCUTÂNEO (TBM CARE PLUS) | D193: 60 | G193: =D193*12.5 -> 750 | I193: 0 | J193: =I193*5% -> 0 | K193: =I193*16.5% -> 0 | L193: =H193*3% -> 0 | M193: =I193-H193-J193-K193-L193 -> 0 | N193: =M193/I193 -> #DIV/0! | P193: =O193*(D193/60) -> 0 | Q193: =O193*I193 -> 0 | R193: =O193*(F193+G193) -> 0 | S193: =O193*H193 -> 0 | T193: =O193*(J193+K193) -> 0 | U193: =O193*L193 -> 0 | V193: =Q193-R193-S193-T193-U193 -> 0
B194: PREENCHEDOR ULTRA XC | D194: 60 | E194: 1 | F194: 317 | G194: =D194*12.5 -> 750 | I194: 1900 | J194: =I194*5% -> 95 | K194: =I194*16.5% -> 313.5 | L194: =H194*3% -> 0 | M194: =I194-H194-J194-K194-L194 -> 1491.5 | N194: =M194/I194 -> 0.785 | P194: =O194*(D194/60) -> 0 | Q194: =O194*I194 -> 0 | R194: =O194*(F194+G194) -> 0 | S194: =O194*H194 -> 0 | T194: =O194*(J194+K194) -> 0 | U194: =O194*L194 -> 0 | V194: =Q194-R194-S194-T194-U194 -> 0
B195: PREENCHEDOR VOLIFT | D195: 60 | E195: 1 | F195: 396.39 | G195: =D195*12.5 -> 750 | I195: 1900 | J195: =I195*5% -> 95 | K195: =I195*16.5% -> 313.5 | L195: =H195*3% -> 0 | M195: =I195-H195-J195-K195-L195 -> 1491.5 | N195: =M195/I195 -> 0.785 | P195: =O195*(D195/60) -> 0 | Q195: =O195*I195 -> 0 | R195: =O195*(F195+G195) -> 0 | S195: =O195*H195 -> 0 | T195: =O195*(J195+K195) -> 0 | U195: =O195*L195 -> 0 | V195: =Q195-R195-S195-T195-U195 -> 0
B196: PREENCHEDOR LIFT DEEP LIDO | D196: 60 | E196: 1 | F196: 49.99 | G196: =D196*12.5 -> 750 | I196: 1900 | J196: =I196*5% -> 95 | K196: =I196*16.5% -> 313.5 | L196: =H196*3% -> 0 | M196: =I196-H196-J196-K196-L196 -> 1491.5 | N196: =M196/I196 -> 0.785 | P196: =O196*(D196/60) -> 0 | Q196: =O196*I196 -> 0 | R196: =O196*(F196+G196) -> 0 | S196: =O196*H196 -> 0 | T196: =O196*(J196+K196) -> 0 | U196: =O196*L196 -> 0 | V196: =Q196-R196-S196-T196-U196 -> 0
...

Sheet PRECIFICAÇÃO 
A1: DATA DA VENDA | B1: MEDICO SOLICITANTE | C1: PACIENTE | D1: QUANTIDADE | E1: PROCEDIMENTO | F1: TIPO | G1: DURAÇÃO | H1: PREÇO DE VENDA | I1: VENDEDOR | J1: FORMA DE PAGAMENTO | K1: BANDEIRA | L1: TAXA ADM | M1: VALOR TAXA ADM | N1: TAXA ANTECIPAÇÃO | O1: VALOR ANTECIPAÇÃO | P1: VALOR LIQUIDO | Q1: PRODUTOS | R1: TAXA DE SALA 3,12 | S1: IMPOSTOS | T1: MÉDICO EXECUTOR | U1: COMISSÃO | V1: CUSTO TOTAL | W1: % | X1: LUCRO LÍQUIDO | Y1: %2 | Z1: MÉDICO | AA1: CLINICA
A2: 45967 | B2: Yasmin | C2: Estela | D2: 1 | E2: MMP Região - Avulso | F2: {=IFERROR(INDEX(PROCEDIMENTOS!$A$2:$A$48,MATCH('PRECIFICAÇÃO '!$E2,PROCEDIMENTOS!$B$2:$B$48,0)),"")} -> PROCEDIMENTO | G2: {=IFERROR(INDEX(PROCEDIMENTOS!$C$2:$C$48,MATCH('PRECIFICAÇÃO '!$E2,PROCEDIMENTOS!$B$2:$B$48,0)),"")} -> 45 | H2: 500 | J2: PIX | L2: =IFERROR(VLOOKUP('PRECIFICAÇÃO '!$J2,TAXA!$A$2:$C$18,2,FALSE),"") -> 0 | M2: =IFERROR(L2*H2,0) -> 0 | N2: =IFERROR(VLOOKUP('PRECIFICAÇÃO '!$J2,TAXA!$A$2:$C$18,3,FALSE),"") -> 0 | O2: =IFERROR(N2*H2,0) -> 0 | P2: =IFERROR('PRECIFICAÇÃO '!$H2-'PRECIFICAÇÃO '!$M2-'PRECIFICAÇÃO '!$O2,0) -> 500 | Q2: {=IFERROR(INDEX(PROCEDIMENTOS!$D$2:$D$48,MATCH('PRECIFICAÇÃO '!$E2,PROCEDIMENTOS!$B$2:$B$48,0)),"")} -> 7.8 | R2: =G2*3.12 -> 140.4 | S2: =IFERROR(H2*16.5%,0) -> 82.5 | U2: =IFERROR(H2*3%,0) -> 15 | V2: ='PRECIFICAÇÃO '!$Q2+'PRECIFICAÇÃO '!$R2+'PRECIFICAÇÃO '!$S2+'PRECIFICAÇÃO '!$T2+'PRECIFICAÇÃO '!$U2 -> 245.7 | W2: =IFERROR(V2/H2,0) -> 0.4914 | X2: =IFERROR(P2-V2,0) -> 254.3 | Y2: =IFERROR(X2/H2,0) -> 0.5086 | Z2: =IFERROR(X2*20%,0) -> 50.86 | AA2: =IFERROR(X2*80%,0) -> 203.44
A3: 45973 | B3: Yasmin | C3: Marlon Henrique Souza de Barros | D3: 1 | E3: Toxina Botulinica - Terço Superior | F3: {=IFERROR(INDEX(PROCEDIMENTOS!$A$2:$A$48,MATCH('PRECIFICAÇÃO '!$E3,PROCEDIMENTOS!$B$2:$B$48,0)),"")} -> PROCEDIMENTO | G3: {=IFERROR(INDEX(PROCEDIMENTOS!$C$2:$C$48,MATCH('PRECIFICAÇÃO '!$E3,PROCEDIMENTOS!$B$2:$B$48,0)),"")} -> 30 | H3: 1250 | J3: PIX | L3: =IFERROR(VLOOKUP('PRECIFICAÇÃO '!$J3,TAXA!$A$2:$C$18,2,FALSE),"") -> 0 | M3: =IFERROR(L3*H3,0) -> 0 | N3: =IFERROR(VLOOKUP('PRECIFICAÇÃO '!$J3,TAXA!$A$2:$C$18,3,FALSE),"") -> 0 | O3: =IFERROR(N3*H3,0) -> 0 | P3: =IFERROR('PRECIFICAÇÃO '!$H3-'PRECIFICAÇÃO '!$M3-'PRECIFICAÇÃO '!$O3,0) -> 1250 | Q3: {=IFERROR(INDEX(PROCEDIMENTOS!$D$2:$D$48,MATCH('PRECIFICAÇÃO '!$E3,PROCEDIMENTOS!$B$2:$B$48,0)),"")} -> 566.4 | R3: =G3*3.12 -> 93.6 | S3: =IFERROR(H3*16.5%,0) -> 206.25 | U3: =IFERROR(H3*3%,0) -> 37.5 | V3: ='PRECIFICAÇÃO '!$Q3+'PRECIFICAÇÃO '!$R3+'PRECIFICAÇÃO '!$S3+'PRECIFICAÇÃO '!$T3+'PRECIFICAÇÃO '!$U3 -> 903.75 | W3: =IFERROR(V3/H3,0) -> 0.723 | X3: =IFERROR(P3-V3,0) -> 346.25 | Y3: =IFERROR(X3/H3,0) -> 0.277 | Z3: =IFERROR(X3*20%,0) -> 69.25 | AA3: =IFERROR(X3*80%,0) -> 277
A4: 45974 | B4: Yasmin | C4: Claudia Estela | D4: 1 | E4: Tirzepatida | F4: {=IFERROR(INDEX(PROCEDIMENTOS!$A$2:$A$48,MATCH('PRECIFICAÇÃO '!$E4,PROCEDIMENTOS!$B$2:$B$48,0)),"")} -> PROCEDIMENTO | G4: 0 | H4: 1700 | J4: PIX | L4: =IFERROR(VLOOKUP('PRECIFICAÇÃO '!$J4,TAXA!$A$2:$C$18,2,FALSE),"") -> 0 | M4: =IFERROR(L4*H4,0) -> 0 | N4: =IFERROR(VLOOKUP('PRECIFICAÇÃO '!$J4,TAXA!$A$2:$C$18,3,FALSE),"") -> 0 | O4: =IFERROR(N4*H4,0) -> 0 | P4: =IFERROR('PRECIFICAÇÃO '!$H4-'PRECIFICAÇÃO '!$M4-'PRECIFICAÇÃO '!$O4,0) -> 1700 | Q4: {=IFERROR(INDEX(PROCEDIMENTOS!$D$2:$D$48,MATCH('PRECIFICAÇÃO '!$E4,PROCEDIMENTOS!$B$2:$B$48,0)),"")} -> 1575 | R4: =G4*3.12 -> 0 | S4: =IFERROR(H4*16.5%,0) -> 280.5 | U4: =IFERROR(H4*3%,0) -> 51 | V4: ='PRECIFICAÇÃO '!$Q4+'PRECIFICAÇÃO '!$R4+'PRECIFICAÇÃO '!$S4+'PRECIFICAÇÃO '!$T4+'PRECIFICAÇÃO '!$U4 -> 1906.5 | W4: =IFERROR(V4/H4,0) -> 1.1214706 | X4: =IFERROR(P4-V4,0) -> -206.5 | Y4: =IFERROR(X4/H4,0) -> -0.12147059 | Z4: =IFERROR(X4*20%,0) -> -41.3 | AA4: =IFERROR(X4*80%,0) -> -165.2
A5: 45975 | B5: Yasmin | C5: Karina Lopes | D5: 1 | E5: 1º consulta médica | F5: {=IFERROR(INDEX(PROCEDIMENTOS!$A$2:$A$48,MATCH('PRECIFICAÇÃO '!$E5,PROCEDIMENTOS!$B$2:$B$48,0)),"")} -> CONSULTA | G5: {=IFERROR(INDEX(PROCEDIMENTOS!$C$2:$C$48,MATCH('PRECIFICAÇÃO '!$E5,PROCEDIMENTOS!$B$2:$B$48,0)),"")} -> 90 | H5: 800 | J5: PIX | L5: =IFERROR(VLOOKUP('PRECIFICAÇÃO '!$J5,TAXA!$A$2:$C$18,2,FALSE),"") -> 0 | M5: =IFERROR(L5*H5,0) -> 0 | N5: =IFERROR(VLOOKUP('PRECIFICAÇÃO '!$J5,TAXA!$A$2:$C$18,3,FALSE),"") -> 0 | O5: =IFERROR(N5*H5,0) -> 0 | P5: =IFERROR('PRECIFICAÇÃO '!$H5-'PRECIFICAÇÃO '!$M5-'PRECIFICAÇÃO '!$O5,0) -> 800 | Q5: {=IFERROR(INDEX(PROCEDIMENTOS!$D$2:$D$48,MATCH('PRECIFICAÇÃO '!$E5,PROCEDIMENTOS!$B$2:$B$48,0)),"")} -> 0 | R5: =G5*3.12 -> 280.8 | S5: =IFERROR(H5*16.5%,0) -> 132 | U5: =IFERROR(H5*3%,0) -> 24 | V5: ='PRECIFICAÇÃO '!$Q5+'PRECIFICAÇÃO '!$R5+'PRECIFICAÇÃO '!$S5+'PRECIFICAÇÃO '!$T5+'PRECIFICAÇÃO '!$U5 -> 436.8 | W5: =IFERROR(V5/H5,0) -> 0.546 | X5: =IFERROR(P5-V5,0) -> 363.2 | Y5: =IFERROR(X5/H5,0) -> 0.454 | Z5: =IFERROR(X5*20%,0) -> 72.64 | AA5: =IFERROR(X5*80%,0) -> 290.56
A6: 45979 | B6: Yasmin | C6: Débora Vicentini | D6: 1 | E6: Toxina Botulinica - Terço Superior | F6: {=IFERROR(INDEX(PROCEDIMENTOS!$A$2:$A$48,MATCH('PRECIFICAÇÃO '!$E6,PROCEDIMENTOS!$B$2:$B$48,0)),"")} -> PROCEDIMENTO | G6: {=IFERROR(INDEX(PROCEDIMENTOS!$C$2:$C$48,MATCH('PRECIFICAÇÃO '!$E6,PROCEDIMENTOS!$B$2:$B$48,0)),"")} -> 30 | H6: 1425 | J6: PIX | L6: =IFERROR(VLOOKUP('PRECIFICAÇÃO '!$J6,TAXA!$A$2:$C$18,2,FALSE),"") -> 0 | M6: =IFERROR(L6*H6,0) -> 0 | N6: =IFERROR(VLOOKUP('PRECIFICAÇÃO '!$J6,TAXA!$A$2:$C$18,3,FALSE),"") -> 0 | O6: =IFERROR(N6*H6,0) -> 0 | P6: =IFERROR('PRECIFICAÇÃO '!$H6-'PRECIFICAÇÃO '!$M6-'PRECIFICAÇÃO '!$O6,0) -> 1425 | Q6: {=IFERROR(INDEX(PROCEDIMENTOS!$D$2:$D$48,MATCH('PRECIFICAÇÃO '!$E6,PROCEDIMENTOS!$B$2:$B$48,0)),"")} -> 566.4 | R6: =G6*3.12 -> 93.6 | S6: =IFERROR(H6*16.5%,0) -> 235.125 | U6: =IFERROR(H6*3%,0) -> 42.75 | V6: ='PRECIFICAÇÃO '!$Q6+'PRECIFICAÇÃO '!$R6+'PRECIFICAÇÃO '!$S6+'PRECIFICAÇÃO '!$T6+'PRECIFICAÇÃO '!$U6 -> 937.875 | W6: =IFERROR(V6/H6,0) -> 0.65815789 | X6: =IFERROR(P6-V6,0) -> 487.125 | Y6: =IFERROR(X6/H6,0) -> 0.34184211 | Z6: =IFERROR(X6*20%,0) -> 97.425 | AA6: =IFERROR(X6*80%,0) -> 389.7
A7: 45985 | B7: Yasmin | C7: Leia Carvalho | D7: 1 | E7: MMP Alopécia Padrão Feminino (6) | F7: {=IFERROR(INDEX(PROCEDIMENTOS!$A$2:$A$48,MATCH('PRECIFICAÇÃO '!$E7,PROCEDIMENTOS!$B$2:$B$48,0)),"")} -> PROCEDIMENTO | G7: {=IFERROR(INDEX(PROCEDIMENTOS!$C$2:$C$48,MATCH('PRECIFICAÇÃO '!$E7,PROCEDIMENTOS!$B$2:$B$48,0)),"")} -> 270 | H7: 4500 | J7: CREDITO 6X | L7: =IFERROR(VLOOKUP('PRECIFICAÇÃO '!$J7,TAXA!$A$2:$C$18,2,FALSE),"") -> 0.0313 | M7: =IFERROR(L7*H7,0) -> 140.85 | N7: =IFERROR(VLOOKUP('PRECIFICAÇÃO '!$J7,TAXA!$A$2:$C$18,3,FALSE),"") -> 0 | O7: =IFERROR(N7*H7,0) -> 0 | P7: =IFERROR('PRECIFICAÇÃO '!$H7-'PRECIFICAÇÃO '!$M7-'PRECIFICAÇÃO '!$O7,0) -> 4359.15 | Q7: {=IFERROR(INDEX(PROCEDIMENTOS!$D$2:$D$48,MATCH('PRECIFICAÇÃO '!$E7,PROCEDIMENTOS!$B$2:$B$48,0)),"")} -> 46.8 | R7: =G7*3.12 -> 842.4 | S7: =IFERROR(H7*16.5%,0) -> 742.5 | U7: =IFERROR(H7*3%,0) -> 135 | V7: ='PRECIFICAÇÃO '!$Q7+'PRECIFICAÇÃO '!$R7+'PRECIFICAÇÃO '!$S7+'PRECIFICAÇÃO '!$T7+'PRECIFICAÇÃO '!$U7 -> 1766.7 | W7: =IFERROR(V7/H7,0) -> 0.3926 | X7: =IFERROR(P7-V7,0) -> 2592.45 | Y7: =IFERROR(X7/H7,0) -> 0.5761 | Z7: =IFERROR(X7*20%,0) -> 518.49 | AA7: =IFERROR(X7*80%,0) -> 2073.96
A8: 45992 | B8: YASMIN | C8: Livia Zugno | D8: 1 | E8: 1º consulta médica | F8: {=IFERROR(INDEX(PROCEDIMENTOS!$A$2:$A$48,MATCH('PRECIFICAÇÃO '!$E8,PROCEDIMENTOS!$B$2:$B$48,0)),"")} -> CONSULTA | G8: {=IFERROR(INDEX(PROCEDIMENTOS!$C$2:$C$48,MATCH('PRECIFICAÇÃO '!$E8,PROCEDIMENTOS!$B$2:$B$48,0)),"")} -> 90 | H8: 800 | J8: CREDITO A VISTA | L8: =IFERROR(VLOOKUP('PRECIFICAÇÃO '!$J8,TAXA!$A$2:$C$18,2,FALSE),"") -> 0.0283 | M8: =IFERROR(L8*H8,0) -> 22.64 | N8: =IFERROR(VLOOKUP('PRECIFICAÇÃO '!$J8,TAXA!$A$2:$C$18,3,FALSE),"") -> 0 | O8: =IFERROR(N8*H8,0) -> 0 | P8: =IFERROR('PRECIFICAÇÃO '!$H8-'PRECIFICAÇÃO '!$M8-'PRECIFICAÇÃO '!$O8,0) -> 777.36 | Q8: {=IFERROR(INDEX(PROCEDIMENTOS!$D$2:$D$48,MATCH('PRECIFICAÇÃO '!$E8,PROCEDIMENTOS!$B$2:$B$48,0)),"")} -> 0 | R8: =G8*3.12 -> 280.8 | S8: =IFERROR(H8*16.5%,0) -> 132 | U8: =IFERROR(H8*3%,0) -> 24 | V8: ='PRECIFICAÇÃO '!$Q8+'PRECIFICAÇÃO '!$R8+'PRECIFICAÇÃO '!$S8+'PRECIFICAÇÃO '!$T8+'PRECIFICAÇÃO '!$U8 -> 436.8 | W8: =IFERROR(V8/H8,0) -> 0.546 | X8: =IFERROR(P8-V8,0) -> 340.56 | Y8: =IFERROR(X8/H8,0) -> 0.4257 | Z8: =IFERROR(X8*20%,0) -> 68.112 | AA8: =IFERROR(X8*80%,0) -> 272.448
A9: 46000 | B9: YAS E STE | C9: Clélia Troleis | D9: 1 | E9: CO2 | F9: PROCEDIMENTO | G9: 30 | H9: 2800 | J9: CREDITO 6X | L9: =IFERROR(VLOOKUP('PRECIFICAÇÃO '!$J9,TAXA!$A$2:$C$18,2,FALSE),"") -> 0.0313 | M9: =IFERROR(L9*H9,0) -> 87.64 | N9: =IFERROR(VLOOKUP('PRECIFICAÇÃO '!$J9,TAXA!$A$2:$C$18,3,FALSE),"") -> 0 | O9: =IFERROR(N9*H9,0) -> 0 | P9: =IFERROR('PRECIFICAÇÃO '!$H9-'PRECIFICAÇÃO '!$M9-'PRECIFICAÇÃO '!$O9,0) -> 2712.36 | Q9: {=IFERROR(INDEX(PROCEDIMENTOS!$D$2:$D$48,MATCH('PRECIFICAÇÃO '!$E9,PROCEDIMENTOS!$B$2:$B$48,0)),"")} -> 566.67 | R9: =G9*3.12 -> 93.6 | S9: =IFERROR(H9*14.33%,0) -> 401.24 | V9: ='PRECIFICAÇÃO '!$Q9+'PRECIFICAÇÃO '!$R9+'PRECIFICAÇÃO '!$S9+'PRECIFICAÇÃO '!$T9+'PRECIFICAÇÃO '!$U9 -> 1061.51 | W9: =IFERROR(V9/H9,0) -> 0.37911071 | X9: =IFERROR(P9-V9,0) -> 1650.85 | Y9: =IFERROR(X9/H9,0) -> 0.58958929 | Z9: =IFERROR(X9*20%,0) -> 330.17 | AA9: =IFERROR(X9*80%,0) -> 1320.68
A10: 46000 | B10: YAS E STE | C10: Estela | D10: 1 | E10: CO2 | F10: PROCEDIMENTO | G10: 30 | H10: 2800 | J10: CREDITO 6X | L10: =IFERROR(VLOOKUP('PRECIFICAÇÃO '!$J10,TAXA!$A$2:$C$18,2,FALSE),"") -> 0.0313 | M10: =IFERROR(L10*H10,0) -> 87.64 | N10: =IFERROR(VLOOKUP('PRECIFICAÇÃO '!$J10,TAXA!$A$2:$C$18,3,FALSE),"") -> 0 | O10: =IFERROR(N10*H10,0) -> 0 | P10: =IFERROR('PRECIFICAÇÃO '!$H10-'PRECIFICAÇÃO '!$M10-'PRECIFICAÇÃO '!$O10,0) -> 2712.36 | Q10: {=IFERROR(INDEX(PROCEDIMENTOS!$D$2:$D$48,MATCH('PRECIFICAÇÃO '!$E10,PROCEDIMENTOS!$B$2:$B$48,0)),"")} -> 566.67 | R10: =G10*3.12 -> 93.6 | S10: =IFERROR(H10*14.33%,0) -> 401.24 | V10: ='PRECIFICAÇÃO '!$Q10+'PRECIFICAÇÃO '!$R10+'PRECIFICAÇÃO '!$S10+'PRECIFICAÇÃO '!$T10+'PRECIFICAÇÃO '!$U10 -> 1061.51 | W10: =IFERROR(V10/H10,0) -> 0.37911071 | X10: =IFERROR(P10-V10,0) -> 1650.85 | Y10: =IFERROR(X10/H10,0) -> 0.58958929 | Z10: =IFERROR(X10*20%,0) -> 330.17 | AA10: =IFERROR(X10*80%,0) -> 1320.68
A11: 46000 | B11: YAS E STE | C11: Nathália | D11: 1 | E11: CO2 | F11: PROCEDIMENTO | G11: 30 | H11: 3000 | J11: CREDITO 6X | L11: =IFERROR(VLOOKUP('PRECIFICAÇÃO '!$J11,TAXA!$A$2:$C$18,2,FALSE),"") -> 0.0313 | M11: =IFERROR(L11*H11,0) -> 93.9 | N11: =IFERROR(VLOOKUP('PRECIFICAÇÃO '!$J11,TAXA!$A$2:$C$18,3,FALSE),"") -> 0 | O11: =IFERROR(N11*H11,0) -> 0 | P11: =IFERROR('PRECIFICAÇÃO '!$H11-'PRECIFICAÇÃO '!$M11-'PRECIFICAÇÃO '!$O11,0) -> 2906.1 | Q11: {=IFERROR(INDEX(PROCEDIMENTOS!$D$2:$D$48,MATCH('PRECIFICAÇÃO '!$E11,PROCEDIMENTOS!$B$2:$B$48,0)),"")} -> 566.67 | R11: =G11*3.12 -> 93.6 | S11: =IFERROR(H11*14.33%,0) -> 429.9 | V11: ='PRECIFICAÇÃO '!$Q11+'PRECIFICAÇÃO '!$R11+'PRECIFICAÇÃO '!$S11+'PRECIFICAÇÃO '!$T11+'PRECIFICAÇÃO '!$U11 -> 1090.17 | W11: =IFERROR(V11/H11,0) -> 0.36339 | X11: =IFERROR(P11-V11,0) -> 1815.93 | Y11: =IFERROR(X11/H11,0) -> 0.60531 | Z11: =IFERROR(X11*20%,0) -> 363.186 | AA11: =IFERROR(X11*80%,0) -> 1452.744
A12: 46001 | B12: YASMIN | C12: Beatriz | D12: 1 | E12: Toxina Botulinica - Terço Superior | F12: {=IFERROR(INDEX(PROCEDIMENTOS!$A$2:$A$48,MATCH('PRECIFICAÇÃO '!$E12,PROCEDIMENTOS!$B$2:$B$48,0)),"")} -> PROCEDIMENTO | G12: {=IFERROR(INDEX(PROCEDIMENTOS!$C$2:$C$48,MATCH('PRECIFICAÇÃO '!$E12,PROCEDIMENTOS!$B$2:$B$48,0)),"")} -> 30 | H12: 1280 | J12: PIX | L12: =IFERROR(VLOOKUP('PRECIFICAÇÃO '!$J12,TAXA!$A$2:$C$18,2,FALSE),"") -> 0 | M12: =IFERROR(L12*H12,0) -> 0 | N12: =IFERROR(VLOOKUP('PRECIFICAÇÃO '!$J12,TAXA!$A$2:$C$18,3,FALSE),"") -> 0 | O12: =IFERROR(N12*H12,0) -> 0 | P12: =IFERROR('PRECIFICAÇÃO '!$H12-'PRECIFICAÇÃO '!$M12-'PRECIFICAÇÃO '!$O12,0) -> 1280 | Q12: {=IFERROR(INDEX(PROCEDIMENTOS!$D$2:$D$48,MATCH('PRECIFICAÇÃO '!$E12,PROCEDIMENTOS!$B$2:$B$48,0)),"")} -> 566.4 | R12: =G12*3.12 -> 93.6 | S12: =IFERROR(H12*16.5%,0) -> 211.2 | U12: =IFERROR(H12*3%,0) -> 38.4 | V12: ='PRECIFICAÇÃO '!$Q12+'PRECIFICAÇÃO '!$R12+'PRECIFICAÇÃO '!$S12+'PRECIFICAÇÃO '!$T12+'PRECIFICAÇÃO '!$U12 -> 909.6 | W12: =IFERROR(V12/H12,0) -> 0.710625 | X12: =IFERROR(P12-V12,0) -> 370.4 | Y12: =IFERROR(X12/H12,0) -> 0.289375 | Z12: =IFERROR(X12*20%,0) -> 74.08 | AA12: =IFERROR(X12*80%,0) -> 296.32
A13: 46001 | B13: YASMIN | C13: Karina Lopes | D13: 1 | E13: Toxina Botulinica - Terço Superior | F13: {=IFERROR(INDEX(PROCEDIMENTOS!$A$2:$A$48,MATCH('PRECIFICAÇÃO '!$E13,PROCEDIMENTOS!$B$2:$B$48,0)),"")} -> PROCEDIMENTO | G13: {=IFERROR(INDEX(PROCEDIMENTOS!$C$2:$C$48,MATCH('PRECIFICAÇÃO '!$E13,PROCEDIMENTOS!$B$2:$B$48,0)),"")} -> 30 | H13: 1280 | J13: CREDITO 6X | L13: =IFERROR(VLOOKUP('PRECIFICAÇÃO '!$J13,TAXA!$A$2:$C$18,2,FALSE),"") -> 0.0313 | M13: =IFERROR(L13*H13,0) -> 40.064 | N13: =IFERROR(VLOOKUP('PRECIFICAÇÃO '!$J13,TAXA!$A$2:$C$18,3,FALSE),"") -> 0 | O13: =IFERROR(N13*H13,0) -> 0 | P13: =IFERROR('PRECIFICAÇÃO '!$H13-'PRECIFICAÇÃO '!$M13-'PRECIFICAÇÃO '!$O13,0) -> 1239.936 | Q13: {=IFERROR(INDEX(PROCEDIMENTOS!$D$2:$D$48,MATCH('PRECIFICAÇÃO '!$E13,PROCEDIMENTOS!$B$2:$B$48,0)),"")} -> 566.4 | R13: =G13*3.12 -> 93.6 | S13: =IFERROR(H13*16.5%,0) -> 211.2 | U13: =IFERROR(H13*3%,0) -> 38.4 | V13: ='PRECIFICAÇÃO '!$Q13+'PRECIFICAÇÃO '!$R13+'PRECIFICAÇÃO '!$S13+'PRECIFICAÇÃO '!$T13+'PRECIFICAÇÃO '!$U13 -> 909.6 | W13: =IFERROR(V13/H13,0) -> 0.710625 | X13: =IFERROR(P13-V13,0) -> 330.336 | Y13: =IFERROR(X13/H13,0) -> 0.258075 | Z13: =IFERROR(X13*20%,0) -> 66.0672 | AA13: =IFERROR(X13*80%,0) -> 264.2688
A14: 46001 | B14: YASMIN | C14: Karina Lopes | D14: 1 | E14: Ácido Hialurônico - Volift Juvederm | F14: {=IFERROR(INDEX(PROCEDIMENTOS!$A$2:$A$48,MATCH('PRECIFICAÇÃO '!$E14,PROCEDIMENTOS!$B$2:$B$48,0)),"")} -> PROCEDIMENTO | G14: {=IFERROR(INDEX(PROCEDIMENTOS!$C$2:$C$48,MATCH('PRECIFICAÇÃO '!$E14,PROCEDIMENTOS!$B$2:$B$48,0)),"")} -> 60 | H14: 1800 | J14: CREDITO 6X | L14: =IFERROR(VLOOKUP('PRECIFICAÇÃO '!$J14,TAXA!$A$2:$C$18,2,FALSE),"") -> 0.0313 | M14: =IFERROR(L14*H14,0) -> 56.34 | N14: =IFERROR(VLOOKUP('PRECIFICAÇÃO '!$J14,TAXA!$A$2:$C$18,3,FALSE),"") -> 0 | O14: =IFERROR(N14*H14,0) -> 0 | P14: =IFERROR('PRECIFICAÇÃO '!$H14-'PRECIFICAÇÃO '!$M14-'PRECIFICAÇÃO '!$O14,0) -> 1743.66 | Q14: {=IFERROR(INDEX(PROCEDIMENTOS!$D$2:$D$48,MATCH('PRECIFICAÇÃO '!$E14,PROCEDIMENTOS!$B$2:$B$48,0)),"")} -> 411.54 | R14: =G14*3.12 -> 187.2 | S14: =IFERROR(H14*16.5%,0) -> 297 | U14: =IFERROR(H14*3%,0) -> 54 | V14: ='PRECIFICAÇÃO '!$Q14+'PRECIFICAÇÃO '!$R14+'PRECIFICAÇÃO '!$S14+'PRECIFICAÇÃO '!$T14+'PRECIFICAÇÃO '!$U14 -> 949.74 | W14: =IFERROR(V14/H14,0) -> 0.52763333 | X14: =IFERROR(P14-V14,0) -> 793.92 | Y14: =IFERROR(X14/H14,0) -> 0.44106667 | Z14: =IFERROR(X14*20%,0) -> 158.784 | AA14: =IFERROR(X14*80%,0) -> 635.136
A15: 46001 | B15: YASMIN | C15: Karina Lopes | D15: 1 | E15: Ácido Hialurônico - Volux Juvederm | F15: {=IFERROR(INDEX(PROCEDIMENTOS!$A$2:$A$48,MATCH('PRECIFICAÇÃO '!$E15,PROCEDIMENTOS!$B$2:$B$48,0)),"")} -> PROCEDIMENTO | G15: {=IFERROR(INDEX(PROCEDIMENTOS!$C$2:$C$48,MATCH('PRECIFICAÇÃO '!$E15,PROCEDIMENTOS!$B$2:$B$48,0)),"")} -> 60 | H15: 1800 | J15: CREDITO 6X | L15: =IFERROR(VLOOKUP('PRECIFICAÇÃO '!$J15,TAXA!$A$2:$C$18,2,FALSE),"") -> 0.0313 | M15: =IFERROR(L15*H15,0) -> 56.34 | N15: =IFERROR(VLOOKUP('PRECIFICAÇÃO '!$J15,TAXA!$A$2:$C$18,3,FALSE),"") -> 0 | O15: =IFERROR(N15*H15,0) -> 0 | P15: =IFERROR('PRECIFICAÇÃO '!$H15-'PRECIFICAÇÃO '!$M15-'PRECIFICAÇÃO '!$O15,0) -> 1743.66 | Q15: {=IFERROR(INDEX(PROCEDIMENTOS!$D$2:$D$48,MATCH('PRECIFICAÇÃO '!$E15,PROCEDIMENTOS!$B$2:$B$48,0)),"")} -> 240.64 | R15: =G15*3.12 -> 187.2 | S15: =IFERROR(H15*16.5%,0) -> 297 | U15: =IFERROR(H15*3%,0) -> 54 | V15: ='PRECIFICAÇÃO '!$Q15+'PRECIFICAÇÃO '!$R15+'PRECIFICAÇÃO '!$S15+'PRECIFICAÇÃO '!$T15+'PRECIFICAÇÃO '!$U15 -> 778.84 | W15: =IFERROR(V15/H15,0) -> 0.43268889 | X15: =IFERROR(P15-V15,0) -> 964.82 | Y15: =IFERROR(X15/H15,0) -> 0.53601111 | Z15: =IFERROR(X15*20%,0) -> 192.964 | AA15: =IFERROR(X15*80%,0) -> 771.856
A16: 46006 | B16: YASMIN | C16: Lucimara | D16: 1 | E16: MMP Alopécia Padrão Feminino (6) | F16: {=IFERROR(INDEX(PROCEDIMENTOS!$A$2:$A$48,MATCH('PRECIFICAÇÃO '!$E16,PROCEDIMENTOS!$B$2:$B$48,0)),"")} -> PROCEDIMENTO | G16: {=IFERROR(INDEX(PROCEDIMENTOS!$C$2:$C$48,MATCH('PRECIFICAÇÃO '!$E16,PROCEDIMENTOS!$B$2:$B$48,0)),"")} -> 270 | H16: 4000 | J16: PIX | L16: =IFERROR(VLOOKUP('PRECIFICAÇÃO '!$J16,TAXA!$A$2:$C$18,2,FALSE),"") -> 0 | M16: =IFERROR(L16*H16,0) -> 0 | N16: =IFERROR(VLOOKUP('PRECIFICAÇÃO '!$J16,TAXA!$A$2:$C$18,3,FALSE),"") -> 0 | O16: =IFERROR(N16*H16,0) -> 0 | P16: =IFERROR('PRECIFICAÇÃO '!$H16-'PRECIFICAÇÃO '!$M16-'PRECIFICAÇÃO '!$O16,0) -> 4000 | Q16: {=IFERROR(INDEX(PROCEDIMENTOS!$D$2:$D$48,MATCH('PRECIFICAÇÃO '!$E16,PROCEDIMENTOS!$B$2:$B$48,0)),"")} -> 46.8 | R16: =G16*3.12 -> 842.4 | S16: =IFERROR(H16*16.5%,0) -> 660 | U16: =IFERROR(H16*3%,0) -> 120 | V16: ='PRECIFICAÇÃO '!$Q16+'PRECIFICAÇÃO '!$R16+'PRECIFICAÇÃO '!$S16+'PRECIFICAÇÃO '!$T16+'PRECIFICAÇÃO '!$U16 -> 1669.2 | W16: =IFERROR(V16/H16,0) -> 0.4173 | X16: =IFERROR(P16-V16,0) -> 2330.8 | Y16: =IFERROR(X16/H16,0) -> 0.5827 | Z16: =IFERROR(X16*20%,0) -> 466.16 | AA16: =IFERROR(X16*80%,0) -> 1864.64
A17: 46006 | B17: YASMIN | C17: Edimisom | D17: 1 | E17: MMP Alopécia Androgenética (6) | F17: {=IFERROR(INDEX(PROCEDIMENTOS!$A$2:$A$48,MATCH('PRECIFICAÇÃO '!$E17,PROCEDIMENTOS!$B$2:$B$48,0)),"")} -> PROCEDIMENTO | G17: {=IFERROR(INDEX(PROCEDIMENTOS!$C$2:$C$48,MATCH('PRECIFICAÇÃO '!$E17,PROCEDIMENTOS!$B$2:$B$48,0)),"")} -> 270 | H17: 4000 | J17: PIX | L17: =IFERROR(VLOOKUP('PRECIFICAÇÃO '!$J17,TAXA!$A$2:$C$18,2,FALSE),"") -> 0 | M17: =IFERROR(L17*H17,0) -> 0 | N17: =IFERROR(VLOOKUP('PRECIFICAÇÃO '!$J17,TAXA!$A$2:$C$18,3,FALSE),"") -> 0 | O17: =IFERROR(N17*H17,0) -> 0 | P17: =IFERROR('PRECIFICAÇÃO '!$H17-'PRECIFICAÇÃO '!$M17-'PRECIFICAÇÃO '!$O17,0) -> 4000 | Q17: {=IFERROR(INDEX(PROCEDIMENTOS!$D$2:$D$48,MATCH('PRECIFICAÇÃO '!$E17,PROCEDIMENTOS!$B$2:$B$48,0)),"")} -> 46.8 | R17: =G17*3.12 -> 842.4 | S17: =IFERROR(H17*16.5%,0) -> 660 | U17: =IFERROR(H17*3%,0) -> 120 | V17: ='PRECIFICAÇÃO '!$Q17+'PRECIFICAÇÃO '!$R17+'PRECIFICAÇÃO '!$S17+'PRECIFICAÇÃO '!$T17+'PRECIFICAÇÃO '!$U17 -> 1669.2 | W17: =IFERROR(V17/H17,0) -> 0.4173 | X17: =IFERROR(P17-V17,0) -> 2330.8 | Y17: =IFERROR(X17/H17,0) -> 0.5827 | Z17: =IFERROR(X17*20%,0) -> 466.16 | AA17: =IFERROR(X17*80%,0) -> 1864.64
A18: 46008 | B18: YASMIN | C18: Nathália | D18: 1 | E18: Clube do Botox | F18: {=IFERROR(INDEX(PROCEDIMENTOS!$A$2:$A$48,MATCH('PRECIFICAÇÃO '!$E18,PROCEDIMENTOS!$B$2:$B$48,0)),"")} -> PROCEDIMENTO | G18: 90 | H18: 3360 | J18: CREDITO 5X | L18: =IFERROR(VLOOKUP('PRECIFICAÇÃO '!$J18,TAXA!$A$2:$C$18,2,FALSE),"") -> 0.0313 | M18: =IFERROR(L18*H18,0) -> 105.168 | N18: =IFERROR(VLOOKUP('PRECIFICAÇÃO '!$J18,TAXA!$A$2:$C$18,3,FALSE),"") -> 0 | O18: =IFERROR(N18*H18,0) -> 0 | P18: =IFERROR('PRECIFICAÇÃO '!$H18-'PRECIFICAÇÃO '!$M18-'PRECIFICAÇÃO '!$O18,0) -> 3254.832 | Q18: {=IFERROR(INDEX(PROCEDIMENTOS!$D$2:$D$48,MATCH('PRECIFICAÇÃO '!$E18,PROCEDIMENTOS!$B$2:$B$48,0)),"")} -> 1699.2 | R18: =G18*3.12 -> 280.8 | S18: =IFERROR(H18*16.5%,0) -> 554.4 | U18: =IFERROR(H18*3%,0) -> 100.8 | V18: ='PRECIFICAÇÃO '!$Q18+'PRECIFICAÇÃO '!$R18+'PRECIFICAÇÃO '!$S18+'PRECIFICAÇÃO '!$T18+'PRECIFICAÇÃO '!$U18 -> 2635.2 | W18: =IFERROR(V18/H18,0) -> 0.78428571 | X18: =IFERROR(P18-V18,0) -> 619.632 | Y18: =IFERROR(X18/H18,0) -> 0.18441429 | Z18: =IFERROR(X18*20%,0) -> 123.9264 | AA18: =IFERROR(X18*80%,0) -> 495.7056
A19: 46017 | B19: YASMIN | C19: João Vitor | D19: 1 | E19: Tirzepatida | F19: {=IFERROR(INDEX(PROCEDIMENTOS!$A$2:$A$48,MATCH('PRECIFICAÇÃO '!$E19,PROCEDIMENTOS!$B$2:$B$48,0)),"")} -> PROCEDIMENTO | G19: 0 | H19: 1700 | J19: PIX | L19: =IFERROR(VLOOKUP('PRECIFICAÇÃO '!$J19,TAXA!$A$2:$C$18,2,FALSE),"") -> 0 | M19: =IFERROR(L19*H19,0) -> 0 | N19: =IFERROR(VLOOKUP('PRECIFICAÇÃO '!$J19,TAXA!$A$2:$C$18,3,FALSE),"") -> 0 | O19: =IFERROR(N19*H19,0) -> 0 | P19: =IFERROR('PRECIFICAÇÃO '!$H19-'PRECIFICAÇÃO '!$M19-'PRECIFICAÇÃO '!$O19,0) -> 1700 | Q19: {=IFERROR(INDEX(PROCEDIMENTOS!$D$2:$D$48,MATCH('PRECIFICAÇÃO '!$E19,PROCEDIMENTOS!$B$2:$B$48,0)),"")} -> 1575 | R19: =G19*3.12 -> 0 | S19: =IFERROR(H19*16.5%,0) -> 280.5 | U19: =IFERROR(H19*3%,0) -> 51 | V19: ='PRECIFICAÇÃO '!$Q19+'PRECIFICAÇÃO '!$R19+'PRECIFICAÇÃO '!$S19+'PRECIFICAÇÃO '!$T19+'PRECIFICAÇÃO '!$U19 -> 1906.5 | W19: =IFERROR(V19/H19,0) -> 1.1214706 | X19: =IFERROR(P19-V19,0) -> -206.5 | Y19: =IFERROR(X19/H19,0) -> -0.12147059 | Z19: =IFERROR(X19*20%,0) -> -41.3 | AA19: =IFERROR(X19*80%,0) -> -165.2
A20: 46019 | B20: YASMIN | C20: Stéphany | D20: 1 | E20: Toxina Botulinica - Terço Superior | F20: {=IFERROR(INDEX(PROCEDIMENTOS!$A$2:$A$48,MATCH('PRECIFICAÇÃO '!$E20,PROCEDIMENTOS!$B$2:$B$48,0)),"")} -> PROCEDIMENTO | G20: {=IFERROR(INDEX(PROCEDIMENTOS!$C$2:$C$48,MATCH('PRECIFICAÇÃO '!$E20,PROCEDIMENTOS!$B$2:$B$48,0)),"")} -> 30 | H20: 999 | J20: PIX | L20: =IFERROR(VLOOKUP('PRECIFICAÇÃO '!$J20,TAXA!$A$2:$C$18,2,FALSE),"") -> 0 | M20: =IFERROR(L20*H20,0) -> 0 | N20: =IFERROR(VLOOKUP('PRECIFICAÇÃO '!$J20,TAXA!$A$2:$C$18,3,FALSE),"") -> 0 | O20: =IFERROR(N20*H20,0) -> 0 | P20: =IFERROR('PRECIFICAÇÃO '!$H20-'PRECIFICAÇÃO '!$M20-'PRECIFICAÇÃO '!$O20,0) -> 999 | Q20: {=IFERROR(INDEX(PROCEDIMENTOS!$D$2:$D$48,MATCH('PRECIFICAÇÃO '!$E20,PROCEDIMENTOS!$B$2:$B$48,0)),"")} -> 566.4 | R20: =G20*3.12 -> 93.6 | S20: =IFERROR(H20*16.5%,0) -> 164.835 | U20: =IFERROR(H20*3%,0) -> 29.97 | V20: ='PRECIFICAÇÃO '!$Q20+'PRECIFICAÇÃO '!$R20+'PRECIFICAÇÃO '!$S20+'PRECIFICAÇÃO '!$T20+'PRECIFICAÇÃO '!$U20 -> 854.805 | W20: =IFERROR(V20/H20,0) -> 0.85566066 | X20: =IFERROR(P20-V20,0) -> 144.195 | Y20: =IFERROR(X20/H20,0) -> 0.14433934 | Z20: =IFERROR(X20*20%,0) -> 28.839 | AA20: =IFERROR(X20*80%,0) -> 115.356
A21: 46021 | B21: YASMIN | C21: Victor Omatti | D21: 1 | E21: MMP Alopécia Androgenética (6) | F21: {=IFERROR(INDEX(PROCEDIMENTOS!$A$2:$A$48,MATCH('PRECIFICAÇÃO '!$E21,PROCEDIMENTOS!$B$2:$B$48,0)),"")} -> PROCEDIMENTO | G21: {=IFERROR(INDEX(PROCEDIMENTOS!$C$2:$C$48,MATCH('PRECIFICAÇÃO '!$E21,PROCEDIMENTOS!$B$2:$B$48,0)),"")} -> 270 | H21: 1900 | J21: DINHEIRO | L21: =IFERROR(VLOOKUP('PRECIFICAÇÃO '!$J21,TAXA!$A$2:$C$18,2,FALSE),"") -> 0 | M21: =IFERROR(L21*H21,0) -> 0 | N21: =IFERROR(VLOOKUP('PRECIFICAÇÃO '!$J21,TAXA!$A$2:$C$18,3,FALSE),"") -> 0 | O21: =IFERROR(N21*H21,0) -> 0 | P21: =IFERROR('PRECIFICAÇÃO '!$H21-'PRECIFICAÇÃO '!$M21-'PRECIFICAÇÃO '!$O21,0) -> 1900 | Q21: {=IFERROR(INDEX(PROCEDIMENTOS!$D$2:$D$48,MATCH('PRECIFICAÇÃO '!$E21,PROCEDIMENTOS!$B$2:$B$48,0)),"")} -> 46.8 | R21: =G21*3.12 -> 842.4 | S21: =IFERROR(H21*16.5%,0) -> 313.5 | U21: =IFERROR(H21*3%,0) -> 57 | V21: ='PRECIFICAÇÃO '!$Q21+'PRECIFICAÇÃO '!$R21+'PRECIFICAÇÃO '!$S21+'PRECIFICAÇÃO '!$T21+'PRECIFICAÇÃO '!$U21 -> 1259.7 | W21: =IFERROR(V21/H21,0) -> 0.663 | X21: =IFERROR(P21-V21,0) -> 640.3 | Y21: =IFERROR(X21/H21,0) -> 0.337 | Z21: =IFERROR(X21*20%,0) -> 128.06 | AA21: =IFERROR(X21*80%,0) -> 512.24
A22: 46021 | B22: YASMIN | C22: Amanda Bárbara | D22: 1 | E22: MMP Alopécia Padrão Feminino (6) | F22: {=IFERROR(INDEX(PROCEDIMENTOS!$A$2:$A$48,MATCH('PRECIFICAÇÃO '!$E22,PROCEDIMENTOS!$B$2:$B$48,0)),"")} -> PROCEDIMENTO | G22: {=IFERROR(INDEX(PROCEDIMENTOS!$C$2:$C$48,MATCH('PRECIFICAÇÃO '!$E22,PROCEDIMENTOS!$B$2:$B$48,0)),"")} -> 270 | H22: 2250 | J22: CREDITO 6X | L22: =IFERROR(VLOOKUP('PRECIFICAÇÃO '!$J22,TAXA!$A$2:$C$18,2,FALSE),"") -> 0.0313 | M22: =IFERROR(L22*H22,0) -> 70.425 | N22: =IFERROR(VLOOKUP('PRECIFICAÇÃO '!$J22,TAXA!$A$2:$C$18,3,FALSE),"") -> 0 | O22: =IFERROR(N22*H22,0) -> 0 | P22: =IFERROR('PRECIFICAÇÃO '!$H22-'PRECIFICAÇÃO '!$M22-'PRECIFICAÇÃO '!$O22,0) -> 2179.575 | Q22: {=IFERROR(INDEX(PROCEDIMENTOS!$D$2:$D$48,MATCH('PRECIFICAÇÃO '!$E22,PROCEDIMENTOS!$B$2:$B$48,0)),"")} -> 46.8 | R22: =G22*3.12 -> 842.4 | S22: =IFERROR(H22*16.5%,0) -> 371.25 | U22: =IFERROR(H22*3%,0) -> 67.5 | V22: ='PRECIFICAÇÃO '!$Q22+'PRECIFICAÇÃO '!$R22+'PRECIFICAÇÃO '!$S22+'PRECIFICAÇÃO '!$T22+'PRECIFICAÇÃO '!$U22 -> 1327.95 | W22: =IFERROR(V22/H22,0) -> 0.5902 | X22: =IFERROR(P22-V22,0) -> 851.625 | Y22: =IFERROR(X22/H22,0) -> 0.3785 | Z22: =IFERROR(X22*20%,0) -> 170.325 | AA22: =IFERROR(X22*80%,0) -> 681.3
A23: 46021 | B23: YASMIN | C23: Amanda Bárbara | D23: 1 | E23: Clube do Botox | F23: {=IFERROR(INDEX(PROCEDIMENTOS!$A$2:$A$48,MATCH('PRECIFICAÇÃO '!$E23,PROCEDIMENTOS!$B$2:$B$48,0)),"")} -> PROCEDIMENTO | G23: {=IFERROR(INDEX(PROCEDIMENTOS!$C$2:$C$48,MATCH('PRECIFICAÇÃO '!$E23,PROCEDIMENTOS!$B$2:$B$48,0)),"")} -> 90 | H23: 3600 | J23: CREDITO 6X | L23: =IFERROR(VLOOKUP('PRECIFICAÇÃO '!$J23,TAXA!$A$2:$C$18,2,FALSE),"") -> 0.0313 | M23: =IFERROR(L23*H23,0) -> 112.68 | N23: =IFERROR(VLOOKUP('PRECIFICAÇÃO '!$J23,TAXA!$A$2:$C$18,3,FALSE),"") -> 0 | O23: =IFERROR(N23*H23,0) -> 0 | P23: =IFERROR('PRECIFICAÇÃO '!$H23-'PRECIFICAÇÃO '!$M23-'PRECIFICAÇÃO '!$O23,0) -> 3487.32 | R23: =G23*3.12 -> 280.8 | S23: =IFERROR(H23*16.5%,0) -> 594 | U23: =IFERROR(H23*3%,0) -> 108 | V23: ='PRECIFICAÇÃO '!$Q23+'PRECIFICAÇÃO '!$R23+'PRECIFICAÇÃO '!$S23+'PRECIFICAÇÃO '!$T23+'PRECIFICAÇÃO '!$U23 -> 982.8 | W23: =IFERROR(V23/H23,0) -> 0.273 | X23: =IFERROR(P23-V23,0) -> 2504.52 | Y23: =IFERROR(X23/H23,0) -> 0.6957 | Z23: =IFERROR(X23*20%,0) -> 500.904 | AA23: =IFERROR(X23*80%,0) -> 2003.616
A24: 46028 | B24: YASMIN | C24: Meire Laura | D24: 1 | E24: Toxina Botulinica - Terço Superior | F24: {=IFERROR(INDEX(PROCEDIMENTOS!$A$2:$A$48,MATCH('PRECIFICAÇÃO '!$E24,PROCEDIMENTOS!$B$2:$B$48,0)),"")} -> PROCEDIMENTO | G24: {=IFERROR(INDEX(PROCEDIMENTOS!$C$2:$C$48,MATCH('PRECIFICAÇÃO '!$E24,PROCEDIMENTOS!$B$2:$B$48,0)),"")} -> 30 | H24: 1600 | J24: CREDITO 3X | L24: =IFERROR(VLOOKUP('PRECIFICAÇÃO '!$J24,TAXA!$A$2:$C$18,2,FALSE),"") -> 0.0313 | M24: =IFERROR(L24*H24,0) -> 50.08 | N24: =IFERROR(VLOOKUP('PRECIFICAÇÃO '!$J24,TAXA!$A$2:$C$18,3,FALSE),"") -> 0 | O24: =IFERROR(N24*H24,0) -> 0 | P24: =IFERROR('PRECIFICAÇÃO '!$H24-'PRECIFICAÇÃO '!$M24-'PRECIFICAÇÃO '!$O24,0) -> 1549.92 | R24: =G24*3.12 -> 93.6 | S24: =IFERROR(H24*16.5%,0) -> 264 | U24: =IFERROR(H24*3%,0) -> 48 | V24: ='PRECIFICAÇÃO '!$Q24+'PRECIFICAÇÃO '!$R24+'PRECIFICAÇÃO '!$S24+'PRECIFICAÇÃO '!$T24+'PRECIFICAÇÃO '!$U24 -> 405.6 | W24: =IFERROR(V24/H24,0) -> 0.2535 | X24: =IFERROR(P24-V24,0) -> 1144.32 | Y24: =IFERROR(X24/H24,0) -> 0.7152 | Z24: =IFERROR(X24*20%,0) -> 228.864 | AA24: =IFERROR(X24*80%,0) -> 915.456
A25: 46034 | B25: YASMIN | C25: Nelson | D25: 1 | E25: 1º consulta médica | F25: {=IFERROR(INDEX(PROCEDIMENTOS!$A$2:$A$48,MATCH('PRECIFICAÇÃO '!$E25,PROCEDIMENTOS!$B$2:$B$48,0)),"")} -> CONSULTA | G25: {=IFERROR(INDEX(PROCEDIMENTOS!$C$2:$C$48,MATCH('PRECIFICAÇÃO '!$E25,PROCEDIMENTOS!$B$2:$B$48,0)),"")} -> 90 | H25: 800 | J25: PIX | L25: =IFERROR(VLOOKUP('PRECIFICAÇÃO '!$J25,TAXA!$A$2:$C$18,2,FALSE),"") -> 0 | M25: =IFERROR(L25*H25,0) -> 0 | N25: =IFERROR(VLOOKUP('PRECIFICAÇÃO '!$J25,TAXA!$A$2:$C$18,3,FALSE),"") -> 0 | O25: =IFERROR(N25*H25,0) -> 0 | P25: =IFERROR('PRECIFICAÇÃO '!$H25-'PRECIFICAÇÃO '!$M25-'PRECIFICAÇÃO '!$O25,0) -> 800 | R25: =G25*3.12 -> 280.8 | S25: =IFERROR(H25*16.5%,0) -> 132 | U25: =IFERROR(H25*3%,0) -> 24 | V25: ='PRECIFICAÇÃO '!$Q25+'PRECIFICAÇÃO '!$R25+'PRECIFICAÇÃO '!$S25+'PRECIFICAÇÃO '!$T25+'PRECIFICAÇÃO '!$U25 -> 436.8 | W25: =IFERROR(V25/H25,0) -> 0.546 | X25: =IFERROR(P25-V25,0) -> 363.2 | Y25: =IFERROR(X25/H25,0) -> 0.454 | Z25: =IFERROR(X25*20%,0) -> 72.64 | AA25: =IFERROR(X25*80%,0) -> 290.56
A26: 46059 | B26: YASMIN | C26: Juliana | D26: 1 | E26: Clube do Botox | F26: {=IFERROR(INDEX(PROCEDIMENTOS!$A$2:$A$48,MATCH('PRECIFICAÇÃO '!$E26,PROCEDIMENTOS!$B$2:$B$48,0)),"")} -> PROCEDIMENTO | G26: {=IFERROR(INDEX(PROCEDIMENTOS!$C$2:$C$48,MATCH('PRECIFICAÇÃO '!$E26,PROCEDIMENTOS!$B$2:$B$48,0)),"")} -> 90 | H26: 3360 | J26: CREDITO 5X | L26: =IFERROR(VLOOKUP('PRECIFICAÇÃO '!$J26,TAXA!$A$2:$C$18,2,FALSE),"") -> 0.0313 | M26: =IFERROR(L26*H26,0) -> 105.168 | N26: =IFERROR(VLOOKUP('PRECIFICAÇÃO '!$J26,TAXA!$A$2:$C$18,3,FALSE),"") -> 0 | O26: =IFERROR(N26*H26,0) -> 0 | P26: =IFERROR('PRECIFICAÇÃO '!$H26-'PRECIFICAÇÃO '!$M26-'PRECIFICAÇÃO '!$O26,0) -> 3254.832 | Q26: {=IFERROR(INDEX(PROCEDIMENTOS!$D$2:$D$48,MATCH('PRECIFICAÇÃO '!$E26,PROCEDIMENTOS!$B$2:$B$48,0)),"")} -> 1699.2 | R26: =G26*3.12 -> 280.8 | S26: =IFERROR(H26*16.5%,0) -> 554.4 | U26: =IFERROR(H26*3%,0) -> 100.8 | V26: ='PRECIFICAÇÃO '!$Q26+'PRECIFICAÇÃO '!$R26+'PRECIFICAÇÃO '!$S26+'PRECIFICAÇÃO '!$T26+'PRECIFICAÇÃO '!$U26 -> 2635.2 | W26: =IFERROR(V26/H26,0) -> 0.78428571 | X26: =IFERROR(P26-V26,0) -> 619.632 | Y26: =IFERROR(X26/H26,0) -> 0.18441429 | Z26: =IFERROR(X26*20%,0) -> 123.9264 | AA26: =IFERROR(X26*80%,0) -> 495.7056
A27: 46065 | B27: YASMIN | C27: Pedro Augusto | D27: 1 | E27: 1º consulta médica | F27: {=IFERROR(INDEX(PROCEDIMENTOS!$A$2:$A$48,MATCH('PRECIFICAÇÃO '!$E27,PROCEDIMENTOS!$B$2:$B$48,0)),"")} -> CONSULTA | G27: {=IFERROR(INDEX(PROCEDIMENTOS!$C$2:$C$48,MATCH('PRECIFICAÇÃO '!$E27,PROCEDIMENTOS!$B$2:$B$48,0)),"")} -> 90 | H27: 800 | J27: CREDITO 2X | L27: =IFERROR(VLOOKUP('PRECIFICAÇÃO '!$J27,TAXA!$A$2:$C$18,2,FALSE),"") -> 0.0313 | M27: =IFERROR(L27*H27,0) -> 25.04 | N27: =IFERROR(VLOOKUP('PRECIFICAÇÃO '!$J27,TAXA!$A$2:$C$18,3,FALSE),"") -> 0 | O27: =IFERROR(N27*H27,0) -> 0 | P27: =IFERROR('PRECIFICAÇÃO '!$H27-'PRECIFICAÇÃO '!$M27-'PRECIFICAÇÃO '!$O27,0) -> 774.96 | Q27: {=IFERROR(INDEX(PROCEDIMENTOS!$D$2:$D$48,MATCH('PRECIFICAÇÃO '!$E27,PROCEDIMENTOS!$B$2:$B$48,0)),"")} -> 0 | R27: =G27*3.12 -> 280.8 | S27: =IFERROR(H27*16.5%,0) -> 132 | U27: =IFERROR(H27*3%,0) -> 24 | V27: ='PRECIFICAÇÃO '!$Q27+'PRECIFICAÇÃO '!$R27+'PRECIFICAÇÃO '!$S27+'PRECIFICAÇÃO '!$T27+'PRECIFICAÇÃO '!$U27 -> 436.8 | W27: =IFERROR(V27/H27,0) -> 0.546 | X27: =IFERROR(P27-V27,0) -> 338.16 | Y27: =IFERROR(X27/H27,0) -> 0.4227 | Z27: =IFERROR(X27*20%,0) -> 67.632 | AA27: =IFERROR(X27*80%,0) -> 270.528
A28: 46071 | B28: YASMIN | C28: Jamille | D28: 1 | E28: Toxina Botulinica - Terço Superior | F28: {=IFERROR(INDEX(PROCEDIMENTOS!$A$2:$A$48,MATCH('PRECIFICAÇÃO '!$E28,PROCEDIMENTOS!$B$2:$B$48,0)),"")} -> PROCEDIMENTO | G28: {=IFERROR(INDEX(PROCEDIMENTOS!$C$2:$C$48,MATCH('PRECIFICAÇÃO '!$E28,PROCEDIMENTOS!$B$2:$B$48,0)),"")} -> 30 | H28: 1600 | J28: CREDITO 4X | L28: =IFERROR(VLOOKUP('PRECIFICAÇÃO '!$J28,TAXA!$A$2:$C$18,2,FALSE),"") -> 0.0313 | M28: =IFERROR(L28*H28,0) -> 50.08 | N28: =IFERROR(VLOOKUP('PRECIFICAÇÃO '!$J28,TAXA!$A$2:$C$18,3,FALSE),"") -> 0 | O28: =IFERROR(N28*H28,0) -> 0 | P28: =IFERROR('PRECIFICAÇÃO '!$H28-'PRECIFICAÇÃO '!$M28-'PRECIFICAÇÃO '!$O28,0) -> 1549.92 | Q28: {=IFERROR(INDEX(PROCEDIMENTOS!$D$2:$D$48,MATCH('PRECIFICAÇÃO '!$E28,PROCEDIMENTOS!$B$2:$B$48,0)),"")} -> 566.4 | R28: =G28*3.12 -> 93.6 | S28: =IFERROR(H28*16.5%,0) -> 264 | U28: =IFERROR(H28*3%,0) -> 48 | V28: ='PRECIFICAÇÃO '!$Q28+'PRECIFICAÇÃO '!$R28+'PRECIFICAÇÃO '!$S28+'PRECIFICAÇÃO '!$T28+'PRECIFICAÇÃO '!$U28 -> 972 | W28: =IFERROR(V28/H28,0) -> 0.6075 | X28: =IFERROR(P28-V28,0) -> 577.92 | Y28: =IFERROR(X28/H28,0) -> 0.3612 | Z28: =IFERROR(X28*20%,0) -> 115.584 | AA28: =IFERROR(X28*80%,0) -> 462.336
A29: 46072 | B29: YASMIN | C29: Sandro | D29: 1 | E29: MMP Alopécia Androgenética (6) | F29: {=IFERROR(INDEX(PROCEDIMENTOS!$A$2:$A$48,MATCH('PRECIFICAÇÃO '!$E29,PROCEDIMENTOS!$B$2:$B$48,0)),"")} -> PROCEDIMENTO | G29: {=IFERROR(INDEX(PROCEDIMENTOS!$C$2:$C$48,MATCH('PRECIFICAÇÃO '!$E29,PROCEDIMENTOS!$B$2:$B$48,0)),"")} -> 270 | H29: 2800 | J29: PIX | L29: =IFERROR(VLOOKUP('PRECIFICAÇÃO '!$J29,TAXA!$A$2:$C$18,2,FALSE),"") -> 0 | M29: =IFERROR(L29*H29,0) -> 0 | N29: =IFERROR(VLOOKUP('PRECIFICAÇÃO '!$J29,TAXA!$A$2:$C$18,3,FALSE),"") -> 0 | O29: =IFERROR(N29*H29,0) -> 0 | P29: =IFERROR('PRECIFICAÇÃO '!$H29-'PRECIFICAÇÃO '!$M29-'PRECIFICAÇÃO '!$O29,0) -> 2800 | Q29: {=IFERROR(INDEX(PROCEDIMENTOS!$D$2:$D$48,MATCH('PRECIFICAÇÃO '!$E29,PROCEDIMENTOS!$B$2:$B$48,0)),"")} -> 46.8 | R29: =G29*3.12 -> 842.4 | S29: =IFERROR(H29*16.5%,0) -> 462 | U29: =IFERROR(H29*3%,0) -> 84 | V29: ='PRECIFICAÇÃO '!$Q29+'PRECIFICAÇÃO '!$R29+'PRECIFICAÇÃO '!$S29+'PRECIFICAÇÃO '!$T29+'PRECIFICAÇÃO '!$U29 -> 1435.2 | W29: =IFERROR(V29/H29,0) -> 0.51257143 | X29: =IFERROR(P29-V29,0) -> 1364.8 | Y29: =IFERROR(X29/H29,0) -> 0.48742857 | Z29: =IFERROR(X29*20%,0) -> 272.96 | AA29: =IFERROR(X29*80%,0) -> 1091.84
A30: 46072 | B30: YASMIN | C30: Sandro | D30: 1 | E30: MMP Alopécia Androgenética (6) | F30: {=IFERROR(INDEX(PROCEDIMENTOS!$A$2:$A$48,MATCH('PRECIFICAÇÃO '!$E30,PROCEDIMENTOS!$B$2:$B$48,0)),"")} -> PROCEDIMENTO | G30: {=IFERROR(INDEX(PROCEDIMENTOS!$C$2:$C$48,MATCH('PRECIFICAÇÃO '!$E30,PROCEDIMENTOS!$B$2:$B$48,0)),"")} -> 270 | H30: 1700 | J30: CREDITO 6X | L30: =IFERROR(VLOOKUP('PRECIFICAÇÃO '!$J30,TAXA!$A$2:$C$18,2,FALSE),"") -> 0.0313 | M30: =IFERROR(L30*H30,0) -> 53.21 | N30: =IFERROR(VLOOKUP('PRECIFICAÇÃO '!$J30,TAXA!$A$2:$C$18,3,FALSE),"") -> 0 | O30: =IFERROR(N30*H30,0) -> 0 | P30: =IFERROR('PRECIFICAÇÃO '!$H30-'PRECIFICAÇÃO '!$M30-'PRECIFICAÇÃO '!$O30,0) -> 1646.79 | Q30: {=IFERROR(INDEX(PROCEDIMENTOS!$D$2:$D$48,MATCH('PRECIFICAÇÃO '!$E30,PROCEDIMENTOS!$B$2:$B$48,0)),"")} -> 46.8 | R30: =G30*3.12 -> 842.4 | S30: =IFERROR(H30*16.5%,0) -> 280.5 | U30: =IFERROR(H30*3%,0) -> 51 | V30: ='PRECIFICAÇÃO '!$Q30+'PRECIFICAÇÃO '!$R30+'PRECIFICAÇÃO '!$S30+'PRECIFICAÇÃO '!$T30+'PRECIFICAÇÃO '!$U30 -> 1220.7 | W30: =IFERROR(V30/H30,0) -> 0.71805882 | X30: =IFERROR(P30-V30,0) -> 426.09 | Y30: =IFERROR(X30/H30,0) -> 0.25064118 | Z30: =IFERROR(X30*20%,0) -> 85.218 | AA30: =IFERROR(X30*80%,0) -> 340.872
A31: 46077 | B31: YASMIN | C31: José Ricardo | D31: 1 | E31: Toxina Botulinica - Terço Superior | F31: {=IFERROR(INDEX(PROCEDIMENTOS!$A$2:$A$48,MATCH('PRECIFICAÇÃO '!$E31,PROCEDIMENTOS!$B$2:$B$48,0)),"")} -> PROCEDIMENTO | G31: {=IFERROR(INDEX(PROCEDIMENTOS!$C$2:$C$48,MATCH('PRECIFICAÇÃO '!$E31,PROCEDIMENTOS!$B$2:$B$48,0)),"")} -> 30 | H31: 1440 | J31: PIX | L31: =IFERROR(VLOOKUP('PRECIFICAÇÃO '!$J31,TAXA!$A$2:$C$18,2,FALSE),"") -> 0 | M31: =IFERROR(L31*H31,0) -> 0 | N31: =IFERROR(VLOOKUP('PRECIFICAÇÃO '!$J31,TAXA!$A$2:$C$18,3,FALSE),"") -> 0 | O31: =IFERROR(N31*H31,0) -> 0 | P31: =IFERROR('PRECIFICAÇÃO '!$H31-'PRECIFICAÇÃO '!$M31-'PRECIFICAÇÃO '!$O31,0) -> 1440 | R31: =G31*3.12 -> 93.6 | S31: =IFERROR(H31*16.5%,0) -> 237.6 | U31: =IFERROR(H31*3%,0) -> 43.2 | V31: ='PRECIFICAÇÃO '!$Q31+'PRECIFICAÇÃO '!$R31+'PRECIFICAÇÃO '!$S31+'PRECIFICAÇÃO '!$T31+'PRECIFICAÇÃO '!$U31 -> 374.4 | W31: =IFERROR(V31/H31,0) -> 0.26 | X31: =IFERROR(P31-V31,0) -> 1065.6 | Y31: =IFERROR(X31/H31,0) -> 0.74 | Z31: =IFERROR(X31*20%,0) -> 213.12 | AA31: =IFERROR(X31*80%,0) -> 852.48
A32: 46079 | B32: YASMIN | C32: Edimsom | D32: 1 | E32: Biópsia de Pele (1 lesão) | F32: {=IFERROR(INDEX(PROCEDIMENTOS!$A$2:$A$48,MATCH('PRECIFICAÇÃO '!$E32,PROCEDIMENTOS!$B$2:$B$48,0)),"")} -> PROCEDIMENTO | G32: {=IFERROR(INDEX(PROCEDIMENTOS!$C$2:$C$48,MATCH('PRECIFICAÇÃO '!$E32,PROCEDIMENTOS!$B$2:$B$48,0)),"")} -> 30 | H32: 1400 | J32: PIX | L32: =IFERROR(VLOOKUP('PRECIFICAÇÃO '!$J32,TAXA!$A$2:$C$18,2,FALSE),"") -> 0 | M32: =IFERROR(L32*H32,0) -> 0 | N32: =IFERROR(VLOOKUP('PRECIFICAÇÃO '!$J32,TAXA!$A$2:$C$18,3,FALSE),"") -> 0 | O32: =IFERROR(N32*H32,0) -> 0 | P32: =IFERROR('PRECIFICAÇÃO '!$H32-'PRECIFICAÇÃO '!$M32-'PRECIFICAÇÃO '!$O32,0) -> 1400 | R32: =G32*3.12 -> 93.6 | S32: =IFERROR(H32*16.5%,0) -> 231 | U32: =IFERROR(H32*3%,0) -> 42 | V32: ='PRECIFICAÇÃO '!$Q32+'PRECIFICAÇÃO '!$R32+'PRECIFICAÇÃO '!$S32+'PRECIFICAÇÃO '!$T32+'PRECIFICAÇÃO '!$U32 -> 366.6 | W32: =IFERROR(V32/H32,0) -> 0.26185714 | X32: =IFERROR(P32-V32,0) -> 1033.4 | Y32: =IFERROR(X32/H32,0) -> 0.73814286 | Z32: =IFERROR(X32*20%,0) -> 206.68 | AA32: =IFERROR(X32*80%,0) -> 826.72
A33: 46056 | B33: YASMIN | C33: Luiza Rodrigues | D33: 1 | E33: MMP Eflúvio Telógeno (geral) 6 | F33: {=IFERROR(INDEX(PROCEDIMENTOS!$A$2:$A$48,MATCH('PRECIFICAÇÃO '!$E33,PROCEDIMENTOS!$B$2:$B$48,0)),"")} -> PROCEDIMENTO | G33: {=IFERROR(INDEX(PROCEDIMENTOS!$C$2:$C$48,MATCH('PRECIFICAÇÃO '!$E33,PROCEDIMENTOS!$B$2:$B$48,0)),"")} -> 270 | H33: 4500 | J33: CREDITO 6X | L33: =IFERROR(VLOOKUP('PRECIFICAÇÃO '!$J33,TAXA!$A$2:$C$18,2,FALSE),"") -> 0.0313 | M33: =IFERROR(L33*H33,0) -> 140.85 | N33: =IFERROR(VLOOKUP('PRECIFICAÇÃO '!$J33,TAXA!$A$2:$C$18,3,FALSE),"") -> 0 | O33: =IFERROR(N33*H33,0) -> 0 | P33: =IFERROR('PRECIFICAÇÃO '!$H33-'PRECIFICAÇÃO '!$M33-'PRECIFICAÇÃO '!$O33,0) -> 4359.15 | R33: =G33*3.12 -> 842.4 | S33: =IFERROR(H33*16.5%,0) -> 742.5 | U33: =IFERROR(H33*3%,0) -> 135 | V33: ='PRECIFICAÇÃO '!$Q33+'PRECIFICAÇÃO '!$R33+'PRECIFICAÇÃO '!$S33+'PRECIFICAÇÃO '!$T33+'PRECIFICAÇÃO '!$U33 -> 1719.9 | W33: =IFERROR(V33/H33,0) -> 0.3822 | X33: =IFERROR(P33-V33,0) -> 2639.25 | Y33: =IFERROR(X33/H33,0) -> 0.5865 | Z33: =IFERROR(X33*20%,0) -> 527.85 | AA33: =IFERROR(X33*80%,0) -> 2111.4
A34: 46087 | B34: YASMIN | C34: Jamille Uez | D34: 2 | E34: Ácido Hialurônico - Volbella Juvederm | F34: {=IFERROR(INDEX(PROCEDIMENTOS!$A$2:$A$48,MATCH('PRECIFICAÇÃO '!$E34,PROCEDIMENTOS!$B$2:$B$48,0)),"")} -> PROCEDIMENTO | G34: {=IFERROR(INDEX(PROCEDIMENTOS!$C$2:$C$48,MATCH('PRECIFICAÇÃO '!$E34,PROCEDIMENTOS!$B$2:$B$48,0)),"")} -> 60 | H34: 3600 | J34: CREDITO 6X | L34: =IFERROR(VLOOKUP('PRECIFICAÇÃO '!$J34,TAXA!$A$2:$C$18,2,FALSE),"") -> 0.0313 | M34: =IFERROR(L34*H34,0) -> 112.68 | N34: =IFERROR(VLOOKUP('PRECIFICAÇÃO '!$J34,TAXA!$A$2:$C$18,3,FALSE),"") -> 0 | O34: =IFERROR(N34*H34,0) -> 0 | P34: =IFERROR('PRECIFICAÇÃO '!$H34-'PRECIFICAÇÃO '!$M34-'PRECIFICAÇÃO '!$O34,0) -> 3487.32 | Q34: {=IFERROR(INDEX(PROCEDIMENTOS!$D$2:$D$48,MATCH('PRECIFICAÇÃO '!$E34,PROCEDIMENTOS!$B$2:$B$48,0)),"")} -> 360.35 | R34: =G34*3.12 -> 187.2 | S34: =IFERROR(H34*16.5%,0) -> 594 | U34: =IFERROR(H34*3%,0) -> 108 | V34: ='PRECIFICAÇÃO '!$Q34+'PRECIFICAÇÃO '!$R34+'PRECIFICAÇÃO '!$S34+'PRECIFICAÇÃO '!$T34+'PRECIFICAÇÃO '!$U34 -> 1249.55 | W34: =IFERROR(V34/H34,0) -> 0.34709722 | X34: =IFERROR(P34-V34,0) -> 2237.77 | Y34: =IFERROR(X34/H34,0) -> 0.62160278 | Z34: =IFERROR(X34*20%,0) -> 447.554 | AA34: =IFERROR(X34*80%,0) -> 1790.216
F35: {=IFERROR(INDEX(PROCEDIMENTOS!$A$2:$A$48,MATCH('PRECIFICAÇÃO '!$E35,PROCEDIMENTOS!$B$2:$B$48,0)),"")} | G35: {=IFERROR(INDEX(PROCEDIMENTOS!$C$2:$C$48,MATCH('PRECIFICAÇÃO '!$E35,PROCEDIMENTOS!$B$2:$B$48,0)),"")} | L35: =IFERROR(VLOOKUP('PRECIFICAÇÃO '!$J35,TAXA!$A$2:$C$18,2,FALSE),"") | M35: =IFERROR(L35*H35,0) -> 0 | N35: =IFERROR(VLOOKUP('PRECIFICAÇÃO '!$J35,TAXA!$A$2:$C$18,3,FALSE),"") | O35: =IFERROR(N35*H35,0) -> 0 | P35: =IFERROR('PRECIFICAÇÃO '!$H35-'PRECIFICAÇÃO '!$M35-'PRECIFICAÇÃO '!$O35,0) -> 0 | Q35: {=IFERROR(INDEX(PROCEDIMENTOS!$D$2:$D$48,MATCH('PRECIFICAÇÃO '!$E35,PROCEDIMENTOS!$B$2:$B$48,0)),"")} | R35: =G35*3.12 -> 0 | S35: =IFERROR(H35*16.5%,0) -> 0 | U35: =IFERROR(H35*3%,0) -> 0 | V35: ='PRECIFICAÇÃO '!$Q35+'PRECIFICAÇÃO '!$R35+'PRECIFICAÇÃO '!$S35+'PRECIFICAÇÃO '!$T35+'PRECIFICAÇÃO '!$U35 -> 0 | W35: =IFERROR(V35/H35,0) -> 0 | X35: =IFERROR(P35-V35,0) -> 0 | Y35: =IFERROR(X35/H35,0) -> 0 | Z35: =IFERROR(X35*20%,0) -> 0 | AA35: =IFERROR(X35*80%,0) -> 0
F36: {=IFERROR(INDEX(PROCEDIMENTOS!$A$2:$A$48,MATCH('PRECIFICAÇÃO '!$E36,PROCEDIMENTOS!$B$2:$B$48,0)),"")} | G36: {=IFERROR(INDEX(PROCEDIMENTOS!$C$2:$C$48,MATCH('PRECIFICAÇÃO '!$E36,PROCEDIMENTOS!$B$2:$B$48,0)),"")} | L36: =IFERROR(VLOOKUP('PRECIFICAÇÃO '!$J36,TAXA!$A$2:$C$18,2,FALSE),"") | M36: =IFERROR(L36*H36,0) -> 0 | N36: =IFERROR(VLOOKUP('PRECIFICAÇÃO '!$J36,TAXA!$A$2:$C$18,3,FALSE),"") | O36: =IFERROR(N36*H36,0) -> 0 | P36: =IFERROR('PRECIFICAÇÃO '!$H36-'PRECIFICAÇÃO '!$M36-'PRECIFICAÇÃO '!$O36,0) -> 0 | Q36: {=IFERROR(INDEX(PROCEDIMENTOS!$D$2:$D$48,MATCH('PRECIFICAÇÃO '!$E36,PROCEDIMENTOS!$B$2:$B$48,0)),"")} | R36: =G36*3.12 -> 0 | S36: =IFERROR(H36*16.5%,0) -> 0 | U36: =IFERROR(H36*3%,0) -> 0 | V36: ='PRECIFICAÇÃO '!$Q36+'PRECIFICAÇÃO '!$R36+'PRECIFICAÇÃO '!$S36+'PRECIFICAÇÃO '!$T36+'PRECIFICAÇÃO '!$U36 -> 0 | W36: =IFERROR(V36/H36,0) -> 0 | X36: =IFERROR(P36-V36,0) -> 0 | Y36: =IFERROR(X36/H36,0) -> 0 | Z36: =IFERROR(X36*20%,0) -> 0 | AA36: =IFERROR(X36*80%,0) -> 0
F37: {=IFERROR(INDEX(PROCEDIMENTOS!$A$2:$A$48,MATCH('PRECIFICAÇÃO '!$E37,PROCEDIMENTOS!$B$2:$B$48,0)),"")} | G37: {=IFERROR(INDEX(PROCEDIMENTOS!$C$2:$C$48,MATCH('PRECIFICAÇÃO '!$E37,PROCEDIMENTOS!$B$2:$B$48,0)),"")} | L37: =IFERROR(VLOOKUP('PRECIFICAÇÃO '!$J37,TAXA!$A$2:$C$18,2,FALSE),"") | M37: =IFERROR(L37*H37,0) -> 0 | N37: =IFERROR(VLOOKUP('PRECIFICAÇÃO '!$J37,TAXA!$A$2:$C$18,3,FALSE),"") | O37: =IFERROR(N37*H37,0) -> 0 | P37: =IFERROR('PRECIFICAÇÃO '!$H37-'PRECIFICAÇÃO '!$M37-'PRECIFICAÇÃO '!$O37,0) -> 0 | R37: =G37*3.12 -> 0 | S37: =IFERROR(H37*16.5%,0) -> 0 | U37: =IFERROR(H37*3%,0) -> 0 | V37: ='PRECIFICAÇÃO '!$Q37+'PRECIFICAÇÃO '!$R37+'PRECIFICAÇÃO '!$S37+'PRECIFICAÇÃO '!$T37+'PRECIFICAÇÃO '!$U37 -> 0 | W37: =IFERROR(V37/H37,0) -> 0 | X37: =IFERROR(P37-V37,0) -> 0 | Y37: =IFERROR(X37/H37,0) -> 0 | Z37: =IFERROR(X37*20%,0) -> 0 | AA37: =IFERROR(X37*80%,0) -> 0
F38: {=IFERROR(INDEX(PROCEDIMENTOS!$A$2:$A$48,MATCH('PRECIFICAÇÃO '!$E38,PROCEDIMENTOS!$B$2:$B$48,0)),"")} | G38: {=IFERROR(INDEX(PROCEDIMENTOS!$C$2:$C$48,MATCH('PRECIFICAÇÃO '!$E38,PROCEDIMENTOS!$B$2:$B$48,0)),"")} | L38: =IFERROR(VLOOKUP('PRECIFICAÇÃO '!$J38,TAXA!$A$2:$C$18,2,FALSE),"") | M38: =IFERROR(L38*H38,0) -> 0 | N38: =IFERROR(VLOOKUP('PRECIFICAÇÃO '!$J38,TAXA!$A$2:$C$18,3,FALSE),"") | O38: =IFERROR(N38*H38,0) -> 0 | P38: =IFERROR('PRECIFICAÇÃO '!$H38-'PRECIFICAÇÃO '!$M38-'PRECIFICAÇÃO '!$O38,0) -> 0 | Q38: {=IFERROR(INDEX(PROCEDIMENTOS!$D$2:$D$48,MATCH('PRECIFICAÇÃO '!$E38,PROCEDIMENTOS!$B$2:$B$48,0)),"")} | R38: =G38*3.12 -> 0 | S38: =IFERROR(H38*16.5%,0) -> 0 | U38: =IFERROR(H38*3%,0) -> 0 | V38: ='PRECIFICAÇÃO '!$Q38+'PRECIFICAÇÃO '!$R38+'PRECIFICAÇÃO '!$S38+'PRECIFICAÇÃO '!$T38+'PRECIFICAÇÃO '!$U38 -> 0 | W38: =IFERROR(V38/H38,0) -> 0 | X38: =IFERROR(P38-V38,0) -> 0 | Y38: =IFERROR(X38/H38,0) -> 0 | Z38: =IFERROR(X38*20%,0) -> 0 | AA38: =IFERROR(X38*80%,0) -> 0
F39: {=IFERROR(INDEX(PROCEDIMENTOS!$A$2:$A$48,MATCH('PRECIFICAÇÃO '!$E39,PROCEDIMENTOS!$B$2:$B$48,0)),"")} | G39: {=IFERROR(INDEX(PROCEDIMENTOS!$C$2:$C$48,MATCH('PRECIFICAÇÃO '!$E39,PROCEDIMENTOS!$B$2:$B$48,0)),"")} | L39: =IFERROR(VLOOKUP('PRECIFICAÇÃO '!$J39,TAXA!$A$2:$C$18,2,FALSE),"") | M39: =IFERROR(L39*H39,0) -> 0 | N39: =IFERROR(VLOOKUP('PRECIFICAÇÃO '!$J39,TAXA!$A$2:$C$18,3,FALSE),"") | O39: =IFERROR(N39*H39,0) -> 0 | P39: =IFERROR('PRECIFICAÇÃO '!$H39-'PRECIFICAÇÃO '!$M39-'PRECIFICAÇÃO '!$O39,0) -> 0 | Q39: {=IFERROR(INDEX(PROCEDIMENTOS!$D$2:$D$48,MATCH('PRECIFICAÇÃO '!$E39,PROCEDIMENTOS!$B$2:$B$48,0)),"")} | R39: =G39*3.12 -> 0 | S39: =IFERROR(H39*16.5%,0) -> 0 | U39: =IFERROR(H39*3%,0) -> 0 | V39: ='PRECIFICAÇÃO '!$Q39+'PRECIFICAÇÃO '!$R39+'PRECIFICAÇÃO '!$S39+'PRECIFICAÇÃO '!$T39+'PRECIFICAÇÃO '!$U39 -> 0 | W39: =IFERROR(V39/H39,0) -> 0 | X39: =IFERROR(P39-V39,0) -> 0 | Y39: =IFERROR(X39/H39,0) -> 0 | Z39: =IFERROR(X39*20%,0) -> 0 | AA39: =IFERROR(X39*80%,0) -> 0
F40: {=IFERROR(INDEX(PROCEDIMENTOS!$A$2:$A$48,MATCH('PRECIFICAÇÃO '!$E40,PROCEDIMENTOS!$B$2:$B$48,0)),"")} | G40: {=IFERROR(INDEX(PROCEDIMENTOS!$C$2:$C$48,MATCH('PRECIFICAÇÃO '!$E40,PROCEDIMENTOS!$B$2:$B$48,0)),"")} | L40: =IFERROR(VLOOKUP('PRECIFICAÇÃO '!$J40,TAXA!$A$2:$C$18,2,FALSE),"") | M40: =IFERROR(L40*H40,0) -> 0 | N40: =IFERROR(VLOOKUP('PRECIFICAÇÃO '!$J40,TAXA!$A$2:$C$18,3,FALSE),"") | O40: =IFERROR(N40*H40,0) -> 0 | P40: =IFERROR('PRECIFICAÇÃO '!$H40-'PRECIFICAÇÃO '!$M40-'PRECIFICAÇÃO '!$O40,0) -> 0 | Q40: {=IFERROR(INDEX(PROCEDIMENTOS!$D$2:$D$48,MATCH('PRECIFICAÇÃO '!$E40,PROCEDIMENTOS!$B$2:$B$48,0)),"")} | R40: =G40*3.12 -> 0 | S40: =IFERROR(H40*16.5%,0) -> 0 | U40: =IFERROR(H40*3%,0) -> 0 | V40: ='PRECIFICAÇÃO '!$Q40+'PRECIFICAÇÃO '!$R40+'PRECIFICAÇÃO '!$S40+'PRECIFICAÇÃO '!$T40+'PRECIFICAÇÃO '!$U40 -> 0 | W40: =IFERROR(V40/H40,0) -> 0 | X40: =IFERROR(P40-V40,0) -> 0 | Y40: =IFERROR(X40/H40,0) -> 0 | Z40: =IFERROR(X40*20%,0) -> 0 | AA40: =IFERROR(X40*80%,0) -> 0
F41: {=IFERROR(INDEX(PROCEDIMENTOS!$A$2:$A$48,MATCH('PRECIFICAÇÃO '!$E41,PROCEDIMENTOS!$B$2:$B$48,0)),"")} | G41: {=IFERROR(INDEX(PROCEDIMENTOS!$C$2:$C$48,MATCH('PRECIFICAÇÃO '!$E41,PROCEDIMENTOS!$B$2:$B$48,0)),"")} | L41: =IFERROR(VLOOKUP('PRECIFICAÇÃO '!$J41,TAXA!$A$2:$C$18,2,FALSE),"") | M41: =IFERROR(L41*H41,0) -> 0 | N41: =IFERROR(VLOOKUP('PRECIFICAÇÃO '!$J41,TAXA!$A$2:$C$18,3,FALSE),"") | O41: =IFERROR(N41*H41,0) -> 0 | P41: =IFERROR('PRECIFICAÇÃO '!$H41-'PRECIFICAÇÃO '!$M41-'PRECIFICAÇÃO '!$O41,0) -> 0 | Q41: {=IFERROR(INDEX(PROCEDIMENTOS!$D$2:$D$48,MATCH('PRECIFICAÇÃO '!$E41,PROCEDIMENTOS!$B$2:$B$48,0)),"")} | R41: =G41*3.12 -> 0 | S41: =IFERROR(H41*16.5%,0) -> 0 | U41: =IFERROR(H41*3%,0) -> 0 | V41: ='PRECIFICAÇÃO '!$Q41+'PRECIFICAÇÃO '!$R41+'PRECIFICAÇÃO '!$S41+'PRECIFICAÇÃO '!$T41+'PRECIFICAÇÃO '!$U41 -> 0 | W41: =IFERROR(V41/H41,0) -> 0 | X41: =IFERROR(P41-V41,0) -> 0 | Y41: =IFERROR(X41/H41,0) -> 0 | Z41: =IFERROR(X41*20%,0) -> 0 | AA41: =IFERROR(X41*80%,0) -> 0
F42: {=IFERROR(INDEX(PROCEDIMENTOS!$A$2:$A$48,MATCH('PRECIFICAÇÃO '!$E42,PROCEDIMENTOS!$B$2:$B$48,0)),"")} | G42: {=IFERROR(INDEX(PROCEDIMENTOS!$C$2:$C$48,MATCH('PRECIFICAÇÃO '!$E42,PROCEDIMENTOS!$B$2:$B$48,0)),"")} | L42: =IFERROR(VLOOKUP('PRECIFICAÇÃO '!$J42,TAXA!$A$2:$C$18,2,FALSE),"") | M42: =IFERROR(L42*H42,0) -> 0 | N42: =IFERROR(VLOOKUP('PRECIFICAÇÃO '!$J42,TAXA!$A$2:$C$18,3,FALSE),"") | O42: =IFERROR(N42*H42,0) -> 0 | P42: =IFERROR('PRECIFICAÇÃO '!$H42-'PRECIFICAÇÃO '!$M42-'PRECIFICAÇÃO '!$O42,0) -> 0 | Q42: {=IFERROR(INDEX(PROCEDIMENTOS!$D$2:$D$48,MATCH('PRECIFICAÇÃO '!$E42,PROCEDIMENTOS!$B$2:$B$48,0)),"")} | R42: =G42*3.12 -> 0 | S42: =IFERROR(H42*16.5%,0) -> 0 | U42: =IFERROR(H42*3%,0) -> 0 | V42: ='PRECIFICAÇÃO '!$Q42+'PRECIFICAÇÃO '!$R42+'PRECIFICAÇÃO '!$S42+'PRECIFICAÇÃO '!$T42+'PRECIFICAÇÃO '!$U42 -> 0 | W42: =IFERROR(V42/H42,0) -> 0 | X42: =IFERROR(P42-V42,0) -> 0 | Y42: =IFERROR(X42/H42,0) -> 0 | Z42: =IFERROR(X42*20%,0) -> 0 | AA42: =IFERROR(X42*80%,0) -> 0
F43: {=IFERROR(INDEX(PROCEDIMENTOS!$A$2:$A$48,MATCH('PRECIFICAÇÃO '!$E43,PROCEDIMENTOS!$B$2:$B$48,0)),"")} | G43: {=IFERROR(INDEX(PROCEDIMENTOS!$C$2:$C$48,MATCH('PRECIFICAÇÃO '!$E43,PROCEDIMENTOS!$B$2:$B$48,0)),"")} | L43: =IFERROR(VLOOKUP('PRECIFICAÇÃO '!$J43,TAXA!$A$2:$C$18,2,FALSE),"") | M43: =IFERROR(L43*H43,0) -> 0 | N43: =IFERROR(VLOOKUP('PRECIFICAÇÃO '!$J43,TAXA!$A$2:$C$18,3,FALSE),"") | O43: =IFERROR(N43*H43,0) -> 0 | P43: =IFERROR('PRECIFICAÇÃO '!$H43-'PRECIFICAÇÃO '!$M43-'PRECIFICAÇÃO '!$O43,0) -> 0 | R43: =G43*3.12 -> 0 | S43: =IFERROR(H43*16.5%,0) -> 0 | U43: =IFERROR(H43*3%,0) -> 0 | V43: ='PRECIFICAÇÃO '!$Q43+'PRECIFICAÇÃO '!$R43+'PRECIFICAÇÃO '!$S43+'PRECIFICAÇÃO '!$T43+'PRECIFICAÇÃO '!$U43 -> 0 | W43: =IFERROR(V43/H43,0) -> 0 | X43: =IFERROR(P43-V43,0) -> 0 | Y43: =IFERROR(X43/H43,0) -> 0 | Z43: =IFERROR(X43*20%,0) -> 0 | AA43: =IFERROR(X43*80%,0) -> 0
F44: {=IFERROR(INDEX(PROCEDIMENTOS!$A$2:$A$48,MATCH('PRECIFICAÇÃO '!$E44,PROCEDIMENTOS!$B$2:$B$48,0)),"")} | G44: {=IFERROR(INDEX(PROCEDIMENTOS!$C$2:$C$48,MATCH('PRECIFICAÇÃO '!$E44,PROCEDIMENTOS!$B$2:$B$48,0)),"")} | L44: =IFERROR(VLOOKUP('PRECIFICAÇÃO '!$J44,TAXA!$A$2:$C$18,2,FALSE),"") | M44: =IFERROR(L44*H44,0) -> 0 | N44: =IFERROR(VLOOKUP('PRECIFICAÇÃO '!$J44,TAXA!$A$2:$C$18,3,FALSE),"") | O44: =IFERROR(N44*H44,0) -> 0 | P44: =IFERROR('PRECIFICAÇÃO '!$H44-'PRECIFICAÇÃO '!$M44-'PRECIFICAÇÃO '!$O44,0) -> 0 | Q44: {=IFERROR(INDEX(PROCEDIMENTOS!$D$2:$D$48,MATCH('PRECIFICAÇÃO '!$E44,PROCEDIMENTOS!$B$2:$B$48,0)),"")} | R44: =G44*3.12 -> 0 | S44: =IFERROR(H44*16.5%,0) -> 0 | U44: =IFERROR(H44*3%,0) -> 0 | V44: ='PRECIFICAÇÃO '!$Q44+'PRECIFICAÇÃO '!$R44+'PRECIFICAÇÃO '!$S44+'PRECIFICAÇÃO '!$T44+'PRECIFICAÇÃO '!$U44 -> 0 | W44: =IFERROR(V44/H44,0) -> 0 | X44: =IFERROR(P44-V44,0) -> 0 | Y44: =IFERROR(X44/H44,0) -> 0 | Z44: =IFERROR(X44*20%,0) -> 0 | AA44: =IFERROR(X44*80%,0) -> 0
F45: {=IFERROR(INDEX(PROCEDIMENTOS!$A$2:$A$48,MATCH('PRECIFICAÇÃO '!$E45,PROCEDIMENTOS!$B$2:$B$48,0)),"")} | G45: {=IFERROR(INDEX(PROCEDIMENTOS!$C$2:$C$48,MATCH('PRECIFICAÇÃO '!$E45,PROCEDIMENTOS!$B$2:$B$48,0)),"")} | L45: =IFERROR(VLOOKUP('PRECIFICAÇÃO '!$J45,TAXA!$A$2:$C$18,2,FALSE),"") | M45: =IFERROR(L45*H45,0) -> 0 | N45: =IFERROR(VLOOKUP('PRECIFICAÇÃO '!$J45,TAXA!$A$2:$C$18,3,FALSE),"") | O45: =IFERROR(N45*H45,0) -> 0 | P45: =IFERROR('PRECIFICAÇÃO '!$H45-'PRECIFICAÇÃO '!$M45-'PRECIFICAÇÃO '!$O45,0) -> 0 | Q45: {=IFERROR(INDEX(PROCEDIMENTOS!$D$2:$D$48,MATCH('PRECIFICAÇÃO '!$E45,PROCEDIMENTOS!$B$2:$B$48,0)),"")} | R45: =G45*3.12 -> 0 | S45: =IFERROR(H45*16.5%,0) -> 0 | U45: =IFERROR(H45*3%,0) -> 0 | V45: ='PRECIFICAÇÃO '!$Q45+'PRECIFICAÇÃO '!$R45+'PRECIFICAÇÃO '!$S45+'PRECIFICAÇÃO '!$T45+'PRECIFICAÇÃO '!$U45 -> 0 | W45: =IFERROR(V45/H45,0) -> 0 | X45: =IFERROR(P45-V45,0) -> 0 | Y45: =IFERROR(X45/H45,0) -> 0 | Z45: =IFERROR(X45*20%,0) -> 0 | AA45: =IFERROR(X45*80%,0) -> 0
F46: {=IFERROR(INDEX(PROCEDIMENTOS!$A$2:$A$48,MATCH('PRECIFICAÇÃO '!$E46,PROCEDIMENTOS!$B$2:$B$48,0)),"")} | G46: {=IFERROR(INDEX(PROCEDIMENTOS!$C$2:$C$48,MATCH('PRECIFICAÇÃO '!$E46,PROCEDIMENTOS!$B$2:$B$48,0)),"")} | L46: =IFERROR(VLOOKUP('PRECIFICAÇÃO '!$J46,TAXA!$A$2:$C$18,2,FALSE),"") | M46: =IFERROR(L46*H46,0) -> 0 | N46: =IFERROR(VLOOKUP('PRECIFICAÇÃO '!$J46,TAXA!$A$2:$C$18,3,FALSE),"") | O46: =IFERROR(N46*H46,0) -> 0 | P46: =IFERROR('PRECIFICAÇÃO '!$H46-'PRECIFICAÇÃO '!$M46-'PRECIFICAÇÃO '!$O46,0) -> 0 | Q46: {=IFERROR(INDEX(PROCEDIMENTOS!$D$2:$D$48,MATCH('PRECIFICAÇÃO '!$E46,PROCEDIMENTOS!$B$2:$B$48,0)),"")} | R46: =G46*3.12 -> 0 | S46: =IFERROR(H46*16.5%,0) -> 0 | U46: =IFERROR(H46*3%,0) -> 0 | V46: ='PRECIFICAÇÃO '!$Q46+'PRECIFICAÇÃO '!$R46+'PRECIFICAÇÃO '!$S46+'PRECIFICAÇÃO '!$T46+'PRECIFICAÇÃO '!$U46 -> 0 | W46: =IFERROR(V46/H46,0) -> 0 | X46: =IFERROR(P46-V46,0) -> 0 | Y46: =IFERROR(X46/H46,0) -> 0 | Z46: =IFERROR(X46*20%,0) -> 0 | AA46: =IFERROR(X46*80%,0) -> 0
F47: {=IFERROR(INDEX(PROCEDIMENTOS!$A$2:$A$48,MATCH('PRECIFICAÇÃO '!$E47,PROCEDIMENTOS!$B$2:$B$48,0)),"")} | G47: {=IFERROR(INDEX(PROCEDIMENTOS!$C$2:$C$48,MATCH('PRECIFICAÇÃO '!$E47,PROCEDIMENTOS!$B$2:$B$48,0)),"")} | L47: =IFERROR(VLOOKUP('PRECIFICAÇÃO '!$J47,TAXA!$A$2:$C$18,2,FALSE),"") | M47: =IFERROR(L47*H47,0) -> 0 | N47: =IFERROR(VLOOKUP('PRECIFICAÇÃO '!$J47,TAXA!$A$2:$C$18,3,FALSE),"") | O47: =IFERROR(N47*H47,0) -> 0 | P47: =IFERROR('PRECIFICAÇÃO '!$H47-'PRECIFICAÇÃO '!$M47-'PRECIFICAÇÃO '!$O47,0) -> 0 | Q47: {=IFERROR(INDEX(PROCEDIMENTOS!$D$2:$D$48,MATCH('PRECIFICAÇÃO '!$E47,PROCEDIMENTOS!$B$2:$B$48,0)),"")} | R47: =G47*3.12 -> 0 | S47: =IFERROR(H47*16.5%,0) -> 0 | U47: =IFERROR(H47*3%,0) -> 0 | V47: ='PRECIFICAÇÃO '!$Q47+'PRECIFICAÇÃO '!$R47+'PRECIFICAÇÃO '!$S47+'PRECIFICAÇÃO '!$T47+'PRECIFICAÇÃO '!$U47 -> 0 | W47: =IFERROR(V47/H47,0) -> 0 | X47: =IFERROR(P47-V47,0) -> 0 | Y47: =IFERROR(X47/H47,0) -> 0 | Z47: =IFERROR(X47*20%,0) -> 0 | AA47: =IFERROR(X47*80%,0) -> 0
F48: {=IFERROR(INDEX(PROCEDIMENTOS!$A$2:$A$48,MATCH('PRECIFICAÇÃO '!$E48,PROCEDIMENTOS!$B$2:$B$48,0)),"")} | G48: {=IFERROR(INDEX(PROCEDIMENTOS!$C$2:$C$48,MATCH('PRECIFICAÇÃO '!$E48,PROCEDIMENTOS!$B$2:$B$48,0)),"")} | L48: =IFERROR(VLOOKUP('PRECIFICAÇÃO '!$J48,TAXA!$A$2:$C$18,2,FALSE),"") | M48: =IFERROR(L48*H48,0) -> 0 | N48: =IFERROR(VLOOKUP('PRECIFICAÇÃO '!$J48,TAXA!$A$2:$C$18,3,FALSE),"") | O48: =IFERROR(N48*H48,0) -> 0 | P48: =IFERROR('PRECIFICAÇÃO '!$H48-'PRECIFICAÇÃO '!$M48-'PRECIFICAÇÃO '!$O48,0) -> 0 | Q48: {=IFERROR(INDEX(PROCEDIMENTOS!$D$2:$D$48,MATCH('PRECIFICAÇÃO '!$E48,PROCEDIMENTOS!$B$2:$B$48,0)),"")} | R48: =G48*3.12 -> 0 | S48: =IFERROR(H48*16.5%,0) -> 0 | U48: =IFERROR(H48*3%,0) -> 0 | V48: ='PRECIFICAÇÃO '!$Q48+'PRECIFICAÇÃO '!$R48+'PRECIFICAÇÃO '!$S48+'PRECIFICAÇÃO '!$T48+'PRECIFICAÇÃO '!$U48 -> 0 | W48: =IFERROR(V48/H48,0) -> 0 | X48: =IFERROR(P48-V48,0) -> 0 | Y48: =IFERROR(X48/H48,0) -> 0 | Z48: =IFERROR(X48*20%,0) -> 0 | AA48: =IFERROR(X48*80%,0) -> 0
F49: {=IFERROR(INDEX(PROCEDIMENTOS!$A$2:$A$48,MATCH('PRECIFICAÇÃO '!$E49,PROCEDIMENTOS!$B$2:$B$48,0)),"")} | G49: {=IFERROR(INDEX(PROCEDIMENTOS!$C$2:$C$48,MATCH('PRECIFICAÇÃO '!$E49,PROCEDIMENTOS!$B$2:$B$48,0)),"")} | L49: =IFERROR(VLOOKUP('PRECIFICAÇÃO '!$J49,TAXA!$A$2:$C$18,2,FALSE),"") | M49: =IFERROR(L49*H49,0) -> 0 | N49: =IFERROR(VLOOKUP('PRECIFICAÇÃO '!$J49,TAXA!$A$2:$C$18,3,FALSE),"") | O49: =IFERROR(N49*H49,0) -> 0 | P49: =IFERROR('PRECIFICAÇÃO '!$H49-'PRECIFICAÇÃO '!$M49-'PRECIFICAÇÃO '!$O49,0) -> 0 | Q49: {=IFERROR(INDEX(PROCEDIMENTOS!$D$2:$D$48,MATCH('PRECIFICAÇÃO '!$E49,PROCEDIMENTOS!$B$2:$B$48,0)),"")} | R49: =G49*3.12 -> 0 | S49: =IFERROR(H49*16.5%,0) -> 0 | U49: =IFERROR(H49*3%,0) -> 0 | V49: ='PRECIFICAÇÃO '!$Q49+'PRECIFICAÇÃO '!$R49+'PRECIFICAÇÃO '!$S49+'PRECIFICAÇÃO '!$T49+'PRECIFICAÇÃO '!$U49 -> 0 | W49: =IFERROR(V49/H49,0) -> 0 | X49: =IFERROR(P49-V49,0) -> 0 | Y49: =IFERROR(X49/H49,0) -> 0 | Z49: =IFERROR(X49*20%,0) -> 0 | AA49: =IFERROR(X49*80%,0) -> 0
F50: {=IFERROR(INDEX(PROCEDIMENTOS!$A$2:$A$48,MATCH('PRECIFICAÇÃO '!$E50,PROCEDIMENTOS!$B$2:$B$48,0)),"")} | G50: {=IFERROR(INDEX(PROCEDIMENTOS!$C$2:$C$48,MATCH('PRECIFICAÇÃO '!$E50,PROCEDIMENTOS!$B$2:$B$48,0)),"")} | L50: =IFERROR(VLOOKUP('PRECIFICAÇÃO '!$J50,TAXA!$A$2:$C$18,2,FALSE),"") | M50: =IFERROR(L50*H50,0) -> 0 | N50: =IFERROR(VLOOKUP('PRECIFICAÇÃO '!$J50,TAXA!$A$2:$C$18,3,FALSE),"") | O50: =IFERROR(N50*H50,0) -> 0 | P50: =IFERROR('PRECIFICAÇÃO '!$H50-'PRECIFICAÇÃO '!$M50-'PRECIFICAÇÃO '!$O50,0) -> 0 | Q50: {=IFERROR(INDEX(PROCEDIMENTOS!$D$2:$D$48,MATCH('PRECIFICAÇÃO '!$E50,PROCEDIMENTOS!$B$2:$B$48,0)),"")} | R50: =G50*3.12 -> 0 | S50: =IFERROR(H50*16.5%,0) -> 0 | U50: =IFERROR(H50*3%,0) -> 0 | V50: ='PRECIFICAÇÃO '!$Q50+'PRECIFICAÇÃO '!$R50+'PRECIFICAÇÃO '!$S50+'PRECIFICAÇÃO '!$T50+'PRECIFICAÇÃO '!$U50 -> 0 | W50: =IFERROR(V50/H50,0) -> 0 | X50: =IFERROR(P50-V50,0) -> 0 | Y50: =IFERROR(X50/H50,0) -> 0 | Z50: =IFERROR(X50*20%,0) -> 0 | AA50: =IFERROR(X50*80%,0) -> 0
F51: {=IFERROR(INDEX(PROCEDIMENTOS!$A$2:$A$48,MATCH('PRECIFICAÇÃO '!$E51,PROCEDIMENTOS!$B$2:$B$48,0)),"")} | G51: {=IFERROR(INDEX(PROCEDIMENTOS!$C$2:$C$48,MATCH('PRECIFICAÇÃO '!$E51,PROCEDIMENTOS!$B$2:$B$48,0)),"")} | L51: =IFERROR(VLOOKUP('PRECIFICAÇÃO '!$J51,TAXA!$A$2:$C$18,2,FALSE),"") | M51: =IFERROR(L51*H51,0) -> 0 | N51: =IFERROR(VLOOKUP('PRECIFICAÇÃO '!$J51,TAXA!$A$2:$C$18,3,FALSE),"") | O51: =IFERROR(N51*H51,0) -> 0 | P51: =IFERROR('PRECIFICAÇÃO '!$H51-'PRECIFICAÇÃO '!$M51-'PRECIFICAÇÃO '!$O51,0) -> 0 | Q51: {=IFERROR(INDEX(PROCEDIMENTOS!$D$2:$D$48,MATCH('PRECIFICAÇÃO '!$E51,PROCEDIMENTOS!$B$2:$B$48,0)),"")} | R51: =G51*3.12 -> 0 | S51: =IFERROR(H51*16.5%,0) -> 0 | U51: =IFERROR(H51*3%,0) -> 0 | V51: ='PRECIFICAÇÃO '!$Q51+'PRECIFICAÇÃO '!$R51+'PRECIFICAÇÃO '!$S51+'PRECIFICAÇÃO '!$T51+'PRECIFICAÇÃO '!$U51 -> 0 | W51: =IFERROR(V51/H51,0) -> 0 | X51: =IFERROR(P51-V51,0) -> 0 | Y51: =IFERROR(X51/H51,0) -> 0 | Z51: =IFERROR(X51*20%,0) -> 0 | AA51: =IFERROR(X51*80%,0) -> 0
F52: {=IFERROR(INDEX(PROCEDIMENTOS!$A$2:$A$48,MATCH('PRECIFICAÇÃO '!$E52,PROCEDIMENTOS!$B$2:$B$48,0)),"")} | G52: {=IFERROR(INDEX(PROCEDIMENTOS!$C$2:$C$48,MATCH('PRECIFICAÇÃO '!$E52,PROCEDIMENTOS!$B$2:$B$48,0)),"")} | L52: =IFERROR(VLOOKUP('PRECIFICAÇÃO '!$J52,TAXA!$A$2:$C$18,2,FALSE),"") | M52: =IFERROR(L52*H52,0) -> 0 | N52: =IFERROR(VLOOKUP('PRECIFICAÇÃO '!$J52,TAXA!$A$2:$C$18,3,FALSE),"") | O52: =IFERROR(N52*H52,0) -> 0 | P52: =IFERROR('PRECIFICAÇÃO '!$H52-'PRECIFICAÇÃO '!$M52-'PRECIFICAÇÃO '!$O52,0) -> 0 | R52: =G52*3.12 -> 0 | S52: =IFERROR(H52*16.5%,0) -> 0 | U52: =IFERROR(H52*3%,0) -> 0 | V52: ='PRECIFICAÇÃO '!$Q52+'PRECIFICAÇÃO '!$R52+'PRECIFICAÇÃO '!$S52+'PRECIFICAÇÃO '!$T52+'PRECIFICAÇÃO '!$U52 -> 0 | W52: =IFERROR(V52/H52,0) -> 0 | X52: =IFERROR(P52-V52,0) -> 0 | Y52: =IFERROR(X52/H52,0) -> 0 | Z52: =IFERROR(X52*20%,0) -> 0 | AA52: =IFERROR(X52*80%,0) -> 0
F53: {=IFERROR(INDEX(PROCEDIMENTOS!$A$2:$A$48,MATCH('PRECIFICAÇÃO '!$E53,PROCEDIMENTOS!$B$2:$B$48,0)),"")} | G53: {=IFERROR(INDEX(PROCEDIMENTOS!$C$2:$C$48,MATCH('PRECIFICAÇÃO '!$E53,PROCEDIMENTOS!$B$2:$B$48,0)),"")} | L53: =IFERROR(VLOOKUP('PRECIFICAÇÃO '!$J53,TAXA!$A$2:$C$18,2,FALSE),"") | M53: =IFERROR(L53*H53,0) -> 0 | N53: =IFERROR(VLOOKUP('PRECIFICAÇÃO '!$J53,TAXA!$A$2:$C$18,3,FALSE),"") | O53: =IFERROR(N53*H53,0) -> 0 | P53: =IFERROR('PRECIFICAÇÃO '!$H53-'PRECIFICAÇÃO '!$M53-'PRECIFICAÇÃO '!$O53,0) -> 0 | Q53: {=IFERROR(INDEX(PROCEDIMENTOS!$D$2:$D$48,MATCH('PRECIFICAÇÃO '!$E53,PROCEDIMENTOS!$B$2:$B$48,0)),"")} | R53: =G53*3.12 -> 0 | S53: =IFERROR(H53*16.5%,0) -> 0 | U53: =IFERROR(H53*3%,0) -> 0 | V53: ='PRECIFICAÇÃO '!$Q53+'PRECIFICAÇÃO '!$R53+'PRECIFICAÇÃO '!$S53+'PRECIFICAÇÃO '!$T53+'PRECIFICAÇÃO '!$U53 -> 0 | W53: =IFERROR(V53/H53,0) -> 0 | X53: =IFERROR(P53-V53,0) -> 0 | Y53: =IFERROR(X53/H53,0) -> 0 | Z53: =IFERROR(X53*20%,0) -> 0 | AA53: =IFERROR(X53*80%,0) -> 0
F54: {=IFERROR(INDEX(PROCEDIMENTOS!$A$2:$A$48,MATCH('PRECIFICAÇÃO '!$E54,PROCEDIMENTOS!$B$2:$B$48,0)),"")} | G54: {=IFERROR(INDEX(PROCEDIMENTOS!$C$2:$C$48,MATCH('PRECIFICAÇÃO '!$E54,PROCEDIMENTOS!$B$2:$B$48,0)),"")} | L54: =IFERROR(VLOOKUP('PRECIFICAÇÃO '!$J54,TAXA!$A$2:$C$18,2,FALSE),"") | M54: =IFERROR(L54*H54,0) -> 0 | N54: =IFERROR(VLOOKUP('PRECIFICAÇÃO '!$J54,TAXA!$A$2:$C$18,3,FALSE),"") | O54: =IFERROR(N54*H54,0) -> 0 | P54: =IFERROR('PRECIFICAÇÃO '!$H54-'PRECIFICAÇÃO '!$M54-'PRECIFICAÇÃO '!$O54,0) -> 0 | Q54: {=IFERROR(INDEX(PROCEDIMENTOS!$D$2:$D$48,MATCH('PRECIFICAÇÃO '!$E54,PROCEDIMENTOS!$B$2:$B$48,0)),"")} | R54: =G54*3.12 -> 0 | S54: =IFERROR(H54*16.5%,0) -> 0 | U54: =IFERROR(H54*3%,0) -> 0 | V54: ='PRECIFICAÇÃO '!$Q54+'PRECIFICAÇÃO '!$R54+'PRECIFICAÇÃO '!$S54+'PRECIFICAÇÃO '!$T54+'PRECIFICAÇÃO '!$U54 -> 0 | W54: =IFERROR(V54/H54,0) -> 0 | X54: =IFERROR(P54-V54,0) -> 0 | Y54: =IFERROR(X54/H54,0) -> 0 | Z54: =IFERROR(X54*20%,0) -> 0 | AA54: =IFERROR(X54*80%,0) -> 0
F55: {=IFERROR(INDEX(PROCEDIMENTOS!$A$2:$A$48,MATCH('PRECIFICAÇÃO '!$E55,PROCEDIMENTOS!$B$2:$B$48,0)),"")} | G55: {=IFERROR(INDEX(PROCEDIMENTOS!$C$2:$C$48,MATCH('PRECIFICAÇÃO '!$E55,PROCEDIMENTOS!$B$2:$B$48,0)),"")} | L55: =IFERROR(VLOOKUP('PRECIFICAÇÃO '!$J55,TAXA!$A$2:$C$18,2,FALSE),"") | M55: =IFERROR(L55*H55,0) -> 0 | N55: =IFERROR(VLOOKUP('PRECIFICAÇÃO '!$J55,TAXA!$A$2:$C$18,3,FALSE),"") | O55: =IFERROR(N55*H55,0) -> 0 | P55: =IFERROR('PRECIFICAÇÃO '!$H55-'PRECIFICAÇÃO '!$M55-'PRECIFICAÇÃO '!$O55,0) -> 0 | Q55: {=IFERROR(INDEX(PROCEDIMENTOS!$D$2:$D$48,MATCH('PRECIFICAÇÃO '!$E55,PROCEDIMENTOS!$B$2:$B$48,0)),"")} | R55: =G55*3.12 -> 0 | S55: =IFERROR(H55*16.5%,0) -> 0 | U55: =IFERROR(H55*3%,0) -> 0 | V55: ='PRECIFICAÇÃO '!$Q55+'PRECIFICAÇÃO '!$R55+'PRECIFICAÇÃO '!$S55+'PRECIFICAÇÃO '!$T55+'PRECIFICAÇÃO '!$U55 -> 0 | W55: =IFERROR(V55/H55,0) -> 0 | X55: =IFERROR(P55-V55,0) -> 0 | Y55: =IFERROR(X55/H55,0) -> 0 | Z55: =IFERROR(X55*20%,0) -> 0 | AA55: =IFERROR(X55*80%,0) -> 0
F56: {=IFERROR(INDEX(PROCEDIMENTOS!$A$2:$A$48,MATCH('PRECIFICAÇÃO '!$E56,PROCEDIMENTOS!$B$2:$B$48,0)),"")} | G56: {=IFERROR(INDEX(PROCEDIMENTOS!$C$2:$C$48,MATCH('PRECIFICAÇÃO '!$E56,PROCEDIMENTOS!$B$2:$B$48,0)),"")} | L56: =IFERROR(VLOOKUP('PRECIFICAÇÃO '!$J56,TAXA!$A$2:$C$18,2,FALSE),"") | M56: =IFERROR(L56*H56,0) -> 0 | N56: =IFERROR(VLOOKUP('PRECIFICAÇÃO '!$J56,TAXA!$A$2:$C$18,3,FALSE),"") | O56: =IFERROR(N56*H56,0) -> 0 | P56: =IFERROR('PRECIFICAÇÃO '!$H56-'PRECIFICAÇÃO '!$M56-'PRECIFICAÇÃO '!$O56,0) -> 0 | R56: =G56*3.12 -> 0 | S56: =IFERROR(H56*16.5%,0) -> 0 | U56: =IFERROR(H56*3%,0) -> 0 | V56: ='PRECIFICAÇÃO '!$Q56+'PRECIFICAÇÃO '!$R56+'PRECIFICAÇÃO '!$S56+'PRECIFICAÇÃO '!$T56+'PRECIFICAÇÃO '!$U56 -> 0 | W56: =IFERROR(V56/H56,0) -> 0 | X56: =IFERROR(P56-V56,0) -> 0 | Y56: =IFERROR(X56/H56,0) -> 0 | Z56: =IFERROR(X56*20%,0) -> 0 | AA56: =IFERROR(X56*80%,0) -> 0
F57: {=IFERROR(INDEX(PROCEDIMENTOS!$A$2:$A$48,MATCH('PRECIFICAÇÃO '!$E57,PROCEDIMENTOS!$B$2:$B$48,0)),"")} | G57: {=IFERROR(INDEX(PROCEDIMENTOS!$C$2:$C$48,MATCH('PRECIFICAÇÃO '!$E57,PROCEDIMENTOS!$B$2:$B$48,0)),"")} | L57: =IFERROR(VLOOKUP('PRECIFICAÇÃO '!$J57,TAXA!$A$2:$C$18,2,FALSE),"") | M57: =IFERROR(L57*H57,0) -> 0 | N57: =IFERROR(VLOOKUP('PRECIFICAÇÃO '!$J57,TAXA!$A$2:$C$18,3,FALSE),"") | O57: =IFERROR(N57*H57,0) -> 0 | P57: =IFERROR('PRECIFICAÇÃO '!$H57-'PRECIFICAÇÃO '!$M57-'PRECIFICAÇÃO '!$O57,0) -> 0 | Q57: {=IFERROR(INDEX(PROCEDIMENTOS!$D$2:$D$48,MATCH('PRECIFICAÇÃO '!$E57,PROCEDIMENTOS!$B$2:$B$48,0)),"")} | R57: =G57*3.12 -> 0 | S57: =IFERROR(H57*16.5%,0) -> 0 | U57: =IFERROR(H57*3%,0) -> 0 | V57: ='PRECIFICAÇÃO '!$Q57+'PRECIFICAÇÃO '!$R57+'PRECIFICAÇÃO '!$S57+'PRECIFICAÇÃO '!$T57+'PRECIFICAÇÃO '!$U57 -> 0 | W57: =IFERROR(V57/H57,0) -> 0 | X57: =IFERROR(P57-V57,0) -> 0 | Y57: =IFERROR(X57/H57,0) -> 0 | Z57: =IFERROR(X57*20%,0) -> 0 | AA57: =IFERROR(X57*80%,0) -> 0
F58: {=IFERROR(INDEX(PROCEDIMENTOS!$A$2:$A$48,MATCH('PRECIFICAÇÃO '!$E58,PROCEDIMENTOS!$B$2:$B$48,0)),"")} | G58: {=IFERROR(INDEX(PROCEDIMENTOS!$C$2:$C$48,MATCH('PRECIFICAÇÃO '!$E58,PROCEDIMENTOS!$B$2:$B$48,0)),"")} | L58: =IFERROR(VLOOKUP('PRECIFICAÇÃO '!$J58,TAXA!$A$2:$C$18,2,FALSE),"") | M58: =IFERROR(L58*H58,0) -> 0 | N58: =IFERROR(VLOOKUP('PRECIFICAÇÃO '!$J58,TAXA!$A$2:$C$18,3,FALSE),"") | O58: =IFERROR(N58*H58,0) -> 0 | P58: =IFERROR('PRECIFICAÇÃO '!$H58-'PRECIFICAÇÃO '!$M58-'PRECIFICAÇÃO '!$O58,0) -> 0 | Q58: {=IFERROR(INDEX(PROCEDIMENTOS!$D$2:$D$48,MATCH('PRECIFICAÇÃO '!$E58,PROCEDIMENTOS!$B$2:$B$48,0)),"")} | R58: =G58*3.12 -> 0 | S58: =IFERROR(H58*16.5%,0) -> 0 | U58: =IFERROR(H58*3%,0) -> 0 | V58: ='PRECIFICAÇÃO '!$Q58+'PRECIFICAÇÃO '!$R58+'PRECIFICAÇÃO '!$S58+'PRECIFICAÇÃO '!$T58+'PRECIFICAÇÃO '!$U58 -> 0 | W58: =IFERROR(V58/H58,0) -> 0 | X58: =IFERROR(P58-V58,0) -> 0 | Y58: =IFERROR(X58/H58,0) -> 0 | Z58: =IFERROR(X58*20%,0) -> 0 | AA58: =IFERROR(X58*80%,0) -> 0
F59: {=IFERROR(INDEX(PROCEDIMENTOS!$A$2:$A$48,MATCH('PRECIFICAÇÃO '!$E59,PROCEDIMENTOS!$B$2:$B$48,0)),"")} | G59: {=IFERROR(INDEX(PROCEDIMENTOS!$C$2:$C$48,MATCH('PRECIFICAÇÃO '!$E59,PROCEDIMENTOS!$B$2:$B$48,0)),"")} | L59: =IFERROR(VLOOKUP('PRECIFICAÇÃO '!$J59,TAXA!$A$2:$C$18,2,FALSE),"") | M59: =IFERROR(L59*H59,0) -> 0 | N59: =IFERROR(VLOOKUP('PRECIFICAÇÃO '!$J59,TAXA!$A$2:$C$18,3,FALSE),"") | O59: =IFERROR(N59*H59,0) -> 0 | P59: =IFERROR('PRECIFICAÇÃO '!$H59-'PRECIFICAÇÃO '!$M59-'PRECIFICAÇÃO '!$O59,0) -> 0 | Q59: {=IFERROR(INDEX(PROCEDIMENTOS!$D$2:$D$48,MATCH('PRECIFICAÇÃO '!$E59,PROCEDIMENTOS!$B$2:$B$48,0)),"")} | R59: =G59*3.12 -> 0 | S59: =IFERROR(H59*16.5%,0) -> 0 | U59: =IFERROR(H59*3%,0) -> 0 | V59: ='PRECIFICAÇÃO '!$Q59+'PRECIFICAÇÃO '!$R59+'PRECIFICAÇÃO '!$S59+'PRECIFICAÇÃO '!$T59+'PRECIFICAÇÃO '!$U59 -> 0 | W59: =IFERROR(V59/H59,0) -> 0 | X59: =IFERROR(P59-V59,0) -> 0 | Y59: =IFERROR(X59/H59,0) -> 0 | Z59: =IFERROR(X59*20%,0) -> 0 | AA59: =IFERROR(X59*80%,0) -> 0
F60: {=IFERROR(INDEX(PROCEDIMENTOS!$A$2:$A$48,MATCH('PRECIFICAÇÃO '!$E60,PROCEDIMENTOS!$B$2:$B$48,0)),"")} | G60: {=IFERROR(INDEX(PROCEDIMENTOS!$C$2:$C$48,MATCH('PRECIFICAÇÃO '!$E60,PROCEDIMENTOS!$B$2:$B$48,0)),"")} | L60: =IFERROR(VLOOKUP('PRECIFICAÇÃO '!$J60,TAXA!$A$2:$C$18,2,FALSE),"") | M60: =IFERROR(L60*H60,0) -> 0 | N60: =IFERROR(VLOOKUP('PRECIFICAÇÃO '!$J60,TAXA!$A$2:$C$18,3,FALSE),"") | O60: =IFERROR(N60*H60,0) -> 0 | P60: =IFERROR('PRECIFICAÇÃO '!$H60-'PRECIFICAÇÃO '!$M60-'PRECIFICAÇÃO '!$O60,0) -> 0 | Q60: {=IFERROR(INDEX(PROCEDIMENTOS!$D$2:$D$48,MATCH('PRECIFICAÇÃO '!$E60,PROCEDIMENTOS!$B$2:$B$48,0)),"")} | R60: =G60*3.12 -> 0 | S60: =IFERROR(H60*16.5%,0) -> 0 | U60: =IFERROR(H60*3%,0) -> 0 | V60: ='PRECIFICAÇÃO '!$Q60+'PRECIFICAÇÃO '!$R60+'PRECIFICAÇÃO '!$S60+'PRECIFICAÇÃO '!$T60+'PRECIFICAÇÃO '!$U60 -> 0 | W60: =IFERROR(V60/H60,0) -> 0 | X60: =IFERROR(P60-V60,0) -> 0 | Y60: =IFERROR(X60/H60,0) -> 0 | Z60: =IFERROR(X60*20%,0) -> 0 | AA60: =IFERROR(X60*80%,0) -> 0
F61: {=IFERROR(INDEX(PROCEDIMENTOS!$A$2:$A$48,MATCH('PRECIFICAÇÃO '!$E61,PROCEDIMENTOS!$B$2:$B$48,0)),"")} | G61: {=IFERROR(INDEX(PROCEDIMENTOS!$C$2:$C$48,MATCH('PRECIFICAÇÃO '!$E61,PROCEDIMENTOS!$B$2:$B$48,0)),"")} | L61: =IFERROR(VLOOKUP('PRECIFICAÇÃO '!$J61,TAXA!$A$2:$C$18,2,FALSE),"") | M61: =IFERROR(L61*H61,0) -> 0 | N61: =IFERROR(VLOOKUP('PRECIFICAÇÃO '!$J61,TAXA!$A$2:$C$18,3,FALSE),"") | O61: =IFERROR(N61*H61,0) -> 0 | P61: =IFERROR('PRECIFICAÇÃO '!$H61-'PRECIFICAÇÃO '!$M61-'PRECIFICAÇÃO '!$O61,0) -> 0 | Q61: {=IFERROR(INDEX(PROCEDIMENTOS!$D$2:$D$48,MATCH('PRECIFICAÇÃO '!$E61,PROCEDIMENTOS!$B$2:$B$48,0)),"")} | R61: =G61*3.12 -> 0 | S61: =IFERROR(H61*16.5%,0) -> 0 | U61: =IFERROR(H61*3%,0) -> 0 | V61: ='PRECIFICAÇÃO '!$Q61+'PRECIFICAÇÃO '!$R61+'PRECIFICAÇÃO '!$S61+'PRECIFICAÇÃO '!$T61+'PRECIFICAÇÃO '!$U61 -> 0 | W61: =IFERROR(V61/H61,0) -> 0 | X61: =IFERROR(P61-V61,0) -> 0 | Y61: =IFERROR(X61/H61,0) -> 0 | Z61: =IFERROR(X61*20%,0) -> 0 | AA61: =IFERROR(X61*80%,0) -> 0
F62: {=IFERROR(INDEX(PROCEDIMENTOS!$A$2:$A$48,MATCH('PRECIFICAÇÃO '!$E62,PROCEDIMENTOS!$B$2:$B$48,0)),"")} | G62: {=IFERROR(INDEX(PROCEDIMENTOS!$C$2:$C$48,MATCH('PRECIFICAÇÃO '!$E62,PROCEDIMENTOS!$B$2:$B$48,0)),"")} | L62: =IFERROR(VLOOKUP('PRECIFICAÇÃO '!$J62,TAXA!$A$2:$C$18,2,FALSE),"") | M62: =IFERROR(L62*H62,0) -> 0 | N62: =IFERROR(VLOOKUP('PRECIFICAÇÃO '!$J62,TAXA!$A$2:$C$18,3,FALSE),"") | O62: =IFERROR(N62*H62,0) -> 0 | P62: =IFERROR('PRECIFICAÇÃO '!$H62-'PRECIFICAÇÃO '!$M62-'PRECIFICAÇÃO '!$O62,0) -> 0 | R62: =G62*3.12 -> 0 | S62: =IFERROR(H62*16.5%,0) -> 0 | U62: =IFERROR(H62*3%,0) -> 0 | V62: ='PRECIFICAÇÃO '!$Q62+'PRECIFICAÇÃO '!$R62+'PRECIFICAÇÃO '!$S62+'PRECIFICAÇÃO '!$T62+'PRECIFICAÇÃO '!$U62 -> 0 | W62: =IFERROR(V62/H62,0) -> 0 | X62: =IFERROR(P62-V62,0) -> 0 | Y62: =IFERROR(X62/H62,0) -> 0 | Z62: =IFERROR(X62*20%,0) -> 0 | AA62: =IFERROR(X62*80%,0) -> 0
F63: {=IFERROR(INDEX(PROCEDIMENTOS!$A$2:$A$48,MATCH('PRECIFICAÇÃO '!$E63,PROCEDIMENTOS!$B$2:$B$48,0)),"")} | G63: {=IFERROR(INDEX(PROCEDIMENTOS!$C$2:$C$48,MATCH('PRECIFICAÇÃO '!$E63,PROCEDIMENTOS!$B$2:$B$48,0)),"")} | L63: =IFERROR(VLOOKUP('PRECIFICAÇÃO '!$J63,TAXA!$A$2:$C$18,2,FALSE),"") | M63: =IFERROR(L63*H63,0) -> 0 | N63: =IFERROR(VLOOKUP('PRECIFICAÇÃO '!$J63,TAXA!$A$2:$C$18,3,FALSE),"") | O63: =IFERROR(N63*H63,0) -> 0 | P63: =IFERROR('PRECIFICAÇÃO '!$H63-'PRECIFICAÇÃO '!$M63-'PRECIFICAÇÃO '!$O63,0) -> 0 | Q63: {=IFERROR(INDEX(PROCEDIMENTOS!$D$2:$D$48,MATCH('PRECIFICAÇÃO '!$E63,PROCEDIMENTOS!$B$2:$B$48,0)),"")} | R63: =G63*3.12 -> 0 | S63: =IFERROR(H63*16.5%,0) -> 0 | U63: =IFERROR(H63*3%,0) -> 0 | V63: ='PRECIFICAÇÃO '!$Q63+'PRECIFICAÇÃO '!$R63+'PRECIFICAÇÃO '!$S63+'PRECIFICAÇÃO '!$T63+'PRECIFICAÇÃO '!$U63 -> 0 | W63: =IFERROR(V63/H63,0) -> 0 | X63: =IFERROR(P63-V63,0) -> 0 | Y63: =IFERROR(X63/H63,0) -> 0 | Z63: =IFERROR(X63*20%,0) -> 0 | AA63: =IFERROR(X63*80%,0) -> 0
F64: {=IFERROR(INDEX(PROCEDIMENTOS!$A$2:$A$48,MATCH('PRECIFICAÇÃO '!$E64,PROCEDIMENTOS!$B$2:$B$48,0)),"")} | G64: {=IFERROR(INDEX(PROCEDIMENTOS!$C$2:$C$48,MATCH('PRECIFICAÇÃO '!$E64,PROCEDIMENTOS!$B$2:$B$48,0)),"")} | L64: =IFERROR(VLOOKUP('PRECIFICAÇÃO '!$J64,TAXA!$A$2:$C$18,2,FALSE),"") | M64: =IFERROR(L64*H64,0) -> 0 | N64: =IFERROR(VLOOKUP('PRECIFICAÇÃO '!$J64,TAXA!$A$2:$C$18,3,FALSE),"") | O64: =IFERROR(N64*H64,0) -> 0 | P64: =IFERROR('PRECIFICAÇÃO '!$H64-'PRECIFICAÇÃO '!$M64-'PRECIFICAÇÃO '!$O64,0) -> 0 | Q64: {=IFERROR(INDEX(PROCEDIMENTOS!$D$2:$D$48,MATCH('PRECIFICAÇÃO '!$E64,PROCEDIMENTOS!$B$2:$B$48,0)),"")} | R64: =G64*3.12 -> 0 | S64: =IFERROR(H64*16.5%,0) -> 0 | U64: =IFERROR(H64*3%,0) -> 0 | V64: ='PRECIFICAÇÃO '!$Q64+'PRECIFICAÇÃO '!$R64+'PRECIFICAÇÃO '!$S64+'PRECIFICAÇÃO '!$T64+'PRECIFICAÇÃO '!$U64 -> 0 | W64: =IFERROR(V64/H64,0) -> 0 | X64: =IFERROR(P64-V64,0) -> 0 | Y64: =IFERROR(X64/H64,0) -> 0 | Z64: =IFERROR(X64*20%,0) -> 0 | AA64: =IFERROR(X64*80%,0) -> 0
F65: {=IFERROR(INDEX(PROCEDIMENTOS!$A$2:$A$48,MATCH('PRECIFICAÇÃO '!$E65,PROCEDIMENTOS!$B$2:$B$48,0)),"")} | G65: {=IFERROR(INDEX(PROCEDIMENTOS!$C$2:$C$48,MATCH('PRECIFICAÇÃO '!$E65,PROCEDIMENTOS!$B$2:$B$48,0)),"")} | L65: =IFERROR(VLOOKUP('PRECIFICAÇÃO '!$J65,TAXA!$A$2:$C$18,2,FALSE),"") | M65: =IFERROR(L65*H65,0) -> 0 | N65: =IFERROR(VLOOKUP('PRECIFICAÇÃO '!$J65,TAXA!$A$2:$C$18,3,FALSE),"") | O65: =IFERROR(N65*H65,0) -> 0 | P65: =IFERROR('PRECIFICAÇÃO '!$H65-'PRECIFICAÇÃO '!$M65-'PRECIFICAÇÃO '!$O65,0) -> 0 | R65: =G65*3.12 -> 0 | S65: =IFERROR(H65*16.5%,0) -> 0 | U65: =IFERROR(H65*3%,0) -> 0 | V65: ='PRECIFICAÇÃO '!$Q65+'PRECIFICAÇÃO '!$R65+'PRECIFICAÇÃO '!$S65+'PRECIFICAÇÃO '!$T65+'PRECIFICAÇÃO '!$U65 -> 0 | W65: =IFERROR(V65/H65,0) -> 0 | X65: =IFERROR(P65-V65,0) -> 0 | Y65: =IFERROR(X65/H65,0) -> 0 | Z65: =IFERROR(X65*20%,0) -> 0 | AA65: =IFERROR(X65*80%,0) -> 0
F66: {=IFERROR(INDEX(PROCEDIMENTOS!$A$2:$A$48,MATCH('PRECIFICAÇÃO '!$E66,PROCEDIMENTOS!$B$2:$B$48,0)),"")} | G66: {=IFERROR(INDEX(PROCEDIMENTOS!$C$2:$C$48,MATCH('PRECIFICAÇÃO '!$E66,PROCEDIMENTOS!$B$2:$B$48,0)),"")} | L66: =IFERROR(VLOOKUP('PRECIFICAÇÃO '!$J66,TAXA!$A$2:$C$18,2,FALSE),"") | M66: =IFERROR(L66*H66,0) -> 0 | N66: =IFERROR(VLOOKUP('PRECIFICAÇÃO '!$J66,TAXA!$A$2:$C$18,3,FALSE),"") | O66: =IFERROR(N66*H66,0) -> 0 | P66: =IFERROR('PRECIFICAÇÃO '!$H66-'PRECIFICAÇÃO '!$M66-'PRECIFICAÇÃO '!$O66,0) -> 0 | Q66: {=IFERROR(INDEX(PROCEDIMENTOS!$D$2:$D$48,MATCH('PRECIFICAÇÃO '!$E66,PROCEDIMENTOS!$B$2:$B$48,0)),"")} | R66: =G66*3.12 -> 0 | S66: =IFERROR(H66*16.5%,0) -> 0 | U66: =IFERROR(H66*3%,0) -> 0 | V66: ='PRECIFICAÇÃO '!$Q66+'PRECIFICAÇÃO '!$R66+'PRECIFICAÇÃO '!$S66+'PRECIFICAÇÃO '!$T66+'PRECIFICAÇÃO '!$U66 -> 0 | W66: =IFERROR(V66/H66,0) -> 0 | X66: =IFERROR(P66-V66,0) -> 0 | Y66: =IFERROR(X66/H66,0) -> 0 | Z66: =IFERROR(X66*20%,0) -> 0 | AA66: =IFERROR(X66*80%,0) -> 0
F67: {=IFERROR(INDEX(PROCEDIMENTOS!$A$2:$A$48,MATCH('PRECIFICAÇÃO '!$E67,PROCEDIMENTOS!$B$2:$B$48,0)),"")} | G67: {=IFERROR(INDEX(PROCEDIMENTOS!$C$2:$C$48,MATCH('PRECIFICAÇÃO '!$E67,PROCEDIMENTOS!$B$2:$B$48,0)),"")} | L67: =IFERROR(VLOOKUP('PRECIFICAÇÃO '!$J67,TAXA!$A$2:$C$18,2,FALSE),"") | M67: =IFERROR(L67*H67,0) -> 0 | N67: =IFERROR(VLOOKUP('PRECIFICAÇÃO '!$J67,TAXA!$A$2:$C$18,3,FALSE),"") | O67: =IFERROR(N67*H67,0) -> 0 | P67: =IFERROR('PRECIFICAÇÃO '!$H67-'PRECIFICAÇÃO '!$M67-'PRECIFICAÇÃO '!$O67,0) -> 0 | R67: =G67*3.12 -> 0 | S67: =IFERROR(H67*16.5%,0) -> 0 | U67: =IFERROR(H67*3%,0) -> 0 | V67: ='PRECIFICAÇÃO '!$Q67+'PRECIFICAÇÃO '!$R67+'PRECIFICAÇÃO '!$S67+'PRECIFICAÇÃO '!$T67+'PRECIFICAÇÃO '!$U67 -> 0 | W67: =IFERROR(V67/H67,0) -> 0 | X67: =IFERROR(P67-V67,0) -> 0 | Y67: =IFERROR(X67/H67,0) -> 0 | Z67: =IFERROR(X67*20%,0) -> 0 | AA67: =IFERROR(X67*80%,0) -> 0
F68: {=IFERROR(INDEX(PROCEDIMENTOS!$A$2:$A$48,MATCH('PRECIFICAÇÃO '!$E68,PROCEDIMENTOS!$B$2:$B$48,0)),"")} | G68: {=IFERROR(INDEX(PROCEDIMENTOS!$C$2:$C$48,MATCH('PRECIFICAÇÃO '!$E68,PROCEDIMENTOS!$B$2:$B$48,0)),"")} | L68: =IFERROR(VLOOKUP('PRECIFICAÇÃO '!$J68,TAXA!$A$2:$C$18,2,FALSE),"") | M68: =IFERROR(L68*H68,0) -> 0 | N68: =IFERROR(VLOOKUP('PRECIFICAÇÃO '!$J68,TAXA!$A$2:$C$18,3,FALSE),"") | O68: =IFERROR(N68*H68,0) -> 0 | P68: =IFERROR('PRECIFICAÇÃO '!$H68-'PRECIFICAÇÃO '!$M68-'PRECIFICAÇÃO '!$O68,0) -> 0 | R68: =G68*3.12 -> 0 | S68: =IFERROR(H68*16.5%,0) -> 0 | U68: =IFERROR(H68*3%,0) -> 0 | V68: ='PRECIFICAÇÃO '!$Q68+'PRECIFICAÇÃO '!$R68+'PRECIFICAÇÃO '!$S68+'PRECIFICAÇÃO '!$T68+'PRECIFICAÇÃO '!$U68 -> 0 | W68: =IFERROR(V68/H68,0) -> 0 | X68: =IFERROR(P68-V68,0) -> 0 | Y68: =IFERROR(X68/H68,0) -> 0 | Z68: =IFERROR(X68*20%,0) -> 0 | AA68: =IFERROR(X68*80%,0) -> 0
F69: {=IFERROR(INDEX(PROCEDIMENTOS!$A$2:$A$48,MATCH('PRECIFICAÇÃO '!$E69,PROCEDIMENTOS!$B$2:$B$48,0)),"")} | G69: {=IFERROR(INDEX(PROCEDIMENTOS!$C$2:$C$48,MATCH('PRECIFICAÇÃO '!$E69,PROCEDIMENTOS!$B$2:$B$48,0)),"")} | L69: =IFERROR(VLOOKUP('PRECIFICAÇÃO '!$J69,TAXA!$A$2:$C$18,2,FALSE),"") | M69: =IFERROR(L69*H69,0) -> 0 | N69: =IFERROR(VLOOKUP('PRECIFICAÇÃO '!$J69,TAXA!$A$2:$C$18,3,FALSE),"") | O69: =IFERROR(N69*H69,0) -> 0 | P69: =IFERROR('PRECIFICAÇÃO '!$H69-'PRECIFICAÇÃO '!$M69-'PRECIFICAÇÃO '!$O69,0) -> 0 | Q69: {=IFERROR(INDEX(PROCEDIMENTOS!$D$2:$D$48,MATCH('PRECIFICAÇÃO '!$E69,PROCEDIMENTOS!$B$2:$B$48,0)),"")} | R69: =G69*3.12 -> 0 | S69: =IFERROR(H69*16.5%,0) -> 0 | U69: =IFERROR(H69*3%,0) -> 0 | V69: ='PRECIFICAÇÃO '!$Q69+'PRECIFICAÇÃO '!$R69+'PRECIFICAÇÃO '!$S69+'PRECIFICAÇÃO '!$T69+'PRECIFICAÇÃO '!$U69 -> 0 | W69: =IFERROR(V69/H69,0) -> 0 | X69: =IFERROR(P69-V69,0) -> 0 | Y69: =IFERROR(X69/H69,0) -> 0 | Z69: =IFERROR(X69*20%,0) -> 0 | AA69: =IFERROR(X69*80%,0) -> 0
F70: {=IFERROR(INDEX(PROCEDIMENTOS!$A$2:$A$48,MATCH('PRECIFICAÇÃO '!$E70,PROCEDIMENTOS!$B$2:$B$48,0)),"")} | G70: {=IFERROR(INDEX(PROCEDIMENTOS!$C$2:$C$48,MATCH('PRECIFICAÇÃO '!$E70,PROCEDIMENTOS!$B$2:$B$48,0)),"")} | L70: =IFERROR(VLOOKUP('PRECIFICAÇÃO '!$J70,TAXA!$A$2:$C$18,2,FALSE),"") | M70: =IFERROR(L70*H70,0) -> 0 | N70: =IFERROR(VLOOKUP('PRECIFICAÇÃO '!$J70,TAXA!$A$2:$C$18,3,FALSE),"") | O70: =IFERROR(N70*H70,0) -> 0 | P70: =IFERROR('PRECIFICAÇÃO '!$H70-'PRECIFICAÇÃO '!$M70-'PRECIFICAÇÃO '!$O70,0) -> 0 | Q70: {=IFERROR(INDEX(PROCEDIMENTOS!$D$2:$D$48,MATCH('PRECIFICAÇÃO '!$E70,PROCEDIMENTOS!$B$2:$B$48,0)),"")} | R70: =G70*3.12 -> 0 | S70: =IFERROR(H70*16.5%,0) -> 0 | U70: =IFERROR(H70*3%,0) -> 0 | V70: ='PRECIFICAÇÃO '!$Q70+'PRECIFICAÇÃO '!$R70+'PRECIFICAÇÃO '!$S70+'PRECIFICAÇÃO '!$T70+'PRECIFICAÇÃO '!$U70 -> 0 | W70: =IFERROR(V70/H70,0) -> 0 | X70: =IFERROR(P70-V70,0) -> 0 | Y70: =IFERROR(X70/H70,0) -> 0 | Z70: =IFERROR(X70*20%,0) -> 0 | AA70: =IFERROR(X70*80%,0) -> 0
F71: {=IFERROR(INDEX(PROCEDIMENTOS!$A$2:$A$48,MATCH('PRECIFICAÇÃO '!$E71,PROCEDIMENTOS!$B$2:$B$48,0)),"")} | G71: {=IFERROR(INDEX(PROCEDIMENTOS!$C$2:$C$48,MATCH('PRECIFICAÇÃO '!$E71,PROCEDIMENTOS!$B$2:$B$48,0)),"")} | L71: =IFERROR(VLOOKUP('PRECIFICAÇÃO '!$J71,TAXA!$A$2:$C$18,2,FALSE),"") | M71: =IFERROR(L71*H71,0) -> 0 | N71: =IFERROR(VLOOKUP('PRECIFICAÇÃO '!$J71,TAXA!$A$2:$C$18,3,FALSE),"") | O71: =IFERROR(N71*H71,0) -> 0 | P71: =IFERROR('PRECIFICAÇÃO '!$H71-'PRECIFICAÇÃO '!$M71-'PRECIFICAÇÃO '!$O71,0) -> 0 | Q71: {=IFERROR(INDEX(PROCEDIMENTOS!$D$2:$D$48,MATCH('PRECIFICAÇÃO '!$E71,PROCEDIMENTOS!$B$2:$B$48,0)),"")} | R71: =G71*3.12 -> 0 | S71: =IFERROR(H71*16.5%,0) -> 0 | U71: =IFERROR(H71*3%,0) -> 0 | V71: ='PRECIFICAÇÃO '!$Q71+'PRECIFICAÇÃO '!$R71+'PRECIFICAÇÃO '!$S71+'PRECIFICAÇÃO '!$T71+'PRECIFICAÇÃO '!$U71 -> 0 | W71: =IFERROR(V71/H71,0) -> 0 | X71: =IFERROR(P71-V71,0) -> 0 | Y71: =IFERROR(X71/H71,0) -> 0 | Z71: =IFERROR(X71*20%,0) -> 0 | AA71: =IFERROR(X71*80%,0) -> 0
F72: {=IFERROR(INDEX(PROCEDIMENTOS!$A$2:$A$48,MATCH('PRECIFICAÇÃO '!$E72,PROCEDIMENTOS!$B$2:$B$48,0)),"")} | G72: {=IFERROR(INDEX(PROCEDIMENTOS!$C$2:$C$48,MATCH('PRECIFICAÇÃO '!$E72,PROCEDIMENTOS!$B$2:$B$48,0)),"")} | L72: =IFERROR(VLOOKUP('PRECIFICAÇÃO '!$J72,TAXA!$A$2:$C$18,2,FALSE),"") | M72: =IFERROR(L72*H72,0) -> 0 | N72: =IFERROR(VLOOKUP('PRECIFICAÇÃO '!$J72,TAXA!$A$2:$C$18,3,FALSE),"") | O72: =IFERROR(N72*H72,0) -> 0 | P72: =IFERROR('PRECIFICAÇÃO '!$H72-'PRECIFICAÇÃO '!$M72-'PRECIFICAÇÃO '!$O72,0) -> 0 | Q72: {=IFERROR(INDEX(PROCEDIMENTOS!$D$2:$D$48,MATCH('PRECIFICAÇÃO '!$E72,PROCEDIMENTOS!$B$2:$B$48,0)),"")} | R72: =G72*3.12 -> 0 | S72: =IFERROR(H72*16.5%,0) -> 0 | U72: =IFERROR(H72*3%,0) -> 0 | V72: ='PRECIFICAÇÃO '!$Q72+'PRECIFICAÇÃO '!$R72+'PRECIFICAÇÃO '!$S72+'PRECIFICAÇÃO '!$T72+'PRECIFICAÇÃO '!$U72 -> 0 | W72: =IFERROR(V72/H72,0) -> 0 | X72: =IFERROR(P72-V72,0) -> 0 | Y72: =IFERROR(X72/H72,0) -> 0 | Z72: =IFERROR(X72*20%,0) -> 0 | AA72: =IFERROR(X72*80%,0) -> 0
F73: {=IFERROR(INDEX(PROCEDIMENTOS!$A$2:$A$48,MATCH('PRECIFICAÇÃO '!$E73,PROCEDIMENTOS!$B$2:$B$48,0)),"")} | G73: {=IFERROR(INDEX(PROCEDIMENTOS!$C$2:$C$48,MATCH('PRECIFICAÇÃO '!$E73,PROCEDIMENTOS!$B$2:$B$48,0)),"")} | L73: =IFERROR(VLOOKUP('PRECIFICAÇÃO '!$J73,TAXA!$A$2:$C$18,2,FALSE),"") | M73: =IFERROR(L73*H73,0) -> 0 | N73: =IFERROR(VLOOKUP('PRECIFICAÇÃO '!$J73,TAXA!$A$2:$C$18,3,FALSE),"") | O73: =IFERROR(N73*H73,0) -> 0 | P73: =IFERROR('PRECIFICAÇÃO '!$H73-'PRECIFICAÇÃO '!$M73-'PRECIFICAÇÃO '!$O73,0) -> 0 | R73: =G73*3.12 -> 0 | S73: =IFERROR(H73*16.5%,0) -> 0 | U73: =IFERROR(H73*3%,0) -> 0 | V73: ='PRECIFICAÇÃO '!$Q73+'PRECIFICAÇÃO '!$R73+'PRECIFICAÇÃO '!$S73+'PRECIFICAÇÃO '!$T73+'PRECIFICAÇÃO '!$U73 -> 0 | W73: =IFERROR(V73/H73,0) -> 0 | X73: =IFERROR(P73-V73,0) -> 0 | Y73: =IFERROR(X73/H73,0) -> 0 | Z73: =IFERROR(X73*20%,0) -> 0 | AA73: =IFERROR(X73*80%,0) -> 0
F74: {=IFERROR(INDEX(PROCEDIMENTOS!$A$2:$A$48,MATCH('PRECIFICAÇÃO '!$E74,PROCEDIMENTOS!$B$2:$B$48,0)),"")} | G74: {=IFERROR(INDEX(PROCEDIMENTOS!$C$2:$C$48,MATCH('PRECIFICAÇÃO '!$E74,PROCEDIMENTOS!$B$2:$B$48,0)),"")} | L74: =IFERROR(VLOOKUP('PRECIFICAÇÃO '!$J74,TAXA!$A$2:$C$18,2,FALSE),"") | M74: =IFERROR(L74*H74,0) -> 0 | N74: =IFERROR(VLOOKUP('PRECIFICAÇÃO '!$J74,TAXA!$A$2:$C$18,3,FALSE),"") | O74: =IFERROR(N74*H74,0) -> 0 | P74: =IFERROR('PRECIFICAÇÃO '!$H74-'PRECIFICAÇÃO '!$M74-'PRECIFICAÇÃO '!$O74,0) -> 0 | R74: =G74*3.12 -> 0 | S74: =IFERROR(H74*16.5%,0) -> 0 | U74: =IFERROR(H74*3%,0) -> 0 | V74: ='PRECIFICAÇÃO '!$Q74+'PRECIFICAÇÃO '!$R74+'PRECIFICAÇÃO '!$S74+'PRECIFICAÇÃO '!$T74+'PRECIFICAÇÃO '!$U74 -> 0 | W74: =IFERROR(V74/H74,0) -> 0 | X74: =IFERROR(P74-V74,0) -> 0 | Y74: =IFERROR(X74/H74,0) -> 0 | Z74: =IFERROR(X74*20%,0) -> 0 | AA74: =IFERROR(X74*80%,0) -> 0
F75: {=IFERROR(INDEX(PROCEDIMENTOS!$A$2:$A$48,MATCH('PRECIFICAÇÃO '!$E75,PROCEDIMENTOS!$B$2:$B$48,0)),"")} | G75: {=IFERROR(INDEX(PROCEDIMENTOS!$C$2:$C$48,MATCH('PRECIFICAÇÃO '!$E75,PROCEDIMENTOS!$B$2:$B$48,0)),"")} | L75: =IFERROR(VLOOKUP('PRECIFICAÇÃO '!$J75,TAXA!$A$2:$C$18,2,FALSE),"") | M75: =IFERROR(L75*H75,0) -> 0 | N75: =IFERROR(VLOOKUP('PRECIFICAÇÃO '!$J75,TAXA!$A$2:$C$18,3,FALSE),"") | O75: =IFERROR(N75*H75,0) -> 0 | P75: =IFERROR('PRECIFICAÇÃO '!$H75-'PRECIFICAÇÃO '!$M75-'PRECIFICAÇÃO '!$O75,0) -> 0 | Q75: {=IFERROR(INDEX(PROCEDIMENTOS!$D$2:$D$48,MATCH('PRECIFICAÇÃO '!$E75,PROCEDIMENTOS!$B$2:$B$48,0)),"")} | R75: =G75*3.12 -> 0 | S75: =IFERROR(H75*16.5%,0) -> 0 | U75: =IFERROR(H75*3%,0) -> 0 | V75: ='PRECIFICAÇÃO '!$Q75+'PRECIFICAÇÃO '!$R75+'PRECIFICAÇÃO '!$S75+'PRECIFICAÇÃO '!$T75+'PRECIFICAÇÃO '!$U75 -> 0 | W75: =IFERROR(V75/H75,0) -> 0 | X75: =IFERROR(P75-V75,0) -> 0 | Y75: =IFERROR(X75/H75,0) -> 0 | Z75: =IFERROR(X75*20%,0) -> 0 | AA75: =IFERROR(X75*80%,0) -> 0
F76: {=IFERROR(INDEX(PROCEDIMENTOS!$A$2:$A$48,MATCH('PRECIFICAÇÃO '!$E76,PROCEDIMENTOS!$B$2:$B$48,0)),"")} | G76: {=IFERROR(INDEX(PROCEDIMENTOS!$C$2:$C$48,MATCH('PRECIFICAÇÃO '!$E76,PROCEDIMENTOS!$B$2:$B$48,0)),"")} | L76: =IFERROR(VLOOKUP('PRECIFICAÇÃO '!$J76,TAXA!$A$2:$C$18,2,FALSE),"") | M76: =IFERROR(L76*H76,0) -> 0 | N76: =IFERROR(VLOOKUP('PRECIFICAÇÃO '!$J76,TAXA!$A$2:$C$18,3,FALSE),"") | O76: =IFERROR(N76*H76,0) -> 0 | P76: =IFERROR('PRECIFICAÇÃO '!$H76-'PRECIFICAÇÃO '!$M76-'PRECIFICAÇÃO '!$O76,0) -> 0 | R76: =G76*3.12 -> 0 | S76: =IFERROR(H76*16.5%,0) -> 0 | U76: =IFERROR(H76*3%,0) -> 0 | V76: ='PRECIFICAÇÃO '!$Q76+'PRECIFICAÇÃO '!$R76+'PRECIFICAÇÃO '!$S76+'PRECIFICAÇÃO '!$T76+'PRECIFICAÇÃO '!$U76 -> 0 | W76: =IFERROR(V76/H76,0) -> 0 | X76: =IFERROR(P76-V76,0) -> 0 | Y76: =IFERROR(X76/H76,0) -> 0 | Z76: =IFERROR(X76*20%,0) -> 0 | AA76: =IFERROR(X76*80%,0) -> 0
F77: {=IFERROR(INDEX(PROCEDIMENTOS!$A$2:$A$48,MATCH('PRECIFICAÇÃO '!$E77,PROCEDIMENTOS!$B$2:$B$48,0)),"")} | G77: {=IFERROR(INDEX(PROCEDIMENTOS!$C$2:$C$48,MATCH('PRECIFICAÇÃO '!$E77,PROCEDIMENTOS!$B$2:$B$48,0)),"")} | L77: =IFERROR(VLOOKUP('PRECIFICAÇÃO '!$J77,TAXA!$A$2:$C$18,2,FALSE),"") | M77: =IFERROR(L77*H77,0) -> 0 | N77: =IFERROR(VLOOKUP('PRECIFICAÇÃO '!$J77,TAXA!$A$2:$C$18,3,FALSE),"") | O77: =IFERROR(N77*H77,0) -> 0 | P77: =IFERROR('PRECIFICAÇÃO '!$H77-'PRECIFICAÇÃO '!$M77-'PRECIFICAÇÃO '!$O77,0) -> 0 | R77: =G77*3.12 -> 0 | S77: =IFERROR(H77*16.5%,0) -> 0 | U77: =IFERROR(H77*3%,0) -> 0 | V77: ='PRECIFICAÇÃO '!$Q77+'PRECIFICAÇÃO '!$R77+'PRECIFICAÇÃO '!$S77+'PRECIFICAÇÃO '!$T77+'PRECIFICAÇÃO '!$U77 -> 0 | W77: =IFERROR(V77/H77,0) -> 0 | X77: =IFERROR(P77-V77,0) -> 0 | Y77: =IFERROR(X77/H77,0) -> 0 | Z77: =IFERROR(X77*20%,0) -> 0 | AA77: =IFERROR(X77*80%,0) -> 0
F78: {=IFERROR(INDEX(PROCEDIMENTOS!$A$2:$A$48,MATCH('PRECIFICAÇÃO '!$E78,PROCEDIMENTOS!$B$2:$B$48,0)),"")} | G78: {=IFERROR(INDEX(PROCEDIMENTOS!$C$2:$C$48,MATCH('PRECIFICAÇÃO '!$E78,PROCEDIMENTOS!$B$2:$B$48,0)),"")} | L78: =IFERROR(VLOOKUP('PRECIFICAÇÃO '!$J78,TAXA!$A$2:$C$18,2,FALSE),"") | M78: =IFERROR(L78*H78,0) -> 0 | N78: =IFERROR(VLOOKUP('PRECIFICAÇÃO '!$J78,TAXA!$A$2:$C$18,3,FALSE),"") | O78: =IFERROR(N78*H78,0) -> 0 | P78: =IFERROR('PRECIFICAÇÃO '!$H78-'PRECIFICAÇÃO '!$M78-'PRECIFICAÇÃO '!$O78,0) -> 0 | R78: =G78*3.12 -> 0 | S78: =IFERROR(H78*16.5%,0) -> 0 | U78: =IFERROR(H78*3%,0) -> 0 | V78: ='PRECIFICAÇÃO '!$Q78+'PRECIFICAÇÃO '!$R78+'PRECIFICAÇÃO '!$S78+'PRECIFICAÇÃO '!$T78+'PRECIFICAÇÃO '!$U78 -> 0 | W78: =IFERROR(V78/H78,0) -> 0 | X78: =IFERROR(P78-V78,0) -> 0 | Y78: =IFERROR(X78/H78,0) -> 0 | Z78: =IFERROR(X78*20%,0) -> 0 | AA78: =IFERROR(X78*80%,0) -> 0
F79: {=IFERROR(INDEX(PROCEDIMENTOS!$A$2:$A$48,MATCH('PRECIFICAÇÃO '!$E79,PROCEDIMENTOS!$B$2:$B$48,0)),"")} | G79: {=IFERROR(INDEX(PROCEDIMENTOS!$C$2:$C$48,MATCH('PRECIFICAÇÃO '!$E79,PROCEDIMENTOS!$B$2:$B$48,0)),"")} | L79: =IFERROR(VLOOKUP('PRECIFICAÇÃO '!$J79,TAXA!$A$2:$C$18,2,FALSE),"") | M79: =IFERROR(L79*H79,0) -> 0 | N79: =IFERROR(VLOOKUP('PRECIFICAÇÃO '!$J79,TAXA!$A$2:$C$18,3,FALSE),"") | O79: =IFERROR(N79*H79,0) -> 0 | P79: =IFERROR('PRECIFICAÇÃO '!$H79-'PRECIFICAÇÃO '!$M79-'PRECIFICAÇÃO '!$O79,0) -> 0 | Q79: {=IFERROR(INDEX(PROCEDIMENTOS!$D$2:$D$48,MATCH('PRECIFICAÇÃO '!$E79,PROCEDIMENTOS!$B$2:$B$48,0)),"")} | R79: =G79*3.12 -> 0 | S79: =IFERROR(H79*16.5%,0) -> 0 | U79: =IFERROR(H79*3%,0) -> 0 | V79: ='PRECIFICAÇÃO '!$Q79+'PRECIFICAÇÃO '!$R79+'PRECIFICAÇÃO '!$S79+'PRECIFICAÇÃO '!$T79+'PRECIFICAÇÃO '!$U79 -> 0 | W79: =IFERROR(V79/H79,0) -> 0 | X79: =IFERROR(P79-V79,0) -> 0 | Y79: =IFERROR(X79/H79,0) -> 0 | Z79: =IFERROR(X79*20%,0) -> 0 | AA79: =IFERROR(X79*80%,0) -> 0
F80: {=IFERROR(INDEX(PROCEDIMENTOS!$A$2:$A$48,MATCH('PRECIFICAÇÃO '!$E80,PROCEDIMENTOS!$B$2:$B$48,0)),"")} | G80: {=IFERROR(INDEX(PROCEDIMENTOS!$C$2:$C$48,MATCH('PRECIFICAÇÃO '!$E80,PROCEDIMENTOS!$B$2:$B$48,0)),"")} | L80: =IFERROR(VLOOKUP('PRECIFICAÇÃO '!$J80,TAXA!$A$2:$C$18,2,FALSE),"") | M80: =IFERROR(L80*H80,0) -> 0 | N80: =IFERROR(VLOOKUP('PRECIFICAÇÃO '!$J80,TAXA!$A$2:$C$18,3,FALSE),"") | O80: =IFERROR(N80*H80,0) -> 0 | P80: =IFERROR('PRECIFICAÇÃO '!$H80-'PRECIFICAÇÃO '!$M80-'PRECIFICAÇÃO '!$O80,0) -> 0 | R80: =G80*3.12 -> 0 | S80: =IFERROR(H80*16.5%,0) -> 0 | U80: =IFERROR(H80*3%,0) -> 0 | V80: ='PRECIFICAÇÃO '!$Q80+'PRECIFICAÇÃO '!$R80+'PRECIFICAÇÃO '!$S80+'PRECIFICAÇÃO '!$T80+'PRECIFICAÇÃO '!$U80 -> 0 | W80: =IFERROR(V80/H80,0) -> 0 | X80: =IFERROR(P80-V80,0) -> 0 | Y80: =IFERROR(X80/H80,0) -> 0 | Z80: =IFERROR(X80*20%,0) -> 0 | AA80: =IFERROR(X80*80%,0) -> 0
F81: {=IFERROR(INDEX(PROCEDIMENTOS!$A$2:$A$48,MATCH('PRECIFICAÇÃO '!$E81,PROCEDIMENTOS!$B$2:$B$48,0)),"")} | G81: {=IFERROR(INDEX(PROCEDIMENTOS!$C$2:$C$48,MATCH('PRECIFICAÇÃO '!$E81,PROCEDIMENTOS!$B$2:$B$48,0)),"")} | L81: =IFERROR(VLOOKUP('PRECIFICAÇÃO '!$J81,TAXA!$A$2:$C$18,2,FALSE),"") | M81: =IFERROR(L81*H81,0) -> 0 | N81: =IFERROR(VLOOKUP('PRECIFICAÇÃO '!$J81,TAXA!$A$2:$C$18,3,FALSE),"") | O81: =IFERROR(N81*H81,0) -> 0 | P81: =IFERROR('PRECIFICAÇÃO '!$H81-'PRECIFICAÇÃO '!$M81-'PRECIFICAÇÃO '!$O81,0) -> 0 | Q81: {=IFERROR(INDEX(PROCEDIMENTOS!$D$2:$D$48,MATCH('PRECIFICAÇÃO '!$E81,PROCEDIMENTOS!$B$2:$B$48,0)),"")} | R81: =G81*3.12 -> 0 | S81: =IFERROR(H81*16.5%,0) -> 0 | U81: =IFERROR(H81*3%,0) -> 0 | V81: ='PRECIFICAÇÃO '!$Q81+'PRECIFICAÇÃO '!$R81+'PRECIFICAÇÃO '!$S81+'PRECIFICAÇÃO '!$T81+'PRECIFICAÇÃO '!$U81 -> 0 | W81: =IFERROR(V81/H81,0) -> 0 | X81: =IFERROR(P81-V81,0) -> 0 | Y81: =IFERROR(X81/H81,0) -> 0 | Z81: =IFERROR(X81*20%,0) -> 0 | AA81: =IFERROR(X81*80%,0) -> 0
F82: {=IFERROR(INDEX(PROCEDIMENTOS!$A$2:$A$48,MATCH('PRECIFICAÇÃO '!$E82,PROCEDIMENTOS!$B$2:$B$48,0)),"")} | G82: {=IFERROR(INDEX(PROCEDIMENTOS!$C$2:$C$48,MATCH('PRECIFICAÇÃO '!$E82,PROCEDIMENTOS!$B$2:$B$48,0)),"")} | L82: =IFERROR(VLOOKUP('PRECIFICAÇÃO '!$J82,TAXA!$A$2:$C$18,2,FALSE),"") | M82: =IFERROR(L82*H82,0) -> 0 | N82: =IFERROR(VLOOKUP('PRECIFICAÇÃO '!$J82,TAXA!$A$2:$C$18,3,FALSE),"") | O82: =IFERROR(N82*H82,0) -> 0 | P82: =IFERROR('PRECIFICAÇÃO '!$H82-'PRECIFICAÇÃO '!$M82-'PRECIFICAÇÃO '!$O82,0) -> 0 | Q82: {=IFERROR(INDEX(PROCEDIMENTOS!$D$2:$D$48,MATCH('PRECIFICAÇÃO '!$E82,PROCEDIMENTOS!$B$2:$B$48,0)),"")} | R82: =G82*3.12 -> 0 | S82: =IFERROR(H82*16.5%,0) -> 0 | U82: =IFERROR(H82*3%,0) -> 0 | V82: ='PRECIFICAÇÃO '!$Q82+'PRECIFICAÇÃO '!$R82+'PRECIFICAÇÃO '!$S82+'PRECIFICAÇÃO '!$T82+'PRECIFICAÇÃO '!$U82 -> 0 | W82: =IFERROR(V82/H82,0) -> 0 | X82: =IFERROR(P82-V82,0) -> 0 | Y82: =IFERROR(X82/H82,0) -> 0 | Z82: =IFERROR(X82*20%,0) -> 0 | AA82: =IFERROR(X82*80%,0) -> 0
F83: {=IFERROR(INDEX(PROCEDIMENTOS!$A$2:$A$48,MATCH('PRECIFICAÇÃO '!$E83,PROCEDIMENTOS!$B$2:$B$48,0)),"")} | G83: {=IFERROR(INDEX(PROCEDIMENTOS!$C$2:$C$48,MATCH('PRECIFICAÇÃO '!$E83,PROCEDIMENTOS!$B$2:$B$48,0)),"")} | L83: =IFERROR(VLOOKUP('PRECIFICAÇÃO '!$J83,TAXA!$A$2:$C$18,2,FALSE),"") | M83: =IFERROR(L83*H83,0) -> 0 | N83: =IFERROR(VLOOKUP('PRECIFICAÇÃO '!$J83,TAXA!$A$2:$C$18,3,FALSE),"") | O83: =IFERROR(N83*H83,0) -> 0 | P83: =IFERROR('PRECIFICAÇÃO '!$H83-'PRECIFICAÇÃO '!$M83-'PRECIFICAÇÃO '!$O83,0) -> 0 | Q83: {=IFERROR(INDEX(PROCEDIMENTOS!$D$2:$D$48,MATCH('PRECIFICAÇÃO '!$E83,PROCEDIMENTOS!$B$2:$B$48,0)),"")} | R83: =G83*3.12 -> 0 | S83: =IFERROR(H83*16.5%,0) -> 0 | U83: =IFERROR(H83*3%,0) -> 0 | V83: ='PRECIFICAÇÃO '!$Q83+'PRECIFICAÇÃO '!$R83+'PRECIFICAÇÃO '!$S83+'PRECIFICAÇÃO '!$T83+'PRECIFICAÇÃO '!$U83 -> 0 | W83: =IFERROR(V83/H83,0) -> 0 | X83: =IFERROR(P83-V83,0) -> 0 | Y83: =IFERROR(X83/H83,0) -> 0 | Z83: =IFERROR(X83*20%,0) -> 0 | AA83: =IFERROR(X83*80%,0) -> 0
F84: {=IFERROR(INDEX(PROCEDIMENTOS!$A$2:$A$48,MATCH('PRECIFICAÇÃO '!$E84,PROCEDIMENTOS!$B$2:$B$48,0)),"")} | G84: {=IFERROR(INDEX(PROCEDIMENTOS!$C$2:$C$48,MATCH('PRECIFICAÇÃO '!$E84,PROCEDIMENTOS!$B$2:$B$48,0)),"")} | L84: =IFERROR(VLOOKUP('PRECIFICAÇÃO '!$J84,TAXA!$A$2:$C$18,2,FALSE),"") | M84: =IFERROR(L84*H84,0) -> 0 | N84: =IFERROR(VLOOKUP('PRECIFICAÇÃO '!$J84,TAXA!$A$2:$C$18,3,FALSE),"") | O84: =IFERROR(N84*H84,0) -> 0 | P84: =IFERROR('PRECIFICAÇÃO '!$H84-'PRECIFICAÇÃO '!$M84-'PRECIFICAÇÃO '!$O84,0) -> 0 | R84: =G84*3.12 -> 0 | S84: =IFERROR(H84*16.5%,0) -> 0 | U84: =IFERROR(H84*3%,0) -> 0 | V84: ='PRECIFICAÇÃO '!$Q84+'PRECIFICAÇÃO '!$R84+'PRECIFICAÇÃO '!$S84+'PRECIFICAÇÃO '!$T84+'PRECIFICAÇÃO '!$U84 -> 0 | W84: =IFERROR(V84/H84,0) -> 0 | X84: =IFERROR(P84-V84,0) -> 0 | Y84: =IFERROR(X84/H84,0) -> 0 | Z84: =IFERROR(X84*20%,0) -> 0 | AA84: =IFERROR(X84*80%,0) -> 0
F85: {=IFERROR(INDEX(PROCEDIMENTOS!$A$2:$A$48,MATCH('PRECIFICAÇÃO '!$E85,PROCEDIMENTOS!$B$2:$B$48,0)),"")} | G85: {=IFERROR(INDEX(PROCEDIMENTOS!$C$2:$C$48,MATCH('PRECIFICAÇÃO '!$E85,PROCEDIMENTOS!$B$2:$B$48,0)),"")} | L85: =IFERROR(VLOOKUP('PRECIFICAÇÃO '!$J85,TAXA!$A$2:$C$18,2,FALSE),"") | M85: =IFERROR(L85*H85,0) -> 0 | N85: =IFERROR(VLOOKUP('PRECIFICAÇÃO '!$J85,TAXA!$A$2:$C$18,3,FALSE),"") | O85: =IFERROR(N85*H85,0) -> 0 | P85: =IFERROR('PRECIFICAÇÃO '!$H85-'PRECIFICAÇÃO '!$M85-'PRECIFICAÇÃO '!$O85,0) -> 0 | Q85: {=IFERROR(INDEX(PROCEDIMENTOS!$D$2:$D$48,MATCH('PRECIFICAÇÃO '!$E85,PROCEDIMENTOS!$B$2:$B$48,0)),"")} | R85: =G85*3.12 -> 0 | S85: =IFERROR(H85*16.5%,0) -> 0 | U85: =IFERROR(H85*3%,0) -> 0 | V85: ='PRECIFICAÇÃO '!$Q85+'PRECIFICAÇÃO '!$R85+'PRECIFICAÇÃO '!$S85+'PRECIFICAÇÃO '!$T85+'PRECIFICAÇÃO '!$U85 -> 0 | W85: =IFERROR(V85/H85,0) -> 0 | X85: =IFERROR(P85-V85,0) -> 0 | Y85: =IFERROR(X85/H85,0) -> 0 | Z85: =IFERROR(X85*20%,0) -> 0 | AA85: =IFERROR(X85*80%,0) -> 0
F86: {=IFERROR(INDEX(PROCEDIMENTOS!$A$2:$A$48,MATCH('PRECIFICAÇÃO '!$E86,PROCEDIMENTOS!$B$2:$B$48,0)),"")} | G86: {=IFERROR(INDEX(PROCEDIMENTOS!$C$2:$C$48,MATCH('PRECIFICAÇÃO '!$E86,PROCEDIMENTOS!$B$2:$B$48,0)),"")} | L86: =IFERROR(VLOOKUP('PRECIFICAÇÃO '!$J86,TAXA!$A$2:$C$18,2,FALSE),"") | M86: =IFERROR(L86*H86,0) -> 0 | N86: =IFERROR(VLOOKUP('PRECIFICAÇÃO '!$J86,TAXA!$A$2:$C$18,3,FALSE),"") | O86: =IFERROR(N86*H86,0) -> 0 | P86: =IFERROR('PRECIFICAÇÃO '!$H86-'PRECIFICAÇÃO '!$M86-'PRECIFICAÇÃO '!$O86,0) -> 0 | Q86: {=IFERROR(INDEX(PROCEDIMENTOS!$D$2:$D$48,MATCH('PRECIFICAÇÃO '!$E86,PROCEDIMENTOS!$B$2:$B$48,0)),"")} | R86: =G86*3.12 -> 0 | S86: =IFERROR(H86*16.5%,0) -> 0 | U86: =IFERROR(H86*3%,0) -> 0 | V86: ='PRECIFICAÇÃO '!$Q86+'PRECIFICAÇÃO '!$R86+'PRECIFICAÇÃO '!$S86+'PRECIFICAÇÃO '!$T86+'PRECIFICAÇÃO '!$U86 -> 0 | W86: =IFERROR(V86/H86,0) -> 0 | X86: =IFERROR(P86-V86,0) -> 0 | Y86: =IFERROR(X86/H86,0) -> 0 | Z86: =IFERROR(X86*20%,0) -> 0 | AA86: =IFERROR(X86*80%,0) -> 0
F87: {=IFERROR(INDEX(PROCEDIMENTOS!$A$2:$A$48,MATCH('PRECIFICAÇÃO '!$E87,PROCEDIMENTOS!$B$2:$B$48,0)),"")} | G87: {=IFERROR(INDEX(PROCEDIMENTOS!$C$2:$C$48,MATCH('PRECIFICAÇÃO '!$E87,PROCEDIMENTOS!$B$2:$B$48,0)),"")} | L87: =IFERROR(VLOOKUP('PRECIFICAÇÃO '!$J87,TAXA!$A$2:$C$18,2,FALSE),"") | M87: =IFERROR(L87*H87,0) -> 0 | N87: =IFERROR(VLOOKUP('PRECIFICAÇÃO '!$J87,TAXA!$A$2:$C$18,3,FALSE),"") | O87: =IFERROR(N87*H87,0) -> 0 | P87: =IFERROR('PRECIFICAÇÃO '!$H87-'PRECIFICAÇÃO '!$M87-'PRECIFICAÇÃO '!$O87,0) -> 0 | Q87: {=IFERROR(INDEX(PROCEDIMENTOS!$D$2:$D$48,MATCH('PRECIFICAÇÃO '!$E87,PROCEDIMENTOS!$B$2:$B$48,0)),"")} | R87: =G87*3.12 -> 0 | S87: =IFERROR(H87*16.5%,0) -> 0 | U87: =IFERROR(H87*3%,0) -> 0 | V87: ='PRECIFICAÇÃO '!$Q87+'PRECIFICAÇÃO '!$R87+'PRECIFICAÇÃO '!$S87+'PRECIFICAÇÃO '!$T87+'PRECIFICAÇÃO '!$U87 -> 0 | W87: =IFERROR(V87/H87,0) -> 0 | X87: =IFERROR(P87-V87,0) -> 0 | Y87: =IFERROR(X87/H87,0) -> 0 | Z87: =IFERROR(X87*20%,0) -> 0 | AA87: =IFERROR(X87*80%,0) -> 0
F88: {=IFERROR(INDEX(PROCEDIMENTOS!$A$2:$A$48,MATCH('PRECIFICAÇÃO '!$E88,PROCEDIMENTOS!$B$2:$B$48,0)),"")} | G88: {=IFERROR(INDEX(PROCEDIMENTOS!$C$2:$C$48,MATCH('PRECIFICAÇÃO '!$E88,PROCEDIMENTOS!$B$2:$B$48,0)),"")} | L88: =IFERROR(VLOOKUP('PRECIFICAÇÃO '!$J88,TAXA!$A$2:$C$18,2,FALSE),"") | M88: =IFERROR(L88*H88,0) -> 0 | N88: =IFERROR(VLOOKUP('PRECIFICAÇÃO '!$J88,TAXA!$A$2:$C$18,3,FALSE),"") | O88: =IFERROR(N88*H88,0) -> 0 | P88: =IFERROR('PRECIFICAÇÃO '!$H88-'PRECIFICAÇÃO '!$M88-'PRECIFICAÇÃO '!$O88,0) -> 0 | Q88: {=IFERROR(INDEX(PROCEDIMENTOS!$D$2:$D$48,MATCH('PRECIFICAÇÃO '!$E88,PROCEDIMENTOS!$B$2:$B$48,0)),"")} | R88: =G88*3.12 -> 0 | S88: =IFERROR(H88*16.5%,0) -> 0 | U88: =IFERROR(H88*3%,0) -> 0 | V88: ='PRECIFICAÇÃO '!$Q88+'PRECIFICAÇÃO '!$R88+'PRECIFICAÇÃO '!$S88+'PRECIFICAÇÃO '!$T88+'PRECIFICAÇÃO '!$U88 -> 0 | W88: =IFERROR(V88/H88,0) -> 0 | X88: =IFERROR(P88-V88,0) -> 0 | Y88: =IFERROR(X88/H88,0) -> 0 | Z88: =IFERROR(X88*20%,0) -> 0 | AA88: =IFERROR(X88*80%,0) -> 0
F89: {=IFERROR(INDEX(PROCEDIMENTOS!$A$2:$A$48,MATCH('PRECIFICAÇÃO '!$E89,PROCEDIMENTOS!$B$2:$B$48,0)),"")} | G89: {=IFERROR(INDEX(PROCEDIMENTOS!$C$2:$C$48,MATCH('PRECIFICAÇÃO '!$E89,PROCEDIMENTOS!$B$2:$B$48,0)),"")} | L89: =IFERROR(VLOOKUP('PRECIFICAÇÃO '!$J89,TAXA!$A$2:$C$18,2,FALSE),"") | M89: =IFERROR(L89*H89,0) -> 0 | N89: =IFERROR(VLOOKUP('PRECIFICAÇÃO '!$J89,TAXA!$A$2:$C$18,3,FALSE),"") | O89: =IFERROR(N89*H89,0) -> 0 | P89: =IFERROR('PRECIFICAÇÃO '!$H89-'PRECIFICAÇÃO '!$M89-'PRECIFICAÇÃO '!$O89,0) -> 0 | R89: =G89*3.12 -> 0 | S89: =IFERROR(H89*16.5%,0) -> 0 | U89: =IFERROR(H89*3%,0) -> 0 | V89: ='PRECIFICAÇÃO '!$Q89+'PRECIFICAÇÃO '!$R89+'PRECIFICAÇÃO '!$S89+'PRECIFICAÇÃO '!$T89+'PRECIFICAÇÃO '!$U89 -> 0 | W89: =IFERROR(V89/H89,0) -> 0 | X89: =IFERROR(P89-V89,0) -> 0 | Y89: =IFERROR(X89/H89,0) -> 0 | Z89: =IFERROR(X89*20%,0) -> 0 | AA89: =IFERROR(X89*80%,0) -> 0
F90: {=IFERROR(INDEX(PROCEDIMENTOS!$A$2:$A$48,MATCH('PRECIFICAÇÃO '!$E90,PROCEDIMENTOS!$B$2:$B$48,0)),"")} | G90: {=IFERROR(INDEX(PROCEDIMENTOS!$C$2:$C$48,MATCH('PRECIFICAÇÃO '!$E90,PROCEDIMENTOS!$B$2:$B$48,0)),"")} | L90: =IFERROR(VLOOKUP('PRECIFICAÇÃO '!$J90,TAXA!$A$2:$C$18,2,FALSE),"") | M90: =IFERROR(L90*H90,0) -> 0 | N90: =IFERROR(VLOOKUP('PRECIFICAÇÃO '!$J90,TAXA!$A$2:$C$18,3,FALSE),"") | O90: =IFERROR(N90*H90,0) -> 0 | P90: =IFERROR('PRECIFICAÇÃO '!$H90-'PRECIFICAÇÃO '!$M90-'PRECIFICAÇÃO '!$O90,0) -> 0 | Q90: {=IFERROR(INDEX(PROCEDIMENTOS!$D$2:$D$48,MATCH('PRECIFICAÇÃO '!$E90,PROCEDIMENTOS!$B$2:$B$48,0)),"")} | R90: =G90*3.12 -> 0 | S90: =IFERROR(H90*16.5%,0) -> 0 | U90: =IFERROR(H90*3%,0) -> 0 | V90: ='PRECIFICAÇÃO '!$Q90+'PRECIFICAÇÃO '!$R90+'PRECIFICAÇÃO '!$S90+'PRECIFICAÇÃO '!$T90+'PRECIFICAÇÃO '!$U90 -> 0 | W90: =IFERROR(V90/H90,0) -> 0 | X90: =IFERROR(P90-V90,0) -> 0 | Y90: =IFERROR(X90/H90,0) -> 0 | Z90: =IFERROR(X90*20%,0) -> 0 | AA90: =IFERROR(X90*80%,0) -> 0
F91: {=IFERROR(INDEX(PROCEDIMENTOS!$A$2:$A$48,MATCH('PRECIFICAÇÃO '!$E91,PROCEDIMENTOS!$B$2:$B$48,0)),"")} | G91: {=IFERROR(INDEX(PROCEDIMENTOS!$C$2:$C$48,MATCH('PRECIFICAÇÃO '!$E91,PROCEDIMENTOS!$B$2:$B$48,0)),"")} | L91: =IFERROR(VLOOKUP('PRECIFICAÇÃO '!$J91,TAXA!$A$2:$C$18,2,FALSE),"") | M91: =IFERROR(L91*H91,0) -> 0 | N91: =IFERROR(VLOOKUP('PRECIFICAÇÃO '!$J91,TAXA!$A$2:$C$18,3,FALSE),"") | O91: =IFERROR(N91*H91,0) -> 0 | P91: =IFERROR('PRECIFICAÇÃO '!$H91-'PRECIFICAÇÃO '!$M91-'PRECIFICAÇÃO '!$O91,0) -> 0 | Q91: {=IFERROR(INDEX(PROCEDIMENTOS!$D$2:$D$48,MATCH('PRECIFICAÇÃO '!$E91,PROCEDIMENTOS!$B$2:$B$48,0)),"")} | R91: =G91*3.12 -> 0 | S91: =IFERROR(H91*16.5%,0) -> 0 | U91: =IFERROR(H91*3%,0) -> 0 | V91: ='PRECIFICAÇÃO '!$Q91+'PRECIFICAÇÃO '!$R91+'PRECIFICAÇÃO '!$S91+'PRECIFICAÇÃO '!$T91+'PRECIFICAÇÃO '!$U91 -> 0 | W91: =IFERROR(V91/H91,0) -> 0 | X91: =IFERROR(P91-V91,0) -> 0 | Y91: =IFERROR(X91/H91,0) -> 0 | Z91: =IFERROR(X91*20%,0) -> 0 | AA91: =IFERROR(X91*80%,0) -> 0
F92: {=IFERROR(INDEX(PROCEDIMENTOS!$A$2:$A$48,MATCH('PRECIFICAÇÃO '!$E92,PROCEDIMENTOS!$B$2:$B$48,0)),"")} | G92: {=IFERROR(INDEX(PROCEDIMENTOS!$C$2:$C$48,MATCH('PRECIFICAÇÃO '!$E92,PROCEDIMENTOS!$B$2:$B$48,0)),"")} | L92: =IFERROR(VLOOKUP('PRECIFICAÇÃO '!$J92,TAXA!$A$2:$C$18,2,FALSE),"") | M92: =IFERROR(L92*H92,0) -> 0 | N92: =IFERROR(VLOOKUP('PRECIFICAÇÃO '!$J92,TAXA!$A$2:$C$18,3,FALSE),"") | O92: =IFERROR(N92*H92,0) -> 0 | P92: =IFERROR('PRECIFICAÇÃO '!$H92-'PRECIFICAÇÃO '!$M92-'PRECIFICAÇÃO '!$O92,0) -> 0 | Q92: {=IFERROR(INDEX(PROCEDIMENTOS!$D$2:$D$48,MATCH('PRECIFICAÇÃO '!$E92,PROCEDIMENTOS!$B$2:$B$48,0)),"")} | R92: =G92*3.12 -> 0 | S92: =IFERROR(H92*16.5%,0) -> 0 | U92: =IFERROR(H92*3%,0) -> 0 | V92: ='PRECIFICAÇÃO '!$Q92+'PRECIFICAÇÃO '!$R92+'PRECIFICAÇÃO '!$S92+'PRECIFICAÇÃO '!$T92+'PRECIFICAÇÃO '!$U92 -> 0 | W92: =IFERROR(V92/H92,0) -> 0 | X92: =IFERROR(P92-V92,0) -> 0 | Y92: =IFERROR(X92/H92,0) -> 0 | Z92: =IFERROR(X92*20%,0) -> 0 | AA92: =IFERROR(X92*80%,0) -> 0
F93: {=IFERROR(INDEX(PROCEDIMENTOS!$A$2:$A$48,MATCH('PRECIFICAÇÃO '!$E93,PROCEDIMENTOS!$B$2:$B$48,0)),"")} | G93: {=IFERROR(INDEX(PROCEDIMENTOS!$C$2:$C$48,MATCH('PRECIFICAÇÃO '!$E93,PROCEDIMENTOS!$B$2:$B$48,0)),"")} | L93: =IFERROR(VLOOKUP('PRECIFICAÇÃO '!$J93,TAXA!$A$2:$C$18,2,FALSE),"") | M93: =IFERROR(L93*H93,0) -> 0 | N93: =IFERROR(VLOOKUP('PRECIFICAÇÃO '!$J93,TAXA!$A$2:$C$18,3,FALSE),"") | O93: =IFERROR(N93*H93,0) -> 0 | P93: =IFERROR('PRECIFICAÇÃO '!$H93-'PRECIFICAÇÃO '!$M93-'PRECIFICAÇÃO '!$O93,0) -> 0 | Q93: {=IFERROR(INDEX(PROCEDIMENTOS!$D$2:$D$48,MATCH('PRECIFICAÇÃO '!$E93,PROCEDIMENTOS!$B$2:$B$48,0)),"")} | R93: =G93*3.12 -> 0 | S93: =IFERROR(H93*16.5%,0) -> 0 | U93: =IFERROR(H93*3%,0) -> 0 | V93: ='PRECIFICAÇÃO '!$Q93+'PRECIFICAÇÃO '!$R93+'PRECIFICAÇÃO '!$S93+'PRECIFICAÇÃO '!$T93+'PRECIFICAÇÃO '!$U93 -> 0 | W93: =IFERROR(V93/H93,0) -> 0 | X93: =IFERROR(P93-V93,0) -> 0 | Y93: =IFERROR(X93/H93,0) -> 0 | Z93: =IFERROR(X93*20%,0) -> 0 | AA93: =IFERROR(X93*80%,0) -> 0
F94: {=IFERROR(INDEX(PROCEDIMENTOS!$A$2:$A$48,MATCH('PRECIFICAÇÃO '!$E94,PROCEDIMENTOS!$B$2:$B$48,0)),"")} | G94: {=IFERROR(INDEX(PROCEDIMENTOS!$C$2:$C$48,MATCH('PRECIFICAÇÃO '!$E94,PROCEDIMENTOS!$B$2:$B$48,0)),"")} | L94: =IFERROR(VLOOKUP('PRECIFICAÇÃO '!$J94,TAXA!$A$2:$C$18,2,FALSE),"") | M94: =IFERROR(L94*H94,0) -> 0 | N94: =IFERROR(VLOOKUP('PRECIFICAÇÃO '!$J94,TAXA!$A$2:$C$18,3,FALSE),"") | O94: =IFERROR(N94*H94,0) -> 0 | P94: =IFERROR('PRECIFICAÇÃO '!$H94-'PRECIFICAÇÃO '!$M94-'PRECIFICAÇÃO '!$O94,0) -> 0 | Q94: {=IFERROR(INDEX(PROCEDIMENTOS!$D$2:$D$48,MATCH('PRECIFICAÇÃO '!$E94,PROCEDIMENTOS!$B$2:$B$48,0)),"")} | R94: =G94*3.12 -> 0 | S94: =IFERROR(H94*16.5%,0) -> 0 | U94: =IFERROR(H94*3%,0) -> 0 | V94: ='PRECIFICAÇÃO '!$Q94+'PRECIFICAÇÃO '!$R94+'PRECIFICAÇÃO '!$S94+'PRECIFICAÇÃO '!$T94+'PRECIFICAÇÃO '!$U94 -> 0 | W94: =IFERROR(V94/H94,0) -> 0 | X94: =IFERROR(P94-V94,0) -> 0 | Y94: =IFERROR(X94/H94,0) -> 0 | Z94: =IFERROR(X94*20%,0) -> 0 | AA94: =IFERROR(X94*80%,0) -> 0
F95: {=IFERROR(INDEX(PROCEDIMENTOS!$A$2:$A$48,MATCH('PRECIFICAÇÃO '!$E95,PROCEDIMENTOS!$B$2:$B$48,0)),"")} | G95: {=IFERROR(INDEX(PROCEDIMENTOS!$C$2:$C$48,MATCH('PRECIFICAÇÃO '!$E95,PROCEDIMENTOS!$B$2:$B$48,0)),"")} | L95: =IFERROR(VLOOKUP('PRECIFICAÇÃO '!$J95,TAXA!$A$2:$C$18,2,FALSE),"") | M95: =IFERROR(L95*H95,0) -> 0 | N95: =IFERROR(VLOOKUP('PRECIFICAÇÃO '!$J95,TAXA!$A$2:$C$18,3,FALSE),"") | O95: =IFERROR(N95*H95,0) -> 0 | P95: =IFERROR('PRECIFICAÇÃO '!$H95-'PRECIFICAÇÃO '!$M95-'PRECIFICAÇÃO '!$O95,0) -> 0 | R95: =G95*3.12 -> 0 | S95: =IFERROR(H95*16.5%,0) -> 0 | U95: =IFERROR(H95*3%,0) -> 0 | V95: ='PRECIFICAÇÃO '!$Q95+'PRECIFICAÇÃO '!$R95+'PRECIFICAÇÃO '!$S95+'PRECIFICAÇÃO '!$T95+'PRECIFICAÇÃO '!$U95 -> 0 | W95: =IFERROR(V95/H95,0) -> 0 | X95: =IFERROR(P95-V95,0) -> 0 | Y95: =IFERROR(X95/H95,0) -> 0 | Z95: =IFERROR(X95*20%,0) -> 0 | AA95: =IFERROR(X95*80%,0) -> 0
F96: {=IFERROR(INDEX(PROCEDIMENTOS!$A$2:$A$48,MATCH('PRECIFICAÇÃO '!$E96,PROCEDIMENTOS!$B$2:$B$48,0)),"")} | G96: {=IFERROR(INDEX(PROCEDIMENTOS!$C$2:$C$48,MATCH('PRECIFICAÇÃO '!$E96,PROCEDIMENTOS!$B$2:$B$48,0)),"")} | L96: =IFERROR(VLOOKUP('PRECIFICAÇÃO '!$J96,TAXA!$A$2:$C$18,2,FALSE),"") | M96: =IFERROR(L96*H96,0) -> 0 | N96: =IFERROR(VLOOKUP('PRECIFICAÇÃO '!$J96,TAXA!$A$2:$C$18,3,FALSE),"") | O96: =IFERROR(N96*H96,0) -> 0 | P96: =IFERROR('PRECIFICAÇÃO '!$H96-'PRECIFICAÇÃO '!$M96-'PRECIFICAÇÃO '!$O96,0) -> 0 | R96: =G96*3.12 -> 0 | S96: =IFERROR(H96*16.5%,0) -> 0 | U96: =IFERROR(H96*3%,0) -> 0 | V96: ='PRECIFICAÇÃO '!$Q96+'PRECIFICAÇÃO '!$R96+'PRECIFICAÇÃO '!$S96+'PRECIFICAÇÃO '!$T96+'PRECIFICAÇÃO '!$U96 -> 0 | W96: =IFERROR(V96/H96,0) -> 0 | X96: =IFERROR(P96-V96,0) -> 0 | Y96: =IFERROR(X96/H96,0) -> 0 | Z96: =IFERROR(X96*20%,0) -> 0 | AA96: =IFERROR(X96*80%,0) -> 0
F97: {=IFERROR(INDEX(PROCEDIMENTOS!$A$2:$A$48,MATCH('PRECIFICAÇÃO '!$E97,PROCEDIMENTOS!$B$2:$B$48,0)),"")} | G97: {=IFERROR(INDEX(PROCEDIMENTOS!$C$2:$C$48,MATCH('PRECIFICAÇÃO '!$E97,PROCEDIMENTOS!$B$2:$B$48,0)),"")} | L97: =IFERROR(VLOOKUP('PRECIFICAÇÃO '!$J97,TAXA!$A$2:$C$18,2,FALSE),"") | M97: =IFERROR(L97*H97,0) -> 0 | N97: =IFERROR(VLOOKUP('PRECIFICAÇÃO '!$J97,TAXA!$A$2:$C$18,3,FALSE),"") | O97: =IFERROR(N97*H97,0) -> 0 | P97: =IFERROR('PRECIFICAÇÃO '!$H97-'PRECIFICAÇÃO '!$M97-'PRECIFICAÇÃO '!$O97,0) -> 0 | R97: =G97*3.12 -> 0 | S97: =IFERROR(H97*16.5%,0) -> 0 | U97: =IFERROR(H97*3%,0) -> 0 | V97: ='PRECIFICAÇÃO '!$Q97+'PRECIFICAÇÃO '!$R97+'PRECIFICAÇÃO '!$S97+'PRECIFICAÇÃO '!$T97+'PRECIFICAÇÃO '!$U97 -> 0 | W97: =IFERROR(V97/H97,0) -> 0 | X97: =IFERROR(P97-V97,0) -> 0 | Y97: =IFERROR(X97/H97,0) -> 0 | Z97: =IFERROR(X97*20%,0) -> 0 | AA97: =IFERROR(X97*80%,0) -> 0
F98: {=IFERROR(INDEX(PROCEDIMENTOS!$A$2:$A$48,MATCH('PRECIFICAÇÃO '!$E98,PROCEDIMENTOS!$B$2:$B$48,0)),"")} | G98: {=IFERROR(INDEX(PROCEDIMENTOS!$C$2:$C$48,MATCH('PRECIFICAÇÃO '!$E98,PROCEDIMENTOS!$B$2:$B$48,0)),"")} | L98: =IFERROR(VLOOKUP('PRECIFICAÇÃO '!$J98,TAXA!$A$2:$C$18,2,FALSE),"") | M98: =IFERROR(L98*H98,0) -> 0 | N98: =IFERROR(VLOOKUP('PRECIFICAÇÃO '!$J98,TAXA!$A$2:$C$18,3,FALSE),"") | O98: =IFERROR(N98*H98,0) -> 0 | P98: =IFERROR('PRECIFICAÇÃO '!$H98-'PRECIFICAÇÃO '!$M98-'PRECIFICAÇÃO '!$O98,0) -> 0 | R98: =G98*3.12 -> 0 | S98: =IFERROR(H98*16.5%,0) -> 0 | U98: =IFERROR(H98*3%,0) -> 0 | V98: ='PRECIFICAÇÃO '!$Q98+'PRECIFICAÇÃO '!$R98+'PRECIFICAÇÃO '!$S98+'PRECIFICAÇÃO '!$T98+'PRECIFICAÇÃO '!$U98 -> 0 | W98: =IFERROR(V98/H98,0) -> 0 | X98: =IFERROR(P98-V98,0) -> 0 | Y98: =IFERROR(X98/H98,0) -> 0 | Z98: =IFERROR(X98*20%,0) -> 0 | AA98: =IFERROR(X98*80%,0) -> 0
F99: {=IFERROR(INDEX(PROCEDIMENTOS!$A$2:$A$48,MATCH('PRECIFICAÇÃO '!$E99,PROCEDIMENTOS!$B$2:$B$48,0)),"")} | G99: {=IFERROR(INDEX(PROCEDIMENTOS!$C$2:$C$48,MATCH('PRECIFICAÇÃO '!$E99,PROCEDIMENTOS!$B$2:$B$48,0)),"")} | L99: =IFERROR(VLOOKUP('PRECIFICAÇÃO '!$J99,TAXA!$A$2:$C$18,2,FALSE),"") | M99: =IFERROR(L99*H99,0) -> 0 | N99: =IFERROR(VLOOKUP('PRECIFICAÇÃO '!$J99,TAXA!$A$2:$C$18,3,FALSE),"") | O99: =IFERROR(N99*H99,0) -> 0 | P99: =IFERROR('PRECIFICAÇÃO '!$H99-'PRECIFICAÇÃO '!$M99-'PRECIFICAÇÃO '!$O99,0) -> 0 | R99: =G99*3.12 -> 0 | S99: =IFERROR(H99*16.5%,0) -> 0 | U99: =IFERROR(H99*3%,0) -> 0 | V99: ='PRECIFICAÇÃO '!$Q99+'PRECIFICAÇÃO '!$R99+'PRECIFICAÇÃO '!$S99+'PRECIFICAÇÃO '!$T99+'PRECIFICAÇÃO '!$U99 -> 0 | W99: =IFERROR(V99/H99,0) -> 0 | X99: =IFERROR(P99-V99,0) -> 0 | Y99: =IFERROR(X99/H99,0) -> 0 | Z99: =IFERROR(X99*20%,0) -> 0 | AA99: =IFERROR(X99*80%,0) -> 0
F100: {=IFERROR(INDEX(PROCEDIMENTOS!$A$2:$A$48,MATCH('PRECIFICAÇÃO '!$E100,PROCEDIMENTOS!$B$2:$B$48,0)),"")} | G100: {=IFERROR(INDEX(PROCEDIMENTOS!$C$2:$C$48,MATCH('PRECIFICAÇÃO '!$E100,PROCEDIMENTOS!$B$2:$B$48,0)),"")} | L100: =IFERROR(VLOOKUP('PRECIFICAÇÃO '!$J100,TAXA!$A$2:$C$18,2,FALSE),"") | M100: =IFERROR(L100*H100,0) -> 0 | N100: =IFERROR(VLOOKUP('PRECIFICAÇÃO '!$J100,TAXA!$A$2:$C$18,3,FALSE),"") | O100: =IFERROR(N100*H100,0) -> 0 | P100: =IFERROR('PRECIFICAÇÃO '!$H100-'PRECIFICAÇÃO '!$M100-'PRECIFICAÇÃO '!$O100,0) -> 0 | R100: =G100*3.12 -> 0 | S100: =IFERROR(H100*16.5%,0) -> 0 | U100: =IFERROR(H100*3%,0) -> 0 | V100: ='PRECIFICAÇÃO '!$Q100+'PRECIFICAÇÃO '!$R100+'PRECIFICAÇÃO '!$S100+'PRECIFICAÇÃO '!$T100+'PRECIFICAÇÃO '!$U100 -> 0 | W100: =IFERROR(V100/H100,0) -> 0 | X100: =IFERROR(P100-V100,0) -> 0 | Y100: =IFERROR(X100/H100,0) -> 0 | Z100: =IFERROR(X100*20%,0) -> 0 | AA100: =IFERROR(X100*80%,0) -> 0

Sheet PROCEDIMENTOS
A1: TIPO | B1: PROCEDIMENTO | C1: DURAÇÃO | D1: PRODUTO
A2: CONSULTA | B2: 1º consulta médica | C2: 90 | D2: 0
A3: PROCEDIMENTO | B3: Ácido Hialurônico - Volbella Juvederm | C3: 60 | D3: 360.35
A4: PROCEDIMENTO | B4: Ácido Hialurônico - Volift Juvederm | C4: 60 | D4: 411.54
A5: PROCEDIMENTO | B5: Ácido Hialurônico - Volux Juvederm | C5: 60 | D5: 240.64
A6: PROCEDIMENTO | B6: Ácido Hialurônico Voluma Juvederm | C6: 60 | D6: 449.8
A7: PROCEDIMENTO | B7: Biópsia de Pele (1 lesão) | C7: 30 | D7: -
A8: PROCEDIMENTO | B8: Consulta médica - rotina | C8: 60 | D8: -
A9: PROCEDIMENTO | B9: Crioterapia (por lesão) | C9: 10 | D9: -
A10: PROCEDIMENTO | B10: Exossomos Capilar (4 sessões) | C10: 45 | D10: -
A11: TECNOLOGIA | B11: Fotoage | C11: 60 | D11: -
A12: PROCEDIMENTO | B12: Jato de Plasma Full Face | C12: 300 | D12: -
A13: PROCEDIMENTO | B13: Jato de Plasma Pálpebras | C13: 150 | D13: -
A14: PROCEDIMENTO | B14: MMP Região - Avulso | C14: 45 | D14: 7.8
A15: PROCEDIMENTO | B15: MMP Alopécia Androgenética (6) | C15: 270 | D15: 46.8
A16: PROCEDIMENTO | B16: MMP Alopécia Areata em Placa (3) | C16: 135 | D16: 46.8
A17: PROCEDIMENTO | B17: MMP Alopécia Padrão Feminino (6) | C17: 270 | D17: 46.8
A18: PROCEDIMENTO | B18: MMP Bronc | C18: 45 | D18: 46.8
A19: PROCEDIMENTO | B19: MMP Capilar Avulsa | C19: 45 | D19: 46.8
A20: PROCEDIMENTO | B20: MMP Crescimento de Barba (5) | C20: 225 | D20: 46.8
A21: PROCEDIMENTO | B21: MMP Crescimento dos Fios (3) | C21: 135 | D21: 46.8
A22: PROCEDIMENTO | B22: MMP Dermatite Seborreica / Caspa / Prurido (3) | C22: 135 | D22: 46.8
A23: PROCEDIMENTO | B23: MMP Eflúvio Telógeno (geral) 6 | C23: 270 | D23: 46.8
A24: PROCEDIMENTO | B24: MMP Eflúvio Telógeno Pós-Parto (3) | C24: 135 | D24: 46.8
A25: PROCEDIMENTO | B25: MMP Eflúvio Telógeno Pós-Praia (3) | C25: 135 | D25: 46.8
... A28: PROCEDIMENTO | B28: MMP Mesoject | C28: 45 | D28: 46.8
A29: PROCEDIMENTO | B29: PDRN em Meso (Facial/Capilar) | C29: 45 | D29: -
A30: PROCEDIMENTO | B30: PRP | C30: 60 | D30: -
A31: PROCEDIMENTO | B31: Radiesse (1ª ampola) | C31: 60 | D31: 660
A32: PROCEDIMENTO | B32: Sculptra (1ª ampola) | C32: 60 | D32: 917
A33: PROCEDIMENTO | B33: Skinbooster (1 ampola) | C33: 30 | D33: -
A34: PROCEDIMENTO | B34: Toxina Botulinica - Masseter (Bruxismo) | C34: 30 | D34: 424.8
A35: PROCEDIMENTO | B35: Toxina Botulinica - Terço Superior | C35: 30 | D35: 566.4
A36: PROCEDIMENTO | B36: Toxina Botulinica - Pescoço | C36: 30 | D36: 424.8
A37: PROCEDIMENTO | B37: Toxina Botulinica - Axilas | C37: 30 | D37: 708
A38: PROCEDIMENTO | B38: Toxina Botulinica - Cefaleia | C38: 30 | D38: 424.8
A39: PROCEDIMENTO | B39: Toxina Botulinica - Full Face + pescoço | C39: 30 | D39: 991.2
A40: PROCEDIMENTO | B40: Toxina Botulinica - Palmas das Mãos | C40: 30 | D40: 424.8
A41: PROCEDIMENTO | B41: Toxina Botulinica - Peptídeo Botulínico (intradermoterapia) | C41: 45 | D41: 212.4
A42: PROCEDIMENTO | B42: Toxina Botulinica - Sorriso Gengival | C42: 30 | D42: 212.4
A43: PROCEDIMENTO | B43: Toxina Botulinica - Toxina Botulinica - Trapézio (Pescoço de Noiva) | C43: 30 | D43: 424.8
A44: PROCEDIMENTO | B44: Vitamina B12 (a cada 40 dias) | C44: 10 | D44: 25
A45: PROCEDIMENTO | B45: Tirzepatida | C45: 10 | D45: 1575
A46: PROCEDIMENTO | B46: CO2 | C46: 60 | D46: 566.67
A47: PROCEDIMENTO | B47: Clube do Botox | C47: 90 | D47: =566.4*3 -> 1699.2
A48: PROCEDIMENTO | B48: Vitamina D3 (4 unid./1 ano) | C48: 10 | D48: 12.84

Sheet TAXA
A1: FORMA DE PAGAMENTO | B1: TAXA ADM | C1: TAXA ANTECIPAÇÃO
A2: DEBITO | B2: 0.0155 | C2: 0
A3: CREDITO A VISTA | B3: 0.0283 | C3: 0
A4: CREDITO 1X | B4: 0.0283 | C4: 0
A5: CREDITO 2X | B5: 0.0313 | C5: 0
A6: CREDITO 3X | B6: 0.0313 | C6: 0
A7: CREDITO 4X | B7: 0.0313 | C7: 0
A8: CREDITO 5X | B8: 0.0313 | C8: 0
A9: CREDITO 6X | B9: 0.0313 | C9: 0
A10: DINHEIRO | B10: 0 | C10: 0 | D10: 0.0363 | E10: A PARTIR DE 6
A11: PIX | B11: 0 | C11: 0
A12: TED | B12: 0 | C12: 0
A13: CORTESIA | B13: 0 | C13: 0
A14: PARCERIA | B14: 0 | C14: 0
A15: RETORNO | B15: 0 | C15: 0
A16: CHEQUE | B16: 0 | C16: 0
A17: PAGO | B17: 0 | C17: 0
A18: EM ABERTO | B18: 0 | C18: 0

Sheet TECNOLOGIAS
B2: Mesojectium | F2: =B2 -> Mesojectium
B3: Investimento | C3: 29900 | F3: Capacidade
B4: Vida útil | C4: 60 | F4: 0.1 | G4: =C25*F4 -> 38400 | H4: 0.2 | I4: =C25*H4 -> 76800 | J4: 0.3 | K4: =C25*J4 -> 115200 | L4: 0.4 | M4: =C25*L4 -> 153600 | N4: 0.5 | O4: =C25*N4 -> 192000
B5: Depreciação mensal | C5: =($C$3-$C$6)/$C$4 -> 299 | F5: Quantidade | G5: =G4/C17 -> 32 | H5: Quantidade | I5: =I4/C17 -> 64 | J5: Quantidade | K5: =K4/C17 -> 96 | L5: Quantidade | M5: =M4/C17 -> 128 | N5: Quantidade | O5: =O4/C17 -> 160
B6: Valor residual | C6: =C3*40% -> 11960 | F6: Custo | G6: =(G5*(C12+C14+C13+C15))+C10 -> 16401.324 | H6: Custo | I6: =(I5*(C12+C14+C13+C15))+C10 -> 29829.804 | J6: Custo | K6: =(K5*(C12+C14+C13+C15))+C10 -> 43258.284 | L6: Custo | M6: =(M5*(C12+C14+C13+C15))+C10 -> 56686.764 | N6: Custo | O6: =(O5*(C12+C14+C13+C15))+C10 -> 70115.244
B7: Montante rentabilizado | C7: =FV(0.5%,C4,0,-C3,0) -> 40330.62 | F7: Impulsionamento | G7: 0 | H7: Impulsionamento | I7: 0 | J7: Impulsionamento | K7: 0 | L7: Impulsionamento | M7: 0 | N7: Impulsionamento | O7: 0
B8: Custo de oportunidade (0,5% a.m.) | C8: =$C$7-$C$3 -> 10430.62 | F8: Lucro | G8: =G4-(G6+G7) -> 21998.676 | H8: Lucro | I8: =I4-(I6+I7) -> 46970.196 | J8: Lucro | K8: =K4-(K6+K7) -> 71941.716 | L8: Lucro | M8: =M4-(M6+M7) -> 96913.236 | N8: Lucro | O8: =O4-(O6+O7) -> 121884.76
B9: Manutenção mensal | C9: 2500 | F9: 0.6 | G9: =C25*F9 -> 230400 | H9: 0.7 | I9: =C25*H9 -> 268800 | J9: 0.8 | K9: =C25*J9 -> 307200 | L9: 0.9 | M9: =C25*L9 -> 345600 | N9: 1 | O9: =C25*N9 -> 384000
B10: Custo mensal | C10: =(($C$7-$C$6)/$C$4)+$C$9 -> 2972.8437 | F10: Quantidade | G10: =G9/C17 -> 192 | H10: Quantidade | I10: =I9/C17 -> 224 | J10: Quantidade | K10: =K9/C17 -> 256 | L10: Quantidade | M10: =M9/C17 -> 288 | N10: Quantidade | O10: =O9/C17 -> 320
B11: Custo/procedimento | C11: =$C$10/$C$19 -> 212.34598 | F11: Custo | G11: =(G10*(C12+C14+C13+C15))+C10 -> 83543.724 | H11: Custo | I11: =(I10*(C12+C14+C13+C15))+C10 -> 96972.204 | J11: Custo | K11: =(K10*(C12+C14+C13+C15))+C10 -> 110400.68 | L11: Custo | M11: =(M10*(C12+C14+C13+C15))+C10 -> 123829.16 | N11: Custo | O11: =(O10*(C12+C14+C13+C15))+C10 -> 137257.64
B12: Custo do consumível | C12: 0 | F12: Impulsionamento | G12: 0 | H12: Impulsionamento | I12: 0 | J12: Impulsionamento | K12: 0 | L12: Impulsionamento | M12: 0 | N12: Impulsionamento | O12: 0
B13: Imposto + cartão | C13: =14.97%*C17 -> 179.64 | F13: Lucro | G13: =G9-(G11+G12) -> 146856.28 | H13: Lucro | I13: =I9-(I11+I12) -> 171827.8 | J13: Lucro | K13: =K9-(K11+K12) -> 196799.32 | L13: Lucro | M13: =M9-(M11+M12) -> 221770.84 | N13: Lucro | O13: =O9-(O11+O12) -> 246742.36
B14: Taxa de sala | C14: =8*C16 -> 240
B15: Mão de obra | C15: 0
B16: Duração média da SS | C16: 30 | G16: META TECNOLOGIA
B17: Valor médio da SS | C17: 1200
B18: Lucro por ss | C18: =$C$17-$C$13-$C$14-$C$12-$C$11 -> 568.01402 | G18: MÍNIMA | H18: IDEAL | I18: DESAFIO
B19: N° de procedimentos | C19: 14 | F19: Faturamento | G19: 0 | H19: =G19/0.7 -> 0 | I19: =H19*1.2 -> 0
B20: PE de procedimentos | C20: 14 | F20: Procedimentos | G20: =G19/C17 -> 0 | H20: =H19/C17 -> 0 | I20: =I19/C17 -> 0
B21: Faturamento | C21: =$C$19*$C$17 -> 16800 | F21: Lucro | G21: =($G$20*$C$17)-(($C$10/$G$20+$C$12+$C$14+$C$13+$C$15)*$G$20) -> #DIV/0! | H21: =($H$20*$C$17)-(($C$10/$H$20+$C$12+$C$14+$C$13+$C$15)*$H$20) -> #DIV/0! | I21: =($I$20*$C$17)-(($C$10/$I$20+$C$12+$C$14+$C$13+$C$15)*$I$20) -> #DIV/0!
B22: Total do custo variável | C22: =($C$11+$C$12+$C$14+$C$13+$C$15)*$C$19 -> 8847.8037 | F22: Lucro (%) | G22: =G21/G19 -> #DIV/0! | H22: =H21/H19 -> #DIV/0! | I22: =I21/I19 -> #DIV/0!
B23: Lucro final | C23: =$C$21-$C$22 -> 7952.1963 | F23: Horas | G23: =(G20*C16)/60 -> 0 | H23: =(H20*C16)/60 -> 0 | I23: =(I20*C16)/60 -> 0
B24: Ponto de equilíbrio | C24: 14 SESSÕES DE R$ 1.200,00 = R$ 110,23 DE LUCRO
B25: Capacidade de faturamento mensal | C25: =$C$26*$C$17 -> 384000
B26: Capacidade de procedimentos mensal | C26: =160/($C$16/60) -> 320
B28: =B2 -> Mesojectium
B29: Investimento | C29: =C3 -> 29900
B30: Vida útil | C30: 1
B31: Depreciação | C31: =($C$29-$C$32)/$C$30 -> 17940
B32: Valor residual | C32: =C6 -> 11960
B33: Montante rentabilizado | C33: =$C$7 -> 40330.62
B34: Custo de oportunidade (0,5% a.m.) | C34: =$C$33-$C$29 -> 10430.62
B35: Manutenção | C35: 0
B36: Custo total | C36: =(($C$33-$C$32)/$C$30)+$C$35 -> 28370.62
B37: Custo/procedimento | C37: =$C$36/$C$44 -> 28.283535 | D37: =$C$37*$C$44 -> 28370.62
B38: Custo do consumível | C38: =C12*C44 -> 0
B39: Imposto + cartão | C39: =C13*C44 -> 180193.11
B40: Taxa de sala | C40: =C14*C44 -> 240738.96
B41: Mão de obra | C41: =C15*C44 -> 0
B42: Duração média da SS | C42: =C16 -> 30
B43: Valor médio da SS | C43: =C17 -> 1200
B44: N° de procedimentos | C44: 1003.079
B45: PE de procedimentos | C45: 1004
B46: Faturamento | C46: =$C$44*$C$43 -> 1203694.8
B47: Total do custo variável | C47: =($C$37+$C$12+$C$14+$C$13+$C$15)*$C$44 -> 449302.69
B48: Lucro final | C48: =$C$46-$C$47 -> 754392.11
B49: Ponto de equilíbrio total | C49: 1004 sessões | D49: =1004/120 -> 8.3666667
B50: Capacidade de faturamento total | C50: =$C$25*C4 -> 23040000
B51: Capacidade de procedimentos total | C51: =$C$26*C4 -> 19200

Sheet PALETA
